Workbook

Sheet 0. Budget Summary
A1: 0. Budget Summary (다음 Sheet 입력 시 자동 생성)
A3: Protocol No: TTK-CS-101 | E3: Updated on:
A5: 1. Overall Status
B6: IQVIA | C6: Syneos | D6: Sharp | E6: Fisher | F6: Marken | G6: SBQ | H6: Aptamer | I6: Invivo | J6: Labconnect | K6: AIMS
B7: CRO CO | C7: Previous CRO CO 현 DMSTAT/PV: 예산은 CD팀에서 관리 | D7: Packaging, Delivery, Destruction, etc | E7: Packaging, Delivery, Destruction, etc | F7: IP Transpotation | G7: PK, SS1 & SS3 | H7: PK, SS2 & SS4 | I7: Biomarker, SS4 | J7: Lab Kit, SS4 | K7: Consulting
A8: Contracted | B8: ='[1]1. IQVIA '!B8 -> 15935420 | D8: ='[1]3. Sharp'!B8 -> 675051 | E8: ='[1]4. Fisher'!B8 -> 249693702 | F8: ='[1]5. Marken'!B8 -> 132368849 | G8: ='6. SBQ'!B8 -> 440404.83 | H8: ='7. Aptamer'!B8 -> 294600000 | I8: ='8. Invivo'!B8 -> 490894 | J8: ='9. Labconnect'!B8 -> 68277 | K8: ='10. AIMS'!B8 -> 367130000
A9: Paid | B9: ='[1]1. IQVIA '!B9 -> 3144815.9 | C9: ='2. Syneos'!B9 -> 0 | D9: ='[1]3. Sharp'!B9 -> 472838.16 | E9: ='[1]4. Fisher'!B9 -> 15142569 | F9: ='[1]5. Marken'!B9 -> 132368849 | G9: ='6. SBQ'!B9 -> 160795.18 | H9: ='7. Aptamer'!B9 -> 54450000 | I9: ='8. Invivo'!B9 -> 213142.36 | J9: ='9. Labconnect'!B9 -> 45962.23 | K9: ='10. AIMS'!B9 -> 250597600
A10: Remaining | B10: ='[1]1. IQVIA '!B10 -> 12790605 | D10: ='[1]3. Sharp'!B10 -> 202212.84 | E10: ='[1]4. Fisher'!B10 -> 234551133 | F10: ='[1]5. Marken'!B10 -> 0 | G10: ='6. SBQ'!B10 -> 279609.65 | H10: ='7. Aptamer'!B10 -> 240150000 | I10: ='8. Invivo'!B10 -> 277751.64 | J10: ='9. Labconnect'!B10 -> 22314.77 | K10: ='10. AIMS'!B10 -> 116532400
A11: % | B11: ='[1]1. IQVIA '!C10 -> 0.80265247 | D11: ='[1]3. Sharp'!C10 -> 0.29955194 | E11: ='[1]4. Fisher'!C10 -> 0.93935542 | F11: ='[1]5. Marken'!C10 -> 0 | G11: ='6. SBQ'!C10 -> 0.63489233 | H11: ='7. Aptamer'!C10 -> 0.81517312 | I11: ='8. Invivo'!C10 -> 0.56580777 | J11: ='9. Labconnect'!C10 -> 0.32682704 | K11: ='10. AIMS'!C10 -> 0.31741454
A13: 2. Yearly/Quarterly Plan and Payment Status
A14: Vendor | B14: Currency | C14: 2023 | N14: 2024 | Y14: 2025 | AJ14: 2026 | AU14: 2027
C15: 1Q (Jan~Mar) | E15: 2Q (Apr~Jun) | G15: 3Q (Jul~Sep) | I15: 4Q (Oct~Dec) | K15: 2023 | N15: 1Q (Jan~Mar) | P15: 2Q (Apr~Jun) | R15: 3Q (Jul~Sep) | T15: 4Q (Oct~Dec) | V15: 2024 | Y15: 1Q (Jan~Mar) | AA15: 2Q (Apr~Jun) | AC15: 3Q (Jul~Sep) | AE15: 4Q (Oct~Dec) | AG15: 2025 | AJ15: 1Q (Jan~Mar) | AL15: 2Q (Apr~Jun) | AN15: 3Q (Jul~Sep) | AP15: 4Q (Oct~Dec) | AR15: 2026 | AU15: 1Q (Jan~Mar) | AW15: 2Q (Apr~Jun) | AY15: 3Q (Jul~Sep) | BA15: 4Q (Oct~Dec) | BC15: 2027
C16: Planned | D16: Actual | E16: Planned | F16: Actual | G16: Planned | H16: Actual | I16: Planned | J16: Actual | K16: Planned | L16: Actual | M16: Delta (Δ) | N16: Planned | O16: Actual | P16: Planned | Q16: Actual | R16: Planned | S16: Actual | T16: Planned | U16: Actual | V16: Planned | W16: Actual | X16: Delta (Δ) | Y16: Planned | Z16: Actual | AA16: Planned | AB16: Actual | AC16: Planned | AD16: Actual | AE16: Planned | AF16: Actual | AG16: Planned | AH16: Actual | AI16: Delta (Δ) | AJ16: Planned | AK16: Actual | AL16: Planned | AM16: Actual | AN16: Planned | AO16: Actual | AP16: Planned | AQ16: Actual | AR16: Planned | AS16: Actual | AT16: Delta (Δ) | AU16: Planned | AV16: Actual | AW16: Planned | AX16: Actual | AY16: Planned | AZ16: Actual | BA16: Planned | BB16: Actual | BC16: Planned | BD16: Actual | BE16: Delta (Δ)
A17: CRO(IQVIA) | B17: USD | K17: =C17+E17+G17+I17 -> 0 | L17: =D17+F17+H17+J17 -> 0 | M17: =K17-L17 -> 0 | O17: ='1. IQVIA '!A16+'1. IQVIA '!B16+'1. IQVIA '!C16 -> 0 | Q17: ='1. IQVIA '!D16+'1. IQVIA '!E16+'1. IQVIA '!F16 -> 0 | S17: ='1. IQVIA '!G16+'1. IQVIA '!H16+'1. IQVIA '!I16 -> 297156.95 | U17: ='1. IQVIA '!J16+'1. IQVIA '!K16+'1. IQVIA '!L16 -> 2772764 | V17: =N17+P17+R17+T17 -> 0 | W17: =O17+Q17+S17+U17 -> 3069920.9 | X17: =V17-W17 -> -3069920.9 | Z17: ='1. IQVIA '!A21+'1. IQVIA '!B21+'1. IQVIA '!C21 -> 34695.35 | AB17: ='1. IQVIA '!D21+'1. IQVIA '!E21+'1. IQVIA '!F21 -> 656709.24 | AD17: ='1. IQVIA '!G21+'1. IQVIA '!H21+'1. IQVIA '!I21 -> 829858.16 | AE17: 772849 | AF17: ='1. IQVIA '!J21+'1. IQVIA '!K21+'1. IQVIA '!L21 -> 2380983.1 | AG17: =Y17+AA17+AC17+AE17 -> 772849 | AH17: =Z17+AB17+AD17+AF17 -> 3902245.9 | AI17: =AG17-AH17 -> -3129396.9 | AJ17: 1050743 | AK17: ='1. IQVIA '!A26+'1. IQVIA '!B26+'1. IQVIA '!C26 -> 1305306.7 | AL17: 437810 | AM17: ='1. IQVIA '!D26+'1. IQVIA '!E26+'1. IQVIA '!F26 -> 1431538.8 | AN17: 437810 | AO17: ='1. IQVIA '!G26+'1. IQVIA '!H26+'1. IQVIA '!I26 -> 134077.92 | AP17: 350243 | AQ17: ='1. IQVIA '!J26+'1. IQVIA '!K26+'1. IQVIA '!L26 -> 0 | AR17: =AJ17+AL17+AN17+AP17 -> 2276606 | AS17: =AK17+AM17+AO17+AQ17 -> 2870923.4 | AT17: =AR17-AS17 -> -594317.44 | AU17: 350243 | AV17: ='1. IQVIA '!A31+'1. IQVIA '!B31+'1. IQVIA '!C31 -> 0 | AW17: 262686 | AX17: ='1. IQVIA '!D31+'1. IQVIA '!E31+'1. IQVIA '!F31 -> 0 | AZ17: ='1. IQVIA '!G31+'1. IQVIA '!H31+'1. IQVIA '!I31 -> 0 | BB17: ='1. IQVIA '!J31+'1. IQVIA '!K31+'1. IQVIA '!L31 -> 0 | BC17: =AU17+AW17+AY17+BA17 -> 612929 | BD17: =AV17+AX17+AZ17+BB17 -> 0 | BE17: =BC17-BD17 -> 612929
A18: CRO(Syneos) | B18: USD | D18: ='2. Syneos'!A16+'2. Syneos'!B16+'2. Syneos'!C16 -> 0 | F18: ='2. Syneos'!D16+'2. Syneos'!E16+'2. Syneos'!F16 -> 0 | H18: ='2. Syneos'!G16+'2. Syneos'!H16+'2. Syneos'!I16 -> 0 | J18: ='2. Syneos'!J16+'2. Syneos'!K16+'2. Syneos'!L16 -> 0 | K18: =C18+E18+G18+I18 -> 0 | L18: =D18+F18+H18+J18 -> 0 | M18: =K18-L18 -> 0 | O18: ='2. Syneos'!A21+'2. Syneos'!B21+'2. Syneos'!C21 -> 0 | Q18: ='2. Syneos'!D21+'2. Syneos'!E21+'2. Syneos'!F21 -> 0 | S18: ='2. Syneos'!G21+'2. Syneos'!H21+'2. Syneos'!I21 -> 0 | U18: ='2. Syneos'!J21+'2. Syneos'!K21+'2. Syneos'!L21 -> 0 | V18: =N18+P18+R18+T18 -> 0 | W18: =O18+Q18+S18+U18 -> 0 | X18: =V18-W18 -> 0 | Z18: ='2. Syneos'!A26+'2. Syneos'!B26+'2. Syneos'!C26 -> 0 | AB18: ='2. Syneos'!D26+'2. Syneos'!E26+'2. Syneos'!F26 -> 0 | AD18: ='2. Syneos'!G26+'2. Syneos'!H26+'2. Syneos'!I26 -> 0 | AE18: 364505 | AF18: ='2. Syneos'!J26+'2. Syneos'!K26+'2. Syneos'!L26 -> 0 | AG18: =Y18+AA18+AC18+AE18 -> 364505 | AH18: =Z18+AB18+AD18+AF18 -> 0 | AI18: =AG18-AH18 -> 364505 | AJ18: 543464 | AK18: ='2. Syneos'!A31+'2. Syneos'!B31+'2. Syneos'!C31 -> 0 | AL18: 452886 | AM18: ='2. Syneos'!D31+'2. Syneos'!E31+'2. Syneos'!F31 -> 0 | AN18: 377405 | AO18: ='2. Syneos'!G31+'2. Syneos'!H31+'2. Syneos'!I31 -> 0 | AP18: 314504 | AQ18: ='2. Syneos'!J31+'2. Syneos'!K31+'2. Syneos'!L31 -> 0 | AR18: =AJ18+AL18+AN18+AP18 -> 1688259 | AS18: =AK18+AM18+AO18+AQ18 -> 0 | AT18: =AR18-AS18 -> 1688259 | AU18: 262087 | AV18: ='2. Syneos'!A36+'2. Syneos'!B36+'2. Syneos'!C36 -> 0 | AX18: ='2. Syneos'!D36+'2. Syneos'!E36+'2. Syneos'!F36 -> 0 | AY18: 262087 | AZ18: ='2. Syneos'!G36+'2. Syneos'!H36+'2. Syneos'!I36 -> 0 | BB18: ='2. Syneos'!J36+'2. Syneos'!K36+'2. Syneos'!L36 -> 0 | BC18: =AU18+AY18+BA18 -> 524174 | BD18: =AV18+AX18+AZ18+BB18 -> 0 | BE18: =BC18-BD18 -> 524174
A19: Sharp | B19: USD | D19: ='[1]3. Sharp'!A15+'[1]3. Sharp'!B15+'[1]3. Sharp'!C15 -> 12267 | F19: ='[1]3. Sharp'!D15+'[1]3. Sharp'!E15+'[1]3. Sharp'!F15 -> 16333.47 | H19: ='[1]3. Sharp'!G15+'[1]3. Sharp'!H15+'[1]3. Sharp'!I15 -> 46052.33 | J19: ='[1]3. Sharp'!J15+'[1]3. Sharp'!K15+'[1]3. Sharp'!L15 -> 20282.86 | K19: =C19+E19+G19+I19 -> 0 | L19: =D19+F19+H19+J19 -> 94935.66 | M19: =K19-L19 -> -94935.66 | O19: ='[1]3. Sharp'!A20+'[1]3. Sharp'!B20+'[1]3. Sharp'!C20 -> 7522.83 | Q19: ='[1]3. Sharp'!D20+'[1]3. Sharp'!E20+'[1]3. Sharp'!F20 -> 49874.57 | S19: ='[1]3. Sharp'!G20+'[1]3. Sharp'!H20+'[1]3. Sharp'!I20 -> 41664.66 | U19: ='[1]3. Sharp'!J20+'[1]3. Sharp'!K20+'[1]3. Sharp'!L20 -> 31336.49 | V19: =N19+P19+R19+T19 -> 0 | W19: =O19+Q19+S19+U19 -> 130398.55 | X19: =V19-W19 -> -130398.55 | Z19: ='[1]3. Sharp'!A25+'[1]3. Sharp'!B25+'[1]3. Sharp'!C25 -> 25424.65 | AB19: ='[1]3. Sharp'!D25+'[1]3. Sharp'!E25+'[1]3. Sharp'!F25 -> 68361.41 | AD19: ='[1]3. Sharp'!G25+'[1]3. Sharp'!H25+'[1]3. Sharp'!I25 -> 100122.42 | AF19: ='[1]3. Sharp'!J25+'[1]3. Sharp'!K25+'[1]3. Sharp'!L25 -> 53595.47 | AG19: =Y19+AA19+AC19+AE19 -> 0 | AH19: =Z19+AB19+AD19+AF19 -> 247503.95 | AI19: =AG19-AH19 -> -247503.95 | AK19: ='[1]3. Sharp'!A30+'[1]3. Sharp'!B30+'[1]3. Sharp'!C30 -> 0 | AM19: ='[1]3. Sharp'!D30+'[1]3. Sharp'!E30+'[1]3. Sharp'!F30 -> 0 | AO19: ='[1]3. Sharp'!G30+'[1]3. Sharp'!H30+'[1]3. Sharp'!I30 -> 0 | AQ19: ='[1]3. Sharp'!J30+'[1]3. Sharp'!K30+'[1]3. Sharp'!L30 -> 0 | AR19: =AJ19+AL19+AN19+AP19 -> 0 | AS19: =AK19+AM19+AO19+AQ19 -> 0 | AT19: =AR19-AS19 -> 0 | AV19: ='[1]3. Sharp'!A35+'[1]3. Sharp'!B35+'[1]3. Sharp'!C35 -> 0 | AX19: ='[1]3. Sharp'!D35+'[1]3. Sharp'!E35+'[1]3. Sharp'!F35 -> 0 | AZ19: ='[1]3. Sharp'!G35+'[1]3. Sharp'!H35+'[1]3. Sharp'!I35 -> 0 | BB19: ='[1]3. Sharp'!J35+'[1]3. Sharp'!K35+'[1]3. Sharp'!L35 -> 0 | BC19: =AU19+AW18+AY19+BA19 -> 0 | BD19: =AV19+AX19+AZ19+BB19 -> 0 | BE19: =BC19-BD19 -> 0
A20: Fisher | B20: KRW | K20: =C20+E20+G20+I20 -> 0 | L20: =D20+F20+H20+J20 -> 0 | M20: =K20-L20 -> 0 | V20: =N20+P20+R20+T20 -> 0 | W20: =O20+Q20+S20+U20 -> 0 | X20: =V20-W20 -> 0 | Z20: ='[1]4. Fisher'!A17+'[1]4. Fisher'!B17+'[1]4. Fisher'!C17 -> 0 | AB20: ='[1]4. Fisher'!D17+'[1]4. Fisher'!E17+'[1]4. Fisher'!F17 -> 0 | AD20: ='[1]4. Fisher'!G17+'[1]4. Fisher'!H17+'[1]4. Fisher'!I17 -> 4838959 | AF20: ='[1]4. Fisher'!J17+'[1]4. Fisher'!K17+'[1]4. Fisher'!L17 -> 10303610 | AG20: =Y20+AA20+AC20 -> 0 | AH20: =Z20+AB20+AD20 -> 4838959 | AI20: =AG20-AH20 -> -4838959 | AK20: ='[1]4. Fisher'!A22+'[1]4. Fisher'!B22+'[1]4. Fisher'!C22 -> 0 | AM20: ='[1]4. Fisher'!D22+'[1]4. Fisher'!E22+'[1]4. Fisher'!F22 -> 0 | AO20: ='[1]4. Fisher'!G22+'[1]4. Fisher'!H22+'[1]4. Fisher'!I22 -> 0 | AQ20: ='[1]4. Fisher'!J22+'[1]4. Fisher'!K22+'[1]4. Fisher'!L22 -> 0 | AR20: =AJ20+AL20+AN20 -> 0 | AS20: =AK20+AM20+AO20 -> 0 | AT20: =AR20-AS20 -> 0 | AV20: ='[1]4. Fisher'!A27+'[1]4. Fisher'!B27+'[1]4. Fisher'!C27 -> 0 | AX20: ='[1]4. Fisher'!D27+'[1]4. Fisher'!E27+'[1]4. Fisher'!F27 -> 0 | AZ20: ='[1]4. Fisher'!G27+'[1]4. Fisher'!H27+'[1]4. Fisher'!I27 -> 0 | BB20: ='[1]4. Fisher'!J27+'[1]4. Fisher'!K27+'[1]4. Fisher'!L27 -> 0 | BC20: =AU20+AW20+AY20 -> 0 | BD20: =AV20+AX20+AZ20 -> 0 | BE20: =BC20-BD20 -> 0
A21: Marken | B21: KRW | D21: ='[1]5. Marken'!A17+'[1]5. Marken'!B17+'[1]5. Marken'!C17 -> 0 | F21: ='[1]5. Marken'!D17+'[1]5. Marken'!E17+'[1]5. Marken'!F17 -> 6832940 | H21: ='[1]5. Marken'!G17+'[1]5. Marken'!H17+'[1]5. Marken'!I17 -> 42000 | J21: ='[1]5. Marken'!J17+'[1]5. Marken'!K17+'[1]5. Marken'!L17 -> 0 | K21: =C21+E21+G21+I21 -> 0 | L21: =D21+F21+H21+J21 -> 6874940 | M21: =K21-L21 -> -6874940 | O21: ='[1]5. Marken'!A22+'[1]5. Marken'!B22+'[1]5. Marken'!C22 -> 0 | Q21: ='[1]5. Marken'!D22+'[1]5. Marken'!E22+'[1]5. Marken'!F22 -> 29201942 | S21: ='[1]5. Marken'!G22+'[1]5. Marken'!H22+'[1]5. Marken'!I22 -> 0 | U21: ='[1]5. Marken'!J22+'[1]5. Marken'!K22+'[1]5. Marken'!L22 -> 10670790 | V21: =N21+P21+R21+T21 -> 0 | W21: =O21+Q21+S21+U21 -> 39872732 | X21: =V21-W21 -> -39872732 | Z21: ='[1]5. Marken'!A27+'[1]5. Marken'!B27+'[1]5. Marken'!C27 -> 0 | AB21: ='[1]5. Marken'!D27+'[1]5. Marken'!E27+'[1]5. Marken'!F27 -> 2942881 | AD21: ='[1]5. Marken'!G27+'[1]5. Marken'!H27+'[1]5. Marken'!I27 -> 39794243 | AF21: ='[1]5. Marken'!J27+'[1]5. Marken'!K27+'[1]5. Marken'!L27 -> 42884053 | AG21: =Y21+AA21+AC21+AE21 -> 0 | AH21: =Z21+AB21+AD21+AF21 -> 85621177 | AI21: =AG21-AH21 -> -85621177 | AK21: ='[1]5. Marken'!A32+'[1]5. Marken'!B32+'[1]5. Marken'!C32 -> 0 | AM21: ='[1]5. Marken'!D32+'[1]5. Marken'!E32+'[1]5. Marken'!F32 -> 0 | AO21: ='[1]5. Marken'!G32+'[1]5. Marken'!H32+'[1]5. Marken'!I32 -> 0 | AQ21: ='[1]5. Marken'!J32+'[1]5. Marken'!K32+'[1]5. Marken'!L32 -> 0 | AR21: =AJ21+AL21+AN21+AP21 -> 0 | AS21: =AK21+AM21+AO21+AQ21 -> 0 | AT21: =AR21-AS21 -> 0 | AV21: ='[1]5. Marken'!A37+'[1]5. Marken'!B37+'[1]5. Marken'!C37 -> 0 | AX21: ='[1]5. Marken'!D37+'[1]5. Marken'!E37+'[1]5. Marken'!F37 -> 0 | AZ21: ='[1]5. Marken'!G37+'[1]5. Marken'!H37+'[1]5. Marken'!I37 -> 0 | BB21: ='[1]5. Marken'!J37+'[1]5. Marken'!K37+'[1]5. Marken'!L37 -> 0 | BC21: =AU21+AW21+AY21+BA21 -> 0 | BD21: =AV21+AX21+AZ21+BB21 -> 0 | BE21: =BC21-BD21 -> 0
A22: SBQ | B22: CHF | D22: ='6. SBQ'!A16+'6. SBQ'!B16+'6. SBQ'!C16 -> 67333.98 | F22: ='6. SBQ'!D16+'6. SBQ'!E16+'6. SBQ'!F16 -> 0 | H22: ='6. SBQ'!G16+'6. SBQ'!H16+'6. SBQ'!I16 -> 1968 | J22: ='6. SBQ'!J16+'6. SBQ'!K16+'6. SBQ'!L16 -> 0 | K22: =C22+E22+G22+I22 -> 0 | L22: =D22+F22+H22+J22 -> 69301.98 | M22: =K22-L22 -> -69301.98 | O22: ='6. SBQ'!A21+'6. SBQ'!B21+'6. SBQ'!C21 -> 0 | Q22: ='6. SBQ'!D21+'6. SBQ'!E21+'6. SBQ'!F21 -> 0 | S22: ='6. SBQ'!G21+'6. SBQ'!H21+'6. SBQ'!I21 -> 0 | U22: ='6. SBQ'!J21+'6. SBQ'!K21+'6. SBQ'!L21 -> 4750 | V22: =N22+P22+R22+T22 -> 0 | W22: =O22+Q22+S22+U22 -> 4750 | X22: =V22-W22 -> -4750 | Z22: ='6. SBQ'!A26+'6. SBQ'!B26+'6. SBQ'!C26 -> 6213.6 | AB22: ='6. SBQ'!D26+'6. SBQ'!E26+'6. SBQ'!F26 -> 70413.6 | AD22: ='6. SBQ'!G26+'6. SBQ'!H26+'6. SBQ'!I26 -> 0 | AF22: ='6. SBQ'!J26+'6. SBQ'!K26+'6. SBQ'!L26 -> 0 | AG22: =Y22+AA22+AC22+AE22 -> 0 | AH22: =Z22+AB22+AD22+AF22 -> 76627.2 | AI22: =AG22-AH22 -> -76627.2 | AJ22: 50182 | AK22: ='6. SBQ'!A31+'6. SBQ'!B31+'6. SBQ'!C31 -> 0 | AL22: 50182 | AM22: ='6. SBQ'!D31+'6. SBQ'!E31+'6. SBQ'!F31 -> 10116 | AN22: 50182 | AO22: ='6. SBQ'!G31+'6. SBQ'!H31+'6. SBQ'!I31 -> 0 | AP22: 50182 | AQ22: ='6. SBQ'!J31+'6. SBQ'!K31+'6. SBQ'!L31 -> 0 | AR22: =AJ22+AL22+AN22+AP22 -> 200728 | AS22: =AK22+AM22+AO22+AQ22 -> 10116 | AT22: =AR22-AS22 -> 190612 | AU22: 50182 | AV22: ='6. SBQ'!A36+'6. SBQ'!B36+'6. SBQ'!C36 -> 0 | AW22: 50182 | AX22: ='6. SBQ'!D36+'6. SBQ'!E36+'6. SBQ'!F36 -> 0 | AY22: 50182 | AZ22: ='6. SBQ'!G36+'6. SBQ'!H36+'6. SBQ'!I36 -> 0 | BA22: 50182 | BB22: ='6. SBQ'!J36+'6. SBQ'!K36+'6. SBQ'!L36 -> 0 | BC22: =AU22+AW22+AY22+BA22 -> 200728 | BD22: =AV22+AX22+AZ22+BB22 -> 0 | BE22: =BC22-BD22 -> 200728
A23: Aptamer | B23: KRW | K23: =C23+E23+G23+I23 -> 0 | L23: =D23+F23+H23+J23 -> 0 | M23: =K23-L23 -> 0 | V23: =N23+P23+R23+T23 -> 0 | W23: =O23+Q23+S23+U23 -> 0 | X23: =V23-W23 -> 0 | Z23: ='7. Aptamer'!A16+'7. Aptamer'!B16+'7. Aptamer'!C16 -> 0 | AB23: ='7. Aptamer'!D16+'7. Aptamer'!E16+'7. Aptamer'!F16 -> 14190000 | AD23: ='7. Aptamer'!G16+'7. Aptamer'!H16+'7. Aptamer'!I16 -> 0 | AE23: 36600000 | AF23: ='7. Aptamer'!J16+'7. Aptamer'!K16+'7. Aptamer'!L16 -> 40260000 | AG23: =Y23+AA23+AC23+AE23 -> 36600000 | AH23: =Z23+AB23+AD23+AF23 -> 54450000 | AI23: =AG23-AH23 -> -17850000 | AJ23: 33777000 | AK23: ='7. Aptamer'!A20+'7. Aptamer'!B20+'7. Aptamer'!C20 -> 0 | AL23: 59577000 | AM23: ='7. Aptamer'!D20+'7. Aptamer'!E20+'7. Aptamer'!F20 -> 0 | AN23: 43377000 | AO23: ='7. Aptamer'!G20+'7. Aptamer'!H20+'7. Aptamer'!I20 -> 0 | AP23: 28377000 | AQ23: ='7. Aptamer'!J20+'7. Aptamer'!K20+'7. Aptamer'!L20 -> 0 | AR23: =AJ23+AL23+AN23+AP23 -> 165108000 | AS23: =AK23+AM23+AO23+AQ23 -> 0 | AT23: =AR23-AS23 -> 165108000 | AU23: 35154000 | AV23: ='7. Aptamer'!A24+'7. Aptamer'!B24+'7. Aptamer'!C24 -> 0 | AW23: 38700000 | AX23: ='7. Aptamer'!D24+'7. Aptamer'!E24+'7. Aptamer'!F24 -> 0 | AZ23: ='7. Aptamer'!G24+'7. Aptamer'!H24+'7. Aptamer'!I24 -> 0 | BB23: ='7. Aptamer'!J24+'7. Aptamer'!K24+'7. Aptamer'!L24 -> 0 | BC23: =AU23+AW23+AY23+BA23 -> 73854000 | BD23: =AV23+AX23+AZ23+BB23 -> 0 | BE23: =BC23-BD23 -> 73854000
A24: Invivo | B24: USD | K24: =C24+E24+G24+I24 -> 0 | L24: =D24+F24+H24+J24 -> 0 | M24: =K24-L24 -> 0 | V24: =N24+P24+R24+T24 -> 0 | W24: =O24+Q24+S24+U24 -> 0 | X24: =V24-W24 -> 0 | Z24: ='8. Invivo'!A16+'8. Invivo'!B16+'8. Invivo'!C16 -> 0 | AB24: ='8. Invivo'!D16+'8. Invivo'!E16+'8. Invivo'!F16 -> 0 | AD24: ='8. Invivo'!G16+'8. Invivo'!H16+'8. Invivo'!I16 -> 166689 | AE24: 10499 | AF24: ='8. Invivo'!J16+'8. Invivo'!K16+'8. Invivo'!L16 -> 17748.87 | AG24: =Y24+AA24+AC24+AE24 -> 10499 | AH24: =Z24+AB24+AD24+AF24 -> 184437.87 | AI24: =AG24-AH24 -> -173938.87 | AJ24: 15748 | AK24: ='8. Invivo'!A21+'8. Invivo'!B21+'8. Invivo'!C21 -> 13484.15 | AL24: 15748 | AM24: ='8. Invivo'!D21+'8. Invivo'!E21+'8. Invivo'!F21 -> 15220.34 | AN24: 15748 | AO24: ='8. Invivo'!G21+'8. Invivo'!H21+'8. Invivo'!I21 -> 0 | AP24: 15748 | AQ24: ='8. Invivo'!J21+'8. Invivo'!K21+'8. Invivo'!L21 -> 0 | AR24: =AJ24+AL24+AN24+AP24 -> 62992 | AS24: =AK24+AM24+AO24+AQ24 -> 28704.49 | AT24: =AR24-AS24 -> 34287.51 | AU24: 20998 | AV24: ='8. Invivo'!A26+'8. Invivo'!B26+'8. Invivo'!C26 -> 0 | AX24: ='8. Invivo'!D26+'8. Invivo'!E26+'8. Invivo'!F26 -> 0 | AZ24: ='8. Invivo'!G26+'8. Invivo'!H26+'8. Invivo'!I26 -> 0 | BB24: ='8. Invivo'!J26+'8. Invivo'!K26+'8. Invivo'!L26 -> 0 | BC24: =AU24+AW24+AY24+BA24 -> 20998 | BD24: =AV24+AX24+AZ24+BB24 -> 0 | BE24: =BC24-BD24 -> 20998
A25: Labconnect | B25: USD | K25: =C25+E25+G25+I25 -> 0 | L25: =D25+F25+H25+J25 -> 0 | M25: =K25-L25 -> 0 | V25: =N25+P25+R25+T25 -> 0 | W25: =O25+Q25+S25+U25 -> 0 | X25: =V25-W25 -> 0 | Z25: ='9. Labconnect'!A16+'9. Labconnect'!B16+'9. Labconnect'!C16 -> 0 | AB25: ='9. Labconnect'!D16+'9. Labconnect'!E16+'9. Labconnect'!F16 -> 0 | AD25: ='9. Labconnect'!G16+'9. Labconnect'!H16+'9. Labconnect'!I16 -> 45130 | AE25: 5413 | AF25: ='9. Labconnect'!J16+'9. Labconnect'!K16+'9. Labconnect'!L16 -> 832.23 | AG25: =Y25+AA25+AC25+AE25 -> 5413 | AH25: =Z25+AB25+AD25+AF25 -> 45962.23 | AI25: =AG25-AH25 -> -40549.23 | AJ25: 8120 | AK25: ='9. Labconnect'!A21+'9. Labconnect'!B21+'9. Labconnect'!C21 -> 0 | AL25: 8120 | AM25: ='9. Labconnect'!D21+'9. Labconnect'!E21+'9. Labconnect'!F21 -> 0 | AN25: 8120 | AO25: ='9. Labconnect'!G21+'9. Labconnect'!H21+'9. Labconnect'!I21 -> 0 | AP25: 8120 | AQ25: ='9. Labconnect'!J21+'9. Labconnect'!K21+'9. Labconnect'!L21 -> 0 | AR25: =AJ25+AL25+AN25+AP25 -> 32480 | AS25: =AK25+AM25+AO25+AQ25 -> 0 | AT25: =AR25-AS25 -> 32480 | AU25: 10826 | AV25: ='9. Labconnect'!A26+'9. Labconnect'!B26+'9. Labconnect'!C26 -> 0 | AX25: ='9. Labconnect'!D26+'9. Labconnect'!E26+'9. Labconnect'!F26 -> 0 | AZ25: ='9. Labconnect'!G26+'9. Labconnect'!H26+'9. Labconnect'!I26 -> 0 | BB25: ='9. Labconnect'!J26+'9. Labconnect'!K26+'9. Labconnect'!L26 -> 0 | BC25: =AU25+AW25+AY25+BA25 -> 10826 | BD25: =AV25+AX25+AZ25+BB25 -> 0 | BE25: =BC25-BD25 -> 10826
A26: AIMS | B26: KRW | D26: ='10. AIMS'!A16+'10. AIMS'!B16+'10. AIMS'!C16 -> 0 | F26: ='10. AIMS'!D16+'10. AIMS'!E16+'10. AIMS'!F16 -> 0 | H26: ='10. AIMS'!G16+'10. AIMS'!H16+'10. AIMS'!I16 -> 0 | J26: ='10. AIMS'!J16+'10. AIMS'!K16+'10. AIMS'!L16 -> 23650000 | K26: =C26+E26+G26+I26 -> 0 | L26: =D26+F26+H26+J26 -> 23650000 | M26: =K26-L26 -> -23650000 | O26: ='10. AIMS'!A20+'10. AIMS'!B20+'10. AIMS'!C20 -> 0 | Q26: ='10. AIMS'!D20+'10. AIMS'!E20+'10. AIMS'!F20 -> 0 | S26: ='10. AIMS'!G20+'10. AIMS'!H20+'10. AIMS'!I20 -> 53399500 | U26: ='10. AIMS'!J20+'10. AIMS'!K20+'10. AIMS'!L20 -> 46695000 | V26: =N26+P26+R26+T26 -> 0 | W26: =O26+Q26+S26+U26 -> 100094500 | X26: =V26-W26 -> -100094500 | Z26: ='10. AIMS'!A24+'10. AIMS'!B24+'10. AIMS'!C24 -> 50160000 | AB26: ='10. AIMS'!D24+'10. AIMS'!E24+'10. AIMS'!F24 -> 23650000 | AD26: ='10. AIMS'!G24+'10. AIMS'!H24+'10. AIMS'!I24 -> 0 | AF26: ='10. AIMS'!J24+'10. AIMS'!K24+'10. AIMS'!L24 -> 44067100 | AG26: =Y26+AA26+AC26+AE26 -> 0 | AH26: =Z26+AB26+AD26+AF26 -> 117877100 | AI26: =AG26-AH26 -> -117877100 | AJ26: 33000000 | AK26: ='10. AIMS'!A28+'10. AIMS'!B28+'10. AIMS'!C28 -> 8976000 | AM26: ='10. AIMS'!D28+'10. AIMS'!E28+'10. AIMS'!F28 -> 0 | AN26: 9075000 | AO26: ='10. AIMS'!G28+'10. AIMS'!H28+'10. AIMS'!I28 -> 0 | AQ26: ='10. AIMS'!J28+'10. AIMS'!K28+'10. AIMS'!L28 -> 0 | AR26: =AJ26+AL26+AN26+AP26 -> 42075000 | AS26: =AK26+AM26+AO26+AQ26 -> 8976000 | AT26: =AR26-AS26 -> 33099000 | AU26: 12500000 | AV26: ='10. AIMS'!A32+'10. AIMS'!B32+'10. AIMS'!C32 -> 0 | AW26: 12500000 | AX26: ='10. AIMS'!D32+'10. AIMS'!E32+'10. AIMS'!F32 -> 0 | AY26: 12500000 | AZ26: ='10. AIMS'!G32+'10. AIMS'!H32+'10. AIMS'!I32 -> 0 | BA26: 12500000 | BB26: ='10. AIMS'!J32+'10. AIMS'!K32+'10. AIMS'!L32 -> 0 | BC26: =AU26+AW26+AY26+BA26 -> 50000000 | BD26: =AV26+AX26+AZ26+BB26 -> 0 | BE26: =BC26-BD26 -> 50000000
A30: Total (KRW) | B30: KRW | C30: =SUMIF($B$17:$B$29,$B30,C$17:C$29) -> 0 | D30: =SUMIF($B$17:$B$29,$B30,D$17:D$29) -> 0 | E30: =SUMIF($B$17:$B$29,$B30,E$17:E$29) -> 0 | F30: =SUMIF($B$17:$B$29,$B30,F$17:F$29) -> 6832940 | G30: =SUMIF($B$17:$B$29,$B30,G$17:G$29) -> 0 | H30: =SUMIF($B$17:$B$29,$B30,H$17:H$29) -> 42000 | I30: =SUMIF($B$17:$B$29,$B30,I$17:I$29) -> 0 | J30: =SUMIF($B$17:$B$29,$B30,J$17:J$29) -> 23650000 | ... BE30: =SUMIF($B$17:$B$29,$B30,BE$17:BE$29) -> 123854000
A31: Total (USD) | B31: USD | C31: =SUMIF($B$17:$B$29,$B31,C$17:C$29) -> 0 | D31: =SUMIF($B$17:$B$29,$B31,D$17:D$29) -> 12267 | E31: =SUMIF($B$17:$B$29,$B31,E$17:E$29) -> 0 | F31: =SUMIF($B$17:$B$29,$B31,F$17:F$29) -> 16333.47 | G31: =SUMIF($B$17:$B$29,$B31,G$17:G$29) -> 0 | H31: =SUMIF($B$17:$B$29,$B31,H$17:H$29) -> 46052.33 | I31: =SUMIF($B$17:$B$29,$B31,I$17:I$29) -> 0 | J31: =SUMIF($B$17:$B$29,$B31,J$17:J$29) -> 20282.86 | ... BE31: =SUMIF($B$17:$B$29,$B31,BE$17:BE$29) -> 1168927
A32: Total (CHF) | B32: CHF | C32: =SUMIF($B$17:$B$29,$B32,C$17:C$29) -> 0 | D32: =SUMIF($B$17:$B$29,$B32,D$17:D$29) -> 67333.98 | E32: =SUMIF($B$17:$B$29,$B32,E$17:E$29) -> 0 | F32: =SUMIF($B$17:$B$29,$B32,F$17:F$29) -> 0 | G32: =SUMIF($B$17:$B$29,$B32,G$17:G$29) -> 0 | H32: =SUMIF($B$17:$B$29,$B32,H$17:H$29) -> 1968 | I32: =SUMIF($B$17:$B$29,$B32,I$17:I$29) -> 0 | J32: =SUMIF($B$17:$B$29,$B32,J$17:J$29) -> 0 | ... BE32: =SUMIF($B$17:$B$29,$B32,BE$17:BE$29) -> 200728

Sheet 1. IQVIA 
A1: 1. CRO: IQVIA | F1: 1-1, 1-2 입력 시 자동 기입되는 페이지
B2: Contract Number: | C2: LAB97701 | D2: Version & date: | E2: CO1_23Sep2025
A4: Protocol No: TTK-CS-101 | D4: Updated on:
A6: 1. Total Payment Status
A7: Category | B7: $ | C7: %
A8: Budget | B8: 15935420
A9: Paid | B9: ='1-1. Direct'!B9+'1-2. PTC'!B10 -> 7387992.2 | C9: =B9/B8 -> 0.46362079
A10: Remaining | B10: =B8-B9 -> 8547428.3 | C10: =B10/B8 -> 0.53637921
A12: 2. Total Yearly and Monthly Payment
B13: USD | C13: KRW
A14: 2024 | B14: =SUM(A16:L16) -> 3069920.9 | C14: =SUM(A17:L17) -> 652255797
A15: 01 | B15: 02 | C15: 03 | D15: 04 | E15: 05 | F15: 06 | G15: 07 | H15: 08 | I15: 09 | J15: 10 | K15: 11 | L15: 12
A16: ='1-1. Direct'!A16+'1-2. PTC'!A17 -> 0 | B16: ='1-1. Direct'!B16+'1-2. PTC'!B17 -> 0 | C16: ='1-1. Direct'!C16+'1-2. PTC'!C17 -> 0 | D16: ='1-1. Direct'!D16+'1-2. PTC'!D17 -> 0 | E16: ='1-1. Direct'!E16+'1-2. PTC'!E17 -> 0 | F16: ='1-1. Direct'!F16+'1-2. PTC'!F17 -> 0 | G16: ='1-1. Direct'!G16+'1-2. PTC'!G17 -> 0 | H16: ='1-1. Direct'!H16+'1-2. PTC'!H17 -> 297156.95 | ... L16: ='1-1. Direct'!L16+'1-2. PTC'!L17 -> 664443.22
A17: ='1-1. Direct'!A17+'1-2. PTC'!A18 -> 0 | B17: ='1-1. Direct'!B17+'1-2. PTC'!B18 -> 0 | C17: ='1-1. Direct'!C17+'1-2. PTC'!C18 -> 0 | D17: ='1-1. Direct'!D17+'1-2. PTC'!D18 -> 0 | E17: ='1-1. Direct'!E17+'1-2. PTC'!E18 -> 0 | F17: ='1-1. Direct'!F17+'1-2. PTC'!F18 -> 0 | G17: ='1-1. Direct'!G17+'1-2. PTC'!G18 -> 0 | H17: ='1-1. Direct'!H17+'1-2. PTC'!H18 -> 445735425 | ... L17: ='1-1. Direct'!L17+'1-2. PTC'!L18 -> 45657
A19: 2025 | B19: =SUM(A21:L21) -> 3902245.9 | C19: =SUM(A22:L22) -> 275739
A20: 01 | B20: 02 | C20: 03 | D20: 04 | E20: 05 | F20: 06 | G20: 07 | H20: 08 | I20: 09 | J20: 10 | K20: 11 | L20: 12
A21: ='1-1. Direct'!A21+'1-2. PTC'!A22 -> 2603.63 | B21: ='1-1. Direct'!B21+'1-2. PTC'!B22 -> 3495.17 | C21: ='1-1. Direct'!C21+'1-2. PTC'!C22 -> 28596.55 | D21: ='1-1. Direct'!D21+'1-2. PTC'!D22 -> 602035.01 | E21: ='1-1. Direct'!E21+'1-2. PTC'!E22 -> 22753.1 | F21: ='1-1. Direct'!F21+'1-2. PTC'!F22 -> 31921.13 | G21: ='1-1. Direct'!G21+'1-2. PTC'!G22 -> 280003.73 | H21: ='1-1. Direct'!H21+'1-2. PTC'!H22 -> 549854.43 | ... L21: ='1-1. Direct'!L21+'1-2. PTC'!L22 -> 2110369
A22: ='1-1. Direct'!A22+'1-2. PTC'!A23 -> 0 | B22: ='1-1. Direct'!B22+'1-2. PTC'!B23 -> 0 | C22: ='1-1. Direct'!C22+'1-2. PTC'!C23 -> 0 | D22: ='1-1. Direct'!D22+'1-2. PTC'!D23 -> 45768 | E22: ='1-1. Direct'!E22+'1-2. PTC'!E23 -> 0 | F22: ='1-1. Direct'!F22+'1-2. PTC'!F23 -> 0 | G22: ='1-1. Direct'!G22+'1-2. PTC'!G23 -> 0 | H22: ='1-1. Direct'!H22+'1-2. PTC'!H23 -> 45891 | ... L22: ='1-1. Direct'!L22+'1-2. PTC'!L23 -> 138081
A24: 2026 | B24: =SUM(A26:L26) -> 2870923.4 | C24: =SUM(A27:L27) -> 184578
A25: 01 | B25: 02 | C25: 03 | D25: 04 | E25: 05 | F25: 06 | G25: 07 | H25: 08 | I25: 09 | J25: 10 | K25: 11 | L25: 12
A26: ='1-1. Direct'!A26+'1-2. PTC'!A27 -> 429677.89 | B26: ='1-1. Direct'!B26+'1-2. PTC'!B27 -> 471496.93 | C26: ='1-1. Direct'!C26+'1-2. PTC'!C27 -> 404131.92 | D26: ='1-1. Direct'!D26+'1-2. PTC'!D27 -> 253068.95 | E26: ='1-1. Direct'!E26+'1-2. PTC'!E27 -> 112404.17 | F26: ='1-1. Direct'!F26+'1-2. PTC'!F27 -> 1066065.7 | G26: ='1-1. Direct'!G26+'1-2. PTC'!G27 -> 134077.92 | H26: ='1-1. Direct'!H26+'1-2. PTC'!H27 -> 0 | ... L26: ='1-1. Direct'!L26+'1-2. PTC'!L27 -> 0
A27: ='1-1. Direct'!A27+'1-2. PTC'!A28 -> 0 | B27: ='1-1. Direct'!B27+'1-2. PTC'!B28 -> 46081 | C27: ='1-1. Direct'!C27+'1-2. PTC'!C28 -> 46096 | D27: ='1-1. Direct'!D27+'1-2. PTC'!D28 -> 0 | E27: ='1-1. Direct'!E27+'1-2. PTC'!E28 -> 0 | F27: ='1-1. Direct'!F27+'1-2. PTC'!F28 -> 92401 | G27: ='1-1. Direct'!G27+'1-2. PTC'!G28 -> 0 | H27: ='1-1. Direct'!H27+'1-2. PTC'!H28 -> 0 | ... L27: ='1-1. Direct'!L27+'1-2. PTC'!L28 -> 0
A29: 2027 | B29: =SUM(A31:L31) -> 0 | C29: =SUM(A32:L32) -> 0
A30: 01 | B30: 02 | C30: 03 | D30: 04 | E30: 05 | F30: 06 | G30: 07 | H30: 08 | I30: 09 | J30: 10 | K30: 11 | L30: 12
A31: ='1-1. Direct'!A31+'1-2. PTC'!A32 -> 0 | B31: ='1-1. Direct'!B31+'1-2. PTC'!B32 -> 0 | C31: ='1-1. Direct'!C31+'1-2. PTC'!C32 -> 0 | D31: ='1-1. Direct'!D31+'1-2. PTC'!D32 -> 0 | E31: ='1-1. Direct'!E31+'1-2. PTC'!E32 -> 0 | F31: ='1-1. Direct'!F31+'1-2. PTC'!F32 -> 0 | G31: ='1-1. Direct'!G31+'1-2. PTC'!G32 -> 0 | H31: ='1-1. Direct'!H31+'1-2. PTC'!H32 -> 0 | ... L31: ='1-1. Direct'!L31+'1-2. PTC'!L32 -> 0
A32: ='1-1. Direct'!A32+'1-2. PTC'!A33 -> 0 | B32: ='1-1. Direct'!B32+'1-2. PTC'!B33 -> 0 | C32: ='1-1. Direct'!C32+'1-2. PTC'!C33 -> 0 | D32: ='1-1. Direct'!D32+'1-2. PTC'!D33 -> 0 | E32: ='1-1. Direct'!E32+'1-2. PTC'!E33 -> 0 | F32: ='1-1. Direct'!F32+'1-2. PTC'!F33 -> 0 | G32: ='1-1. Direct'!G32+'1-2. PTC'!G33 -> 0 | H32: ='1-1. Direct'!H32+'1-2. PTC'!H33 -> 0 | ... L32: ='1-1. Direct'!L32+'1-2. PTC'!L33 -> 0
A34: 3. Contract Details
A35: Team FTE | B35: Initial | C35: Country | D35: CO1 | E35: Country
A36: Project Lead (PL) | D36: 0.54 | E36: KR
A37: PL Oversight | D37: 0.08 | E37: KR
A38: Transition Lead | D38: 0.01 | E38: KR
A39: Project Management Associate (PMA) | D39: 0.34 | E39: IN
A40: Clinical Lead (CL) KR | D40: 0.54 | E40: KR
A41: Clinical Lead (CL) US | D41: 0.39 | E41: BR
A42: Clinical Monitoring Lead (CML) | D42: 0.27 | E42: IN
B44: Initial | E44: CO1 | H44: Change
A45: Milestones | B45: Duration(Months) | C45: Start Date | D45: End Date | E45: Duration(Months) | F45: Start Date | G45: End Date | H45: Initial to CO1
A46: Pre-Study Activities : ATP/Contract Signed to Final Protocol | E46: 0.46 | F46: 45473 | G46: 45487 | H46: =B46-E46 -> -0.46
A47: Start-Up: Final Protocol to FPI | E47: 2.56 | F47: 45488 | G47: 45565 | H47: =B47-E47 -> -2.56
A48: Recruitment: FPI to LPI | E48: 24.72 | F48: 45566 | G48: 46316 | H48: =B48-E48 -> -24.72
A49: Run-in/Screening: LPI | E49: 0.46 | F49: 46317 | G49: 46330 | H49: =B49-E49 -> -0.46
A50: Treatment: LPI to LPO | E50: 4.2 | F50: 46331 | G50: 46457 | H50: =B50-E50 -> -4.2
A51: Follow-Up: LPIF to LPOF | E51: 24.08 | F51: 46458 | G51: 47187 | H51: =B51-E51 -> -24.08
A52: Locked Database: Last Site Closed to Data Lock | E52: 1 | F52: 47188 | G52: 47217 | H52: =B52-E52 -> -1
A53: Close-Out: LPO to Last Site Closed | E53: 1 | F53: 47218 | G53: 47247 | H53: =B53-E53 -> -1
A54: Biostatistical Analysis: Database Lock to Final Tables | E54: 1 | F54: 47218 | G54: 47247 | H54: =B54-E54 -> -1
A55: Draft Report: Final Tables to 1st Draft Report | E55: 1 | F55: 47248 | G55: 47277 | H55: =B55-E55 -> -1
A56: Final Report: Draft Report to Final Report | E56: 1.46 | F56: 47278 | G56: 47321 | H56: =B56-E56 -> -1.46
A57: Post-Study Activities: (Archiving, Document Return) | E57: 0.23 | F57: 47322 | G57: 47328 | H57: =B57-E57 -> -0.23
A58: Total Study Duration, Start and End | E58: 61.17 | F58: 45473 | G58: 47328 | H58: =B58-E58 -> -61.17
A60: Direct Costs by Milestones
A61: Initial | B61: % | C61: Amount | D61: CO1 | E61: % | F61: Amount
D62: Pre-Payment Due Upon ATP Execution | E62: 4.02 | F62: 270676.37
D63: Pre-Payment Due Upon WO Execution | E63: 10.72 | F63: 722048.76
D64: Sign off transition checklist | E64: 9.83 | F64: 661816.76
D65: First IRB submission of AML site | E65: 8.84 | F65: 595635.08
D66: First IRB approval of AML site | E66: 6.88 | F66: 463271.73
D67: Pre-payment upon CO1 Execution | E67: 0.26 | F67: 17605
D68: First SIV for additional solid tumor site | E68: 9 | F68: 606207.57
D69: 30% of Monitoring Visits & Reports Completed | E69: 7 | F69: 471496.93
D70: 80% of Site Initiation Visits & Reports Completed | E70: 7 | F70: 471496.93
D71: 25% of Monitoring Visits & Reports Completed | E71: 7 | F71: 471496.93
D72: 35% of Monitoring Visits & Reports Completed | E72: 6 | F72: 404131.92
D73: 40% of Monitoring Visits & Reports Completed | E73: 6 | F73: 404131.92
... D83: Credit of residual Pre-Payment | E83: -15 | F83: -1010330.1
A85: Total | B85: 100 | D85: Total | E85: 100 | F85: 6735531.8
A86: *이 외, PTC(Core Services + Investigator Grants and Vendor)는 계약서 참고

Sheet 1-1. Direct
A1: 1. CRO: IQVIA
B2: Contract Number: | C2: LAB97701 | D2: Version & date: | E2: CO1_23Sep2025
A4: Protocol No: TTK-CS-101 | D4: Updated on:
A6: 1. Sub Total Direct Cost Status
A7: Category | B7: $ | C7: %
A8: Budget | B8: ='1. IQVIA '!F85 -> 6735531.8
A9: Paid | B9: =B14+B19+B24+B29 -> 5896792.5 | C9: =B9/B8 -> 0.87547542
A10: Remaining | B10: =B8-B9 -> 838739.25 | C10: =B10/B8 -> 0.12452458
A12: 2. Direct Cost Yearly and Monthly Payment
B13: USD | C13: KRW
A14: 2024 | B14: =SUM(A16:L16) -> 1654541.9 | C14: =SUM(A17:L17) -> 406105797
A15: 01 | B15: 02 | C15: 03 | D15: 04 | E15: 05 | F15: 06 | G15: 07 | H15: 08 | I15: 09 | J15: 10 | K15: 11 | L15: 12
A16: =SUMIFS($C$36:$C$57,$F$36:$F$57,2024,$G$36:$G$57,1,$J$36:$J$57,"Y") -> 0 | B16: =SUMIFS($C$36:$C$57,$F$36:$F$57,2024,$G$36:$G$57,2,$J$36:$J$57,"Y") -> 0 | C16: =SUMIFS($C$36:$C$57,$F$36:$F$57,2024,$G$36:$G$57,3,$J$36:$J$57,"Y") -> 0 | D16: =SUMIFS($C$36:$C$57,$F$36:$F$57,2024,$G$36:$G$57,4,$J$36:$J$57,"Y") -> 0 | E16: =SUMIFS($C$36:$C$57,$F$36:$F$57,2024,$G$36:$G$57,5,$J$36:$J$57,"Y") -> 0 | F16: =SUMIFS($C$36:$C$57,$F$36:$F$57,2024,$G$36:$G$57,6,$J$36:$J$57,"Y") -> 0 | G16: =SUMIFS($C$36:$C$57,$F$36:$F$57,2024,$G$36:$G$57,7,$J$36:$J$57,"Y") -> 0 | H16: =SUMIFS($C$36:$C$57,$F$36:$F$57,2024,$G$36:$G$57,8,$J$36:$J$57,"Y") -> 270676.37 | I16: =SUMIFS($C$36:$C$57,$F$36:$F$57,2024,$G$36:$G$57,9,$J$36:$J$57,"Y") -> 0 | J16: =SUMIFS($C$36:$C$57,$F$36:$F$57,2024,$G$36:$G$57,10,$J$36:$J$57,"Y") -> 722048.76 | K16: =SUMIFS($C$36:$C$57,$F$36:$F$57,2024,$G$36:$G$57,11,$J$36:$J$57,"Y") -> 0 | L16: =SUMIFS($C$36:$C$57,$F$36:$F$57,2024,$G$36:$G$57,12,$J$36:$J$57,"Y") -> 661816.76
A17: =SUMIFS($I$36:$I$57,$F$36:$F$57,2024,$G$36:$G$57,1,$J$36:$J$57,"Y") -> 0 | B17: =SUMIFS($I$36:$I$57,$F$36:$F$57,2024,$G$36:$G$57,2,$J$36:$J$57,"Y") -> 0 | C17: =SUMIFS($I$36:$I$57,$F$36:$F$57,2024,$G$36:$G$57,3,$J$36:$J$57,"Y") -> 0 | D17: =SUMIFS($I$36:$I$57,$F$36:$F$57,2024,$G$36:$G$57,4,$J$36:$J$57,"Y") -> 0 | E17: =SUMIFS($I$36:$I$57,$F$36:$F$57,2024,$G$36:$G$57,5,$J$36:$J$57,"Y") -> 0 | F17: =SUMIFS($I$36:$I$57,$F$36:$F$57,2024,$G$36:$G$57,6,$J$36:$J$57,"Y") -> 0 | G17: =SUMIFS($I$36:$I$57,$F$36:$F$57,2024,$G$36:$G$57,7,$J$36:$J$57,"Y") -> 0 | H17: =SUMIFS($I$36:$I$57,$F$36:$F$57,2024,$G$36:$G$57,8,$J$36:$J$57,"Y") -> 406014555 | I17: =SUMIFS($I$36:$I$57,$F$36:$F$57,2024,$G$36:$G$57,9,$J$36:$J$57,"Y") -> 0 | J17: =SUMIFS($I$36:$I$57,$F$36:$F$57,2024,$G$36:$G$57,10,$J$36:$J$57,"Y") -> 45585 | K17: =SUMIFS($I$36:$I$57,$F$36:$F$57,2024,$G$36:$G$57,11,$J$36:$J$57,"Y") -> 0 | L17: =SUMIFS($I$36:$I$57,$F$36:$F$57,2024,$G$36:$G$57,12,$J$36:$J$57,"Y") -> 45657
A19: 2025 | B19: =SUM(A21:L21) -> 2625713.3 | C19: =SUM(A22:L22) -> 275739
A20: 01 | B20: 02 | C20: 03 | D20: 04 | E20: 05 | F20: 06 | G20: 07 | H20: 08 | I20: 09 | J20: 10 | K20: 11 | L20: 12
A21: =SUMIFS($C$36:$C$57,$F$36:$F$57,2025,$G$36:$G$57,1,$J$36:$J$57,"Y") -> 0 | B21: =SUMIFS($C$36:$C$57,$F$36:$F$57,2025,$G$36:$G$57,2,$J$36:$J$57,"Y") -> 0 | C21: =SUMIFS($C$36:$C$57,$F$36:$F$57,2025,$G$36:$G$57,3,$J$36:$J$57,"Y") -> 0 | D21: =SUMIFS($C$36:$C$57,$F$36:$F$57,2025,$G$36:$G$57,4,$J$36:$J$57,"Y") -> 595635.08 | E21: =SUMIFS($C$36:$C$57,$F$36:$F$57,2025,$G$36:$G$57,5,$J$36:$J$57,"Y") -> 0 | F21: =SUMIFS($C$36:$C$57,$F$36:$F$57,2025,$G$36:$G$57,6,$J$36:$J$57,"Y") -> 0 | G21: =SUMIFS($C$36:$C$57,$F$36:$F$57,2025,$G$36:$G$57,7,$J$36:$J$57,"Y") -> 0 | H21: =SUMIFS($C$36:$C$57,$F$36:$F$57,2025,$G$36:$G$57,8,$J$36:$J$57,"Y") -> 463271.73 | I21: =SUMIFS($C$36:$C$57,$F$36:$F$57,2025,$G$36:$G$57,9,$J$36:$J$57,"Y") -> 0 | J21: =SUMIFS($C$36:$C$57,$F$36:$F$57,2025,$G$36:$G$57,10,$J$36:$J$57,"Y") -> 0 | K21: =SUMIFS($C$36:$C$57,$F$36:$F$57,2025,$G$36:$G$57,11,$J$36:$J$57,"Y") -> 17605 | L21: =SUMIFS($C$36:$C$57,$F$36:$F$57,2025,$G$36:$G$57,12,$J$36:$J$57,"Y") -> 1549201.5
A22: =SUMIFS($I$36:$I$57,$F$36:$F$57,2025,$G$36:$G$57,1,$J$36:$J$57,"Y") -> 0 | B22: =SUMIFS($I$36:$I$57,$F$36:$F$57,2025,$G$36:$G$57,2,$J$36:$J$57,"Y") -> 0 | C22: =SUMIFS($I$36:$I$57,$F$36:$F$57,2025,$G$36:$G$57,3,$J$36:$J$57,"Y") -> 0 | D22: =SUMIFS($I$36:$I$57,$F$36:$F$57,2025,$G$36:$G$57,4,$J$36:$J$57,"Y") -> 45768 | E22: =SUMIFS($I$36:$I$57,$F$36:$F$57,2025,$G$36:$G$57,5,$J$36:$J$57,"Y") -> 0 | F22: =SUMIFS($I$36:$I$57,$F$36:$F$57,2025,$G$36:$G$57,6,$J$36:$J$57,"Y") -> 0 | G22: =SUMIFS($I$36:$I$57,$F$36:$F$57,2025,$G$36:$G$57,7,$J$36:$J$57,"Y") -> 0 | H22: =SUMIFS($I$36:$I$57,$F$36:$F$57,2025,$G$36:$G$57,8,$J$36:$J$57,"Y") -> 45891 | I22: =SUMIFS($I$36:$I$57,$F$36:$F$57,2025,$G$36:$G$57,9,$J$36:$J$57,"Y") -> 0 | J22: =SUMIFS($I$36:$I$57,$F$36:$F$57,2025,$G$36:$G$57,10,$J$36:$J$57,"Y") -> 0 | K22: =SUMIFS($I$36:$I$57,$F$36:$F$57,2025,$G$36:$G$57,11,$J$36:$J$57,"Y") -> 45999 | L22: =SUMIFS($I$36:$I$57,$F$36:$F$57,2025,$G$36:$G$57,12,$J$36:$J$57,"Y") -> 138081
A24: 2026 | B24: =SUM(A26:L26) -> 1616537.4 | C24: =SUM(A27:L27) -> 184578
A25: 01 | B25: 02 | C25: 03 | D25: 04 | E25: 05 | F25: 06 | G25: 07 | H25: 08 | I25: 09 | J25: 10 | K25: 11 | L25: 12
A26: =SUMIFS($C$36:$C$57,$F$36:$F$57,2026,$G$36:$G$57,1,$J$36:$J$57,"Y") -> 0 | B26: =SUMIFS($C$36:$C$57,$F$36:$F$57,2026,$G$36:$G$57,2,$J$36:$J$57,"Y") -> 471496.93 | C26: =SUMIFS($C$36:$C$57,$F$36:$F$57,2026,$G$36:$G$57,3,$J$36:$J$57,"Y") -> 404131.92 | D26: =SUMIFS($C$36:$C$57,$F$36:$F$57,2026,$G$36:$G$57,4,$J$36:$J$57,"Y") -> 0 | E26: =SUMIFS($C$36:$C$57,$F$36:$F$57,2026,$G$36:$G$57,5,$J$36:$J$57,"Y") -> 0 | F26: =SUMIFS($C$36:$C$57,$F$36:$F$57,2026,$G$36:$G$57,6,$J$36:$J$57,"Y") -> 740908.51 | G26: =SUMIFS($C$36:$C$57,$F$36:$F$57,2026,$G$36:$G$57,7,$J$36:$J$57,"Y") -> 0 | H26: =SUMIFS($C$36:$C$57,$F$36:$F$57,2026,$G$36:$G$57,8,$J$36:$J$57,"Y") -> 0 | I26: =SUMIFS($C$36:$C$57,$F$36:$F$57,2026,$G$36:$G$57,9,$J$36:$J$57,"Y") -> 0 | J26: =SUMIFS($C$36:$C$57,$F$36:$F$57,2026,$G$36:$G$57,10,$J$36:$J$57,"Y") -> 0 | K26: =SUMIFS($C$36:$C$57,$F$36:$F$57,2026,$G$36:$G$57,11,$J$36:$J$57,"Y") -> 0 | L26: =SUMIFS($C$36:$C$57,$F$36:$F$57,2026,$G$36:$G$57,12,$J$36:$J$57,"Y") -> 0
A27: =SUMIFS($I$36:$I$57,$F$36:$F$57,2026,$G$36:$G$57,1,$J$36:$J$57,"Y") -> 0 | B27: =SUMIFS($I$36:$I$57,$F$36:$F$57,2026,$G$36:$G$57,2,$J$36:$J$57,"Y") -> 46081 | C27: =SUMIFS($I$36:$I$57,$F$36:$F$57,2026,$G$36:$G$57,3,$J$36:$J$57,"Y") -> 46096 | D27: =SUMIFS($I$36:$I$57,$F$36:$F$57,2026,$G$36:$G$57,4,$J$36:$J$57,"Y") -> 0 | E27: =SUMIFS($I$36:$I$57,$F$36:$F$57,2026,$G$36:$G$57,5,$J$36:$J$57,"Y") -> 0 | F27: =SUMIFS($I$36:$I$57,$F$36:$F$57,2026,$G$36:$G$57,6,$J$36:$J$57,"Y") -> 92401 | G27: =SUMIFS($I$36:$I$57,$F$36:$F$57,2026,$G$36:$G$57,7,$J$36:$J$57,"Y") -> 0 | H27: =SUMIFS($I$36:$I$57,$F$36:$F$57,2026,$G$36:$G$57,8,$J$36:$J$57,"Y") -> 0 | I27: =SUMIFS($I$36:$I$57,$F$36:$F$57,2026,$G$36:$G$57,9,$J$36:$J$57,"Y") -> 0 | J27: =SUMIFS($I$36:$I$57,$F$36:$F$57,2026,$G$36:$G$57,10,$J$36:$J$57,"Y") -> 0 | K27: =SUMIFS($I$36:$I$57,$F$36:$F$57,2026,$G$36:$G$57,11,$J$36:$J$57,"Y") -> 0 | L27: =SUMIFS($I$36:$I$57,$F$36:$F$57,2026,$G$36:$G$57,12,$J$36:$J$57,"Y") -> 0
A29: 2027 | B29: =SUM(A31:L31) -> 0 | C29: =SUM(A32:L32) -> 0
A30: 01 | B30: 02 | C30: 03 | D30: 04 | E30: 05 | F30: 06 | G30: 07 | H30: 08 | I30: 09 | J30: 10 | K30: 11 | L30: 12
A31: =SUMIFS($C$36:$C$57,$F$36:$F$57,2027,$G$36:$G$57,1,$J$36:$J$57,"Y") -> 0 | B31: =SUMIFS($C$36:$C$57,$F$36:$F$57,2027,$G$36:$G$57,2,$J$36:$J$57,"Y") -> 0 | C31: =SUMIFS($C$36:$C$57,$F$36:$F$57,2027,$G$36:$G$57,3,$J$36:$J$57,"Y") -> 0 | D31: =SUMIFS($C$36:$C$57,$F$36:$F$57,2027,$G$36:$G$57,4,$J$36:$J$57,"Y") -> 0 | E31: =SUMIFS($C$36:$C$57,$F$36:$F$57,2027,$G$36:$G$57,5,$J$36:$J$57,"Y") -> 0 | F31: =SUMIFS($C$36:$C$57,$F$36:$F$57,2027,$G$36:$G$57,6,$J$36:$J$57,"Y") -> 0 | G31: =SUMIFS($C$36:$C$57,$F$36:$F$57,2027,$G$36:$G$57,7,$J$36:$J$57,"Y") -> 0 | H31: =SUMIFS($C$36:$C$57,$F$36:$F$57,2027,$G$36:$G$57,8,$J$36:$J$57,"Y") -> 0 | I31: =SUMIFS($C$36:$C$57,$F$36:$F$57,2027,$G$36:$G$57,9,$J$36:$J$57,"Y") -> 0 | J31: =SUMIFS($C$36:$C$57,$F$36:$F$57,2027,$G$36:$G$57,10,$J$36:$J$57,"Y") -> 0 | K31: =SUMIFS($C$36:$C$57,$F$36:$F$57,2027,$G$36:$G$57,11,$J$36:$J$57,"Y") -> 0 | L31: =SUMIFS($C$36:$C$57,$F$36:$F$57,2027,$G$36:$G$57,12,$J$36:$J$57,"Y") -> 0
A32: =SUMIFS($I$36:$I$57,$F$36:$F$57,2027,$G$36:$G$57,1,$J$36:$J$57,"Y") -> 0 | B32: =SUMIFS($I$36:$I$57,$F$36:$F$57,2027,$G$36:$G$57,2,$J$36:$J$57,"Y") -> 0 | C32: =SUMIFS($I$36:$I$57,$F$36:$F$57,2027,$G$36:$G$57,3,$J$36:$J$57,"Y") -> 0 | D32: =SUMIFS($I$36:$I$57,$F$36:$F$57,2027,$G$36:$G$57,4,$J$36:$J$57,"Y") -> 0 | E32: =SUMIFS($I$36:$I$57,$F$36:$F$57,2027,$G$36:$G$57,5,$J$36:$J$57,"Y") -> 0 | F32: =SUMIFS($I$36:$I$57,$F$36:$F$57,2027,$G$36:$G$57,6,$J$36:$J$57,"Y") -> 0 | G32: =SUMIFS($I$36:$I$57,$F$36:$F$57,2027,$G$36:$G$57,7,$J$36:$J$57,"Y") -> 0 | H32: =SUMIFS($I$36:$I$57,$F$36:$F$57,2027,$G$36:$G$57,8,$J$36:$J$57,"Y") -> 0 | I32: =SUMIFS($I$36:$I$57,$F$36:$F$57,2027,$G$36:$G$57,9,$J$36:$J$57,"Y") -> 0 | J32: =SUMIFS($I$36:$I$57,$F$36:$F$57,2027,$G$36:$G$57,10,$J$36:$J$57,"Y") -> 0 | K32: =SUMIFS($I$36:$I$57,$F$36:$F$57,2027,$G$36:$G$57,11,$J$36:$J$57,"Y") -> 0 | L32: =SUMIFS($I$36:$I$57,$F$36:$F$57,2027,$G$36:$G$57,12,$J$36:$J$57,"Y") -> 0
A34: 3. Direct Costs Details
A35: Milestones | B35: Budget Amount($) | C35: Invoiced Amount($) | D35: Invoice # | E35: Invoiced Date | F35: Paid Year | G35: Paid Month | H35: Paid Date | I35: Total Amount(₩) | J35: Paid (Y) | K35: 지출결의 #
A36: Pre-Payment Due Upon ATP Execution | B36: 270676.37 | C36: 270676.37 | D36: SGP-030213 | E36: 45495 | F36: 2024 | G36: 8 | H36: 45512 | I36: 406014555 | J36: Y | K36: CD24-170
A37: Pre-Payment Due Upon WO Execution | B37: 722048.76 | C37: 722048.76 | D37: SGP-030533 | E37: 45562 | F37: 2024 | G37: 10 | H37: 45575 | I37: =G37+H37 -> 45585 | J37: Y | K37: CD24-220
A38: Sign off transition checklist | B38: 661816.76 | C38: 661816.76 | D38: SGP-030822 | E38: 45625 | F38: 2024 | G38: 12 | H38: 45645 | I38: =G38+H38 -> 45657 | J38: Y | K38: CD24-277
A39: First IRB submission of AML site | B39: 595635.08 | C39: 595635.08 | D39: SGP-031343 | E39: 45755 | F39: 2025 | G39: 4 | H39: 45764 | I39: =G39+H39 -> 45768 | J39: Y | K39: CD25-072
A40: First IRB approval of AML site | B40: 463271.73 | C40: 463271.73 | D40: SGP-031701 | E40: 45852 | F40: 2025 | G40: 8 | H40: 45883 | I40: =G40+H40 -> 45891 | J40: Y | K40: CD25-155
A41: Pre-payment upon CO1 Execution | B41: 17605 | C41: 17605 | D41: SGP-032017 | E41: 45938 | F41: 2025 | G41: 11 | H41: 45988 | I41: =G41+H41 -> 45999 | J41: Y | K41: CD25-205
A42: First SIV for additional solid tumor site | B42: 606207.57 | C42: 606207.57 | D42: SGP-032306 | E42: 46001 | F42: 2025 | G42: 12 | H42: 46015 | I42: =G42+H42 -> 46027 | J42: Y | K42: CD25-232
A43: 30% of Monitoring Visits & Reports Completed | B43: 471496.93 | C43: 471496.96 | D43: SGP-032306 | E43: 46001 | F43: 2025 | G43: 12 | H43: 46015 | I43: =G43+H43 -> 46027 | J43: Y | K43: CD25-232
A44: 80% of Site Initiation Visits & Reports Completed | B44: 471496.93 | C44: 471496.93 | D44: SGP-032465 | E44: 46042 | F44: 2026 | G44: 2 | H44: 46079 | I44: =G44+H44 -> 46081 | J44: Y | K44: CD26-016
A45: 25% of Monitoring Visits & Reports Completed | B45: 471496.93 | C45: 471496.93 | D45: SGP-032175 | E45: 45970 | F45: 2025 | G45: 12 | H45: 46015 | I45: =G45+H45 -> 46027 | J45: Y | K45: CD25-225
A46: 35% of Monitoring Visits & Reports Completed | B46: 404131.92 | C46: 404131.92 | D46: SGP-032533 | E46: 46063 | F46: 2026 | G46: 3 | H46: 46093 | I46: =G46+H46 -> 46096 | J46: Y | K46: CD26-023
A47: 40% of Monitoring Visits & Reports Completed | B47: 404131.92 | C47: 404131.92 | D47: SGP-032889 | E47: 46155 | F47: 2026 | G47: 6 | H47: 46177 | I47: =G47+H47 -> 46183 | J47: Y | K47: CO26-025
A48: 50% of Monitoring Visits & Reports Completed | B48: 336776.59 | C48: 336776.59 | D48: SGP-032978 | E48: 46183 | F48: 2026 | G48: 6 | H48: 46212 | I48: =G48+H48 -> 46218 | J48: Y | K48: CO26-045
A49: 55% of Monitoring Visits & Reports Completed | B49: 336776.59 | I49: =G49+H49 -> 0
A50: 65% of Monitoring Visits & Reports Completed | B50: 269421.27 | I50: =G50+H50 -> 0
A51: 75% of Monitoring Visits & Reports Completed | B51: 269421.27 | I51: =G51+H51 -> 0
A52: 80% of Monitoring Visits & Reports Completed | B52: 202065.95 | I52: =G52+H52 -> 0
A53: 90% of Monitoring Visits & Reports Completed | B53: 202065.95 | I53: =G53+H53 -> 0
A54: 95% of Monitoring Visits & Reports Completed | B54: 202065.95 | I54: =G54+H54 -> 0
A55: Completion of In-treatment follow-up of last patient | B55: 202065.95 | I55: =G55+H55 -> 0
A56: 100% Site close out | B56: 165186.48 | I56: =G56+H56 -> 0
A57: Credit of residual Pre-Payment | B57: -1010330.1 | I57: =G57+H57 -> 0

Sheet 1-2. PTC
A1: 1. CRO: IQVIA
B2: Contract Number: | C2: LAB97701 | D2: Version & date: | E2: CO1_23Sep2025
A4: Protocol No: TTK-CS-101 | D4: Updated on:
A6: 1. Sub Total PTC Status
A7: Category | B7: $ | C7: %
A8: Budget | B8: 9199888.7
A9: Advance(Deposit) | D9: 연구 종료 시 Reconcilation 예정이므로 paid에서 제외
A10: Paid | B10: =B36+B41+B46+B51 -> 1491199.7 | C10: =B10/B8 -> 0.16208888
A11: Remaining | B11: =B8-B10 -> 7708689 | C11: =B11/B8 -> 0.83791112
A13: 2. PTC Yearly and Monthly Payment
B14: USD | C14: KRW
A15: 2024 | B15: =SUM(A17:L17) -> 1415379 | C15: =SUM(A18:L18) -> 2.4615e+08
A16: 01 | B16: 02 | C16: 03 | D16: 04 | E16: 05 | F16: 06 | G16: 07 | H16: 08 | I16: 09 | J16: 10 | K16: 11 | L16: 12
A17: =SUMIFS($P$41:$P$60,$R$41:$R$60,2024,$S$41:$S$60,1,$V$41:$V$60,"Y") -> 0 | B17: =SUMIFS($P$41:$P$60,$R$41:$R$60,2024,$S$41:$S$60,2,$V$41:$V$60,"Y") -> 0 | C17: =SUMIFS($P$41:$P$60,$R$41:$R$60,2024,$S$41:$S$60,3,$V$41:$V$60,"Y") -> 0 | D17: =SUMIFS($P$41:$P$60,$R$41:$R$60,2024,$S$41:$S$60,4,$V$41:$V$60,"Y") -> 0 | E17: =SUMIFS($P$41:$P$60,$R$41:$R$60,2024,$S$41:$S$60,5,$V$41:$V$60,"Y") -> 0 | F17: =SUMIFS($P$41:$P$60,$R$41:$R$60,2024,$S$41:$S$60,6,$V$41:$V$60,"Y") -> 0 | G17: =SUMIFS($P$41:$P$60,$R$41:$R$60,2024,$S$41:$S$60,7,$V$41:$V$60,"Y") -> 0 | H17: =SUMIFS($P$41:$P$60,$R$41:$R$60,2024,$S$41:$S$60,8,$V$41:$V$60,"Y") -> 26480.58 | I17: =SUMIFS($P$41:$P$60,$R$41:$R$60,2024,$S$41:$S$60,9,$V$41:$V$60,"Y") -> 0 | J17: =SUMIFS($P$41:$P$60,$R$41:$R$60,2024,$S$41:$S$60,10,$V$41:$V$60,"Y") -> 1386272 | K17: =SUMIFS($P$41:$P$60,$R$41:$R$60,2024,$S$41:$S$60,11,$V$41:$V$60,"Y") -> 0 | L17: =SUMIFS($P$41:$P$60,$R$41:$R$60,2024,$S$41:$S$60,12,$V$41:$V$60,"Y") -> 2626.46
A18: =SUMIFS($U$41:$U$60,$R$41:$R$60,2024,$S$41:$S$60,1,$V$41:$V$60,"Y") -> 0 | B18: =SUMIFS($U$41:$U$60,$R$41:$R$60,2024,$S$41:$S$60,2,$V$41:$V$60,"Y") -> 0 | C18: =SUMIFS($U$41:$U$60,$R$41:$R$60,2024,$S$41:$S$60,3,$V$41:$V$60,"Y") -> 0 | D18: =SUMIFS($U$41:$U$60,$R$41:$R$60,2024,$S$41:$S$60,4,$V$41:$V$60,"Y") -> 0 | E18: =SUMIFS($U$41:$U$60,$R$41:$R$60,2024,$S$41:$S$60,5,$V$41:$V$60,"Y") -> 0 | F18: =SUMIFS($U$41:$U$60,$R$41:$R$60,2024,$S$41:$S$60,6,$V$41:$V$60,"Y") -> 0 | G18: =SUMIFS($U$41:$U$60,$R$41:$R$60,2024,$S$41:$S$60,7,$V$41:$V$60,"Y") -> 0 | H18: =SUMIFS($U$41:$U$60,$R$41:$R$60,2024,$S$41:$S$60,8,$V$41:$V$60,"Y") -> 39720870 | I18: =SUMIFS($U$41:$U$60,$R$41:$R$60,2024,$S$41:$S$60,9,$V$41:$V$60,"Y") -> 0 | J18: =SUMIFS($U$41:$U$60,$R$41:$R$60,2024,$S$41:$S$60,10,$V$41:$V$60,"Y") -> 2.0642913e+08 | K18: =SUMIFS($U$41:$U$60,$R$41:$R$60,2024,$S$41:$S$60,11,$V$41:$V$60,"Y") -> 0 | L18: =SUMIFS($U$41:$U$60,$R$41:$R$60,2024,$S$41:$S$60,12,$V$41:$V$60,"Y") -> 0
A20: 2025 | B20: =SUM(A22:L22) -> 1276532.6 | C20: =SUM(A23:L23) -> 0
A21: 01 | B21: 02 | C21: 03 | D21: 04 | E21: 05 | F21: 06 | G21: 07 | H21: 08 | I21: 09 | J21: 10 | K21: 11 | L21: 12
A22: =SUMIFS($P$41:$P$60,$R$41:$R$60,2025,$S$41:$S$60,1,$V$41:$V$60,"Y") -> 2603.63 | B22: =SUMIFS($P$41:$P$60,$R$41:$R$60,2025,$S$41:$S$60,2,$V$41:$V$60,"Y") -> 3495.17 | C22: =SUMIFS($P$41:$P$60,$R$41:$R$60,2025,$S$41:$S$60,3,$V$41:$V$60,"Y") -> 28596.55 | D22: =SUMIFS($P$41:$P$60,$R$41:$R$60,2025,$S$41:$S$60,4,$V$41:$V$60,"Y") -> 6399.93 | E22: =SUMIFS($P$41:$P$60,$R$41:$R$60,2025,$S$41:$S$60,5,$V$41:$V$60,"Y") -> 22753.1 | F22: =SUMIFS($P$41:$P$60,$R$41:$R$60,2025,$S$41:$S$60,6,$V$41:$V$60,"Y") -> 31921.13 | G22: =SUMIFS($P$41:$P$92,$R$41:$R$92,2025,$S$41:$S$92,7,$V$41:$V$92,"Y") -> 280003.73 | H22: =SUMIFS($P$41:$P$92,$R$41:$R$92,2025,$S$41:$S$92,8,$V$41:$V$92,"Y") -> 86582.7 | I22: =SUMIFS($P$41:$P$60,$R$41:$R$60,2025,$S$41:$S$60,9,$V$41:$V$60,"Y") -> 0 | J22: =SUMIFS($P$41:$P$60,$R$41:$R$60,2025,$S$41:$S$60,10,$V$41:$V$60,"Y") -> 0 | K22: =SUMIFS($P$41:$P$60,$R$41:$R$60,2025,$S$41:$S$60,11,$V$41:$V$60,"Y") -> 253009.14 | L22: =SUMIFS($P$41:$P$92,$R$41:$R$92,2025,$S$41:$S$92,12,$V$41:$V$92,"Y") -> 561167.5
A23: =SUMIFS($U$41:$U$60,$R$41:$R$60,2025,$S$41:$S$60,1,$V$41:$V$60,"Y") -> 0 | B23: =SUMIFS($U$41:$U$60,$R$41:$R$60,2025,$S$41:$S$60,2,$V$41:$V$60,"Y") -> 0 | C23: =SUMIFS($U$41:$U$60,$R$41:$R$60,2025,$S$41:$S$60,3,$V$41:$V$60,"Y") -> 0 | D23: =SUMIFS($U$41:$U$60,$R$41:$R$60,2025,$S$41:$S$60,4,$V$41:$V$60,"Y") -> 0 | E23: =SUMIFS($U$41:$U$60,$R$41:$R$60,2025,$S$41:$S$60,5,$V$41:$V$60,"Y") -> 0 | F23: =SUMIFS($U$41:$U$60,$R$41:$R$60,2025,$S$41:$S$60,6,$V$41:$V$60,"Y") -> 0 | G23: =SUMIFS($U$41:$U$60,$R$41:$R$60,2025,$S$41:$S$60,7,$V$41:$V$60,"Y") -> 0 | H23: =SUMIFS($U$41:$U$60,$R$41:$R$60,2025,$S$41:$S$60,8,$V$41:$V$60,"Y") -> 0 | I23: =SUMIFS($U$41:$U$60,$R$41:$R$60,2025,$S$41:$S$60,9,$V$41:$V$60,"Y") -> 0 | J23: =SUMIFS($U$41:$U$60,$R$41:$R$60,2025,$S$41:$S$60,10,$V$41:$V$60,"Y") -> 0 | K23: =SUMIFS($U$41:$U$60,$R$41:$R$60,2025,$S$41:$S$60,11,$V$41:$V$60,"Y") -> 0 | L23: =SUMIFS($U$41:$U$60,$R$41:$R$60,2025,$S$41:$S$60,12,$V$41:$V$60,"Y") -> 0
A25: 2026 | B25: =SUM(A27:L27) -> 1254386.1 | C25: =SUM(A28:L28) -> 0
A26: 01 | B26: 02 | C26: 03 | D26: 04 | E26: 05 | F26: 06 | G26: 07 | H26: 08 | I26: 09 | J26: 10 | K26: 11 | L26: 12
A27: =SUMIFS($P$41:$P$67,$R$41:$R$67,2026,$S$41:$S$67,1,$V$41:$V$67,"Y") -> 429677.89 | B27: =SUMIFS($P$41:$P$67,$R$41:$R$67,2026,$S$41:$S$67,2,$V$41:$V$67,"Y") -> 0 | C27: =SUMIFS($P$41:$P$67,$R$41:$R$67,2026,$S$41:$S$67,3,$V$41:$V$67,"Y") -> 0 | D27: =SUMIFS($P$41:$P$86,$R$41:$R$86,2026,$S$41:$S$86,4,$V$41:$V$86,"Y") -> 253068.95 | E27: =SUMIFS($P$41:$P$86,$R$41:$R$86,2026,$S$41:$S$86,5,$V$41:$V$86,"Y") -> 112404.17 | F27: =SUMIFS($P$41:$P$86,$R$41:$R$86,2026,$S$41:$S$86,6,$V$41:$V$86,"Y") -> 325157.15 | G27: =SUMIFS($P$41:$P$86,$R$41:$R$86,2026,$S$41:$S$86,7,$V$41:$V$86,"Y") -> 134077.92 | H27: =SUMIFS($P$41:$P$86,$R$41:$R$86,2026,$S$41:$S$86,8,$V$41:$V$86,"Y") -> 0 | I27: =SUMIFS($P$41:$P$86,$R$41:$R$86,2026,$S$41:$S$86,9,$V$41:$V$86,"Y") -> 0 | J27: =SUMIFS($P$41:$P$86,$R$41:$R$86,2026,$S$41:$S$86,10,$V$41:$V$86,"Y") -> 0 | K27: =SUMIFS($P$41:$P$70,$R$41:$R$70,2026,$S$41:$S$70,11,$V$41:$V$70,"Y") -> 0 | L27: =SUMIFS($P$41:$P$70,$R$41:$R$70,2026,$S$41:$S$70,12,$V$41:$V$70,"Y") -> 0
A28: =SUMIFS($U$41:$U$60,$R$41:$R$60,2026,$S$41:$S$60,1,$V$41:$V$60,"Y") -> 0 | B28: =SUMIFS($U$41:$U$60,$R$41:$R$60,2026,$S$41:$S$60,2,$V$41:$V$60,"Y") -> 0 | C28: =SUMIFS($U$41:$U$60,$R$41:$R$60,2026,$S$41:$S$60,3,$V$41:$V$60,"Y") -> 0 | D28: =SUMIFS($U$41:$U$60,$R$41:$R$60,2026,$S$41:$S$60,4,$V$41:$V$60,"Y") -> 0 | E28: =SUMIFS($U$41:$U$60,$R$41:$R$60,2026,$S$41:$S$60,5,$V$41:$V$60,"Y") -> 0 | F28: =SUMIFS($U$41:$U$60,$R$41:$R$60,2026,$S$41:$S$60,6,$V$41:$V$60,"Y") -> 0 | G28: =SUMIFS($U$41:$U$60,$R$41:$R$60,2026,$S$41:$S$60,7,$V$41:$V$60,"Y") -> 0 | H28: =SUMIFS($U$41:$U$60,$R$41:$R$60,2026,$S$41:$S$60,8,$V$41:$V$60,"Y") -> 0 | I28: =SUMIFS($U$41:$U$60,$R$41:$R$60,2026,$S$41:$S$60,9,$V$41:$V$60,"Y") -> 0 | J28: =SUMIFS($U$41:$U$60,$R$41:$R$60,2026,$S$41:$S$60,10,$V$41:$V$60,"Y") -> 0 | K28: =SUMIFS($U$41:$U$60,$R$41:$R$60,2026,$S$41:$S$60,11,$V$41:$V$60,"Y") -> 0 | L28: =SUMIFS($U$41:$U$60,$R$41:$R$60,2026,$S$41:$S$60,12,$V$41:$V$60,"Y") -> 0
A30: 2027 | B30: =SUM(A32:L32) -> 0 | C30: =SUM(A33:L33) -> 0
A31: 01 | B31: 02 | C31: 03 | D31: 04 | E31: 05 | F31: 06 | G31: 07 | H31: 08 | I31: 09 | J31: 10 | K31: 11 | L31: 12
A32: =SUMIFS($P$41:$P$60,$R$41:$R$60,2027,$S$41:$S$60,1,$V$41:$V$60,"Y") -> 0 | B32: =SUMIFS($P$41:$P$60,$R$41:$R$60,2027,$S$41:$S$60,2,$V$41:$V$60,"Y") -> 0 | C32: =SUMIFS($P$41:$P$60,$R$41:$R$60,2027,$S$41:$S$60,3,$V$41:$V$60,"Y") -> 0 | D32: =SUMIFS($P$41:$P$60,$R$41:$R$60,2027,$S$41:$S$60,4,$V$41:$V$60,"Y") -> 0 | E32: =SUMIFS($P$41:$P$60,$R$41:$R$60,2027,$S$41:$S$60,5,$V$41:$V$60,"Y") -> 0 | F32: =SUMIFS($P$41:$P$60,$R$41:$R$60,2027,$S$41:$S$60,6,$V$41:$V$60,"Y") -> 0 | G32: =SUMIFS($P$41:$P$60,$R$41:$R$60,2027,$S$41:$S$60,7,$V$41:$V$60,"Y") -> 0 | H32: =SUMIFS($P$41:$P$60,$R$41:$R$60,2027,$S$41:$S$60,8,$V$41:$V$60,"Y") -> 0 | I32: =SUMIFS($P$41:$P$60,$R$41:$R$60,2027,$S$41:$S$60,9,$V$41:$V$60,"Y") -> 0 | J32: =SUMIFS($P$41:$P$60,$R$41:$R$60,2027,$S$41:$S$60,10,$V$41:$V$60,"Y") -> 0 | K32: =SUMIFS($P$41:$P$60,$R$41:$R$60,2027,$S$41:$S$60,11,$V$41:$V$60,"Y") -> 0 | L32: =SUMIFS($P$41:$P$60,$R$41:$R$60,2027,$S$41:$S$60,12,$V$41:$V$60,"Y") -> 0
A33: =SUMIFS($U$41:$U$60,$R$41:$R$60,2027,$S$41:$S$60,1,$V$41:$V$60,"Y") -> 0 | B33: =SUMIFS($U$41:$U$60,$R$41:$R$60,2027,$S$41:$S$60,2,$V$41:$V$60,"Y") -> 0 | C33: =SUMIFS($U$41:$U$60,$R$41:$R$60,2027,$S$41:$S$60,3,$V$41:$V$60,"Y") -> 0 | D33: =SUMIFS($U$41:$U$60,$R$41:$R$60,2027,$S$41:$S$60,4,$V$41:$V$60,"Y") -> 0 | E33: =SUMIFS($U$41:$U$60,$R$41:$R$60,2027,$S$41:$S$60,5,$V$41:$V$60,"Y") -> 0 | F33: =SUMIFS($U$41:$U$60,$R$41:$R$60,2027,$S$41:$S$60,6,$V$41:$V$60,"Y") -> 0 | G33: =SUMIFS($U$41:$U$60,$R$41:$R$60,2027,$S$41:$S$60,7,$V$41:$V$60,"Y") -> 0 | H33: =SUMIFS($U$41:$U$60,$R$41:$R$60,2027,$S$41:$S$60,8,$V$41:$V$60,"Y") -> 0 | I33: =SUMIFS($U$41:$U$60,$R$41:$R$60,2027,$S$41:$S$60,9,$V$41:$V$60,"Y") -> 0 | J33: =SUMIFS($U$41:$U$60,$R$41:$R$60,2027,$S$41:$S$60,10,$V$41:$V$60,"Y") -> 0 | K33: =SUMIFS($U$41:$U$60,$R$41:$R$60,2027,$S$41:$S$60,11,$V$41:$V$60,"Y") -> 0 | L33: =SUMIFS($U$41:$U$60,$R$41:$R$60,2027,$S$41:$S$60,12,$V$41:$V$60,"Y") -> 0
A35: 3. PTC details
A36: Budget | B36: =1248213+24756.78+137619.42+26480.58 -> 1437069.8 | C36: 26740 | D36: 267560 | E36: 421115.32 | F36: 498.6 | G36: 171 | H36: 5544 | I36: 24717 | J36: - | K36: 39.78 | L36: 556302 | M36: 62192 | N36: 3467289 | O36: 4367720
A37: Invoiced | B37: =SUM(B41:B77) -> 3946297.7 | C37: =SUM(C41:C60) -> 0 | D37: =SUM(D41:D60) -> 0 | E37: =SUM(E41:E60) -> 0 | F37: =SUM(F41:F60) -> 0 | G37: =SUM(G41:G60) -> 0 | H37: =SUM(H41:H60) -> 0 | I37: =SUM(I41:I60) -> 0 | J37: =SUM(J41:J60) -> 0 | ... O37: =SUM(O41:O60) -> 0
A38: Remaining | B38: =B36-B37 -> -2509227.9 | C38: =C36-C37 -> 26740 | D38: =D36-D37 -> 267560 | E38: =E36-E37 -> 421115.32 | F38: =F36-F37 -> 498.6 | G38: =G36-G37 -> 171 | H38: =H36-H37 -> 5544 | I38: =I36-I37 -> 24717 | ... O38: =O36-O37 -> 4367720
A39: Remaining (%) | C39: =C38/C36 -> 1 | D39: =D38/D36 -> 1 | E39: =E38/E36 -> 1 | F39: =F38/F36 -> 1 | G39: =G38/G36 -> 1 | H39: =H38/H36 -> 1 | I39: =I38/I36 -> 1 | J39: =J38/J36 -> #VALUE! | ... O39: =O38/O36 -> 1
A40: Invoice # | B40: Deposit (Budget 미포함) | C40: Office Supplies | D40: Monitoring Travel | E40: Regulatory/IRB/EC fees | F40: Document Indexing, QC and File Review | G40: Printing | H40: Teleconferences | I40: Miscellaneous Administrative Overhead | J40: Informed Consent Form | K40: DocuSign | L40: Clario | M40: Investigator Meetings Logistics | N40: Investigator Payments (North America) | O40: Investigator Payments (Asia Pacific) | P40: Invoiced Amount($) | Q40: Invoiced Date | R40: Paid Year | S40: Paid Month | T40: Paid Date | U40: Paid Amount(₩) | V40: Paid (Y) | W40: 지출결의 #
A41: SGP-030212 | B41: 26480.58 | P41: =SUM(B41:O41) -> 26480.58 | Q41: 45495 | R41: 2024 | S41: 8 | T41: 45512 | U41: 39720870 | V41: Y | W41: CD24-170
A42: SGP-030531 | B42: 137619.42 | P42: =SUM(B42:O42) -> 137619.42 | Q42: 45562 | R42: 2024 | S42: 10 | T42: 45575 | U42: 2.0642913e+08 | V42: Y | W42: CD24-220
A43: SGP-030532 | B43: 1248213 | P43: =SUM(B43:O43) -> 1248213 | Q43: 45562 | R43: 2024 | S43: 10 | T43: 45575 | V43: Y | W43: CD24-220
A44: SGP-030621 | B44: 439.55 | P44: =SUM(B44:O44) -> 439.55 | Q44: 45580 | R44: 2024 | S44: 10 | T44: 45589 | V44: Y | W44: CD24-225
A45: SGP-030789 | B45: 2626.46 | P45: =SUM(B45:O45) -> 2626.46 | Q45: 45617 | R45: 2024 | S45: 12 | T45: 45631 | V45: Y | W45: CD24-277
A46: SGP-030941 | B46: 2603.63 | P46: =SUM(B46:O46) -> 2603.63 | Q46: 45652 | R46: 2025 | S46: 1 | T46: 45659 | V46: Y | W46: CD24-289
A47: SGP-031090 | B47: 3495.17 | P47: =SUM(B47:O47) -> 3495.17 | Q47: 45699 | R47: 2025 | S47: 2 | T47: 45708 | V47: Y | W47: CD25-034
A48: SGP-031208 | B48: 28596.55 | P48: =SUM(B48:O48) -> 28596.55 | Q48: 45721 | R48: 2025 | S48: 3 | T48: 45736 | V48: Y | W48: CD25-045
A49: SGP-031300 | B49: 6399.93 | P49: =SUM(B49:O49) -> 6399.93 | Q49: 45740 | R49: 2025 | S49: 4 | T49: 45764 | V49: Y | W49: CD25-069
A50: SGP-031418 | B50: 22753.1 | P50: =SUM(B50:O50) -> 22753.1 | Q50: 45775 | R50: 2025 | S50: 5 | T50: 45799 | V50: Y | W50: CD25-086
A51: SGP-031520 | B51: 25045.7 | P51: =SUM(B51:O51) -> 25045.7 | Q51: 45799 | R51: 2025 | S51: 6 | T51: 45827 | V51: Y | W51: CD25-101
A52: SGP-031521 | B52: 6875.43 | P52: =SUM(B52:O52) -> 6875.43 | Q52: 45799 | R52: 2025 | S52: 6 | T52: 45827 | V52: Y | W52: CD25-101
A53: SGP-031653 | B53: 246916.46 | P53: =SUM(B53:O53) -> 246916.46 | Q53: 45842 | R53: 2025 | S53: 7 | T53: 45869 | V53: Y | W53: CD25-137
A54: SGP-031654 | B54: 33087.27 | P54: =SUM(B54:O54) -> 33087.27 | Q54: 45842 | R54: 2025 | S54: 7 | T54: 45869 | V54: Y | W54: CD25-137
... A74: SGP-033033 | B74: 95163.17 | P74: =SUM(B74:O74) -> 95163.17 | Q74: 46195 | R74: 2026 | S74: 7 | T74: 46212 | V74: Y | W74: CO26-045
P75: =SUM(B75:O75) -> 0
P76: =SUM(B76:O76) -> 0
P77: =SUM(B77:O77) -> 0
P78: =SUM(B78:O78) -> 0
P79: =SUM(B79:O79) -> 0
P80: =SUM(B80:O80) -> 0
P81: =SUM(B81:O81) -> 0
P82: =SUM(B82:O82) -> 0
P83: =SUM(B83:O83) -> 0
P84: =SUM(B84:O84) -> 0
P85: =SUM(B85:O85) -> 0
P86: =SUM(B86:O86) -> 0

Sheet 2. Syneos
A1: 1. CRO:Syneos
B2: Contract Number: | D2: Version & date:
A4: Protocol No: TTK-CS-101 | D4: Updated on:
A6: 1. Total Payment Status
A7: Category | B7: $ | C7: %
A8: Budget
A9: Paid | B9: =B14+B19+B24+B29+B34 -> 0 | C9: =B9/B8 -> #DIV/0!
A10: Remaining | B10: =B8-B9 -> 0 | C10: =B10/B8 -> #DIV/0!
A12: 2.Yearly and Monthly Payment
B13: USD | C13: KRW
A14: 2023 | B14: =SUM(A16:L16) -> 0 | C14: =SUM(A17:L17) -> 0
A15: 01 | B15: 02 | C15: 03 | D15: 04 | E15: 05 | F15: 06 | G15: 07 | H15: 08 | I15: 09 | J15: 10 | K15: 11 | L15: 12
A16: =SUMIFS($C$41:$C$61,$F$41:$F$61,2024,$G$41:$G$61,1,$J$41:$J$61,"Y") -> 0 | B16: =SUMIFS($C$41:$C$61,$F$41:$F$61,2024,$G$41:$G$61,2,$J$41:$J$61,"Y") -> 0 | C16: =SUMIFS($C$41:$C$61,$F$41:$F$61,2024,$G$41:$G$61,3,$J$41:$J$61,"Y") -> 0 | D16: =SUMIFS($C$41:$C$61,$F$41:$F$61,2024,$G$41:$G$61,4,$J$41:$J$61,"Y") -> 0 | E16: =SUMIFS($C$41:$C$61,$F$41:$F$61,2024,$G$41:$G$61,5,$J$41:$J$61,"Y") -> 0 | F16: =SUMIFS($C$41:$C$61,$F$41:$F$61,2024,$G$41:$G$61,6,$J$41:$J$61,"Y") -> 0 | G16: =SUMIFS($C$41:$C$61,$F$41:$F$61,2024,$G$41:$G$61,7,$J$41:$J$61,"Y") -> 0 | H16: =SUMIFS($C$41:$C$61,$F$41:$F$61,2024,$G$41:$G$61,8,$J$41:$J$61,"Y") -> 0 | I16: =SUMIFS($C$41:$C$61,$F$41:$F$61,2024,$G$41:$G$61,9,$J$41:$J$61,"Y") -> 0 | J16: =SUMIFS($C$41:$C$61,$F$41:$F$61,2024,$G$41:$G$61,10,$J$41:$J$61,"Y") -> 0 | K16: =SUMIFS($C$41:$C$61,$F$41:$F$61,2024,$G$41:$G$61,11,$J$41:$J$61,"Y") -> 0 | L16: =SUMIFS($C$41:$C$61,$F$41:$F$61,2024,$G$41:$G$61,12,$J$41:$J$61,"Y") -> 0
A17: =SUMIFS($I$41:$I$61,$F$41:$F$61,2024,$G$41:$G$61,1,$J$41:$J$61,"Y") -> 0 | B17: =SUMIFS($I$41:$I$61,$F$41:$F$61,2024,$G$41:$G$61,2,$J$41:$J$61,"Y") -> 0 | C17: =SUMIFS($I$41:$I$61,$F$41:$F$61,2024,$G$41:$G$61,3,$J$41:$J$61,"Y") -> 0 | D17: =SUMIFS($I$41:$I$61,$F$41:$F$61,2024,$G$41:$G$61,4,$J$41:$J$61,"Y") -> 0 | E17: =SUMIFS($I$41:$I$61,$F$41:$F$61,2024,$G$41:$G$61,5,$J$41:$J$61,"Y") -> 0 | F17: =SUMIFS($I$41:$I$61,$F$41:$F$61,2024,$G$41:$G$61,6,$J$41:$J$61,"Y") -> 0 | G17: =SUMIFS($I$41:$I$61,$F$41:$F$61,2024,$G$41:$G$61,7,$J$41:$J$61,"Y") -> 0 | H17: =SUMIFS($I$41:$I$61,$F$41:$F$61,2024,$G$41:$G$61,8,$J$41:$J$61,"Y") -> 0 | I17: =SUMIFS($I$41:$I$61,$F$41:$F$61,2024,$G$41:$G$61,9,$J$41:$J$61,"Y") -> 0 | J17: =SUMIFS($I$41:$I$61,$F$41:$F$61,2024,$G$41:$G$61,10,$J$41:$J$61,"Y") -> 0 | K17: =SUMIFS($I$41:$I$61,$F$41:$F$61,2024,$G$41:$G$61,11,$J$41:$J$61,"Y") -> 0 | L17: =SUMIFS($I$41:$I$61,$F$41:$F$61,2024,$G$41:$G$61,12,$J$41:$J$61,"Y") -> 0
A19: 2024 | B19: =SUM(A21:L21) -> 0 | C19: =SUM(A22:L22) -> 0
A20: 01 | B20: 02 | C20: 03 | D20: 04 | E20: 05 | F20: 06 | G20: 07 | H20: 08 | I20: 09 | J20: 10 | K20: 11 | L20: 12
A21: =SUMIFS($C$41:$C$61,$F$41:$F$61,2024,$G$41:$G$61,1,$J$41:$J$61,"Y") -> 0 | B21: =SUMIFS($C$41:$C$61,$F$41:$F$61,2024,$G$41:$G$61,2,$J$41:$J$61,"Y") -> 0 | C21: =SUMIFS($C$41:$C$61,$F$41:$F$61,2024,$G$41:$G$61,3,$J$41:$J$61,"Y") -> 0 | D21: =SUMIFS($C$41:$C$61,$F$41:$F$61,2024,$G$41:$G$61,4,$J$41:$J$61,"Y") -> 0 | E21: =SUMIFS($C$41:$C$61,$F$41:$F$61,2024,$G$41:$G$61,5,$J$41:$J$61,"Y") -> 0 | F21: =SUMIFS($C$41:$C$61,$F$41:$F$61,2024,$G$41:$G$61,6,$J$41:$J$61,"Y") -> 0 | G21: =SUMIFS($C$41:$C$61,$F$41:$F$61,2024,$G$41:$G$61,7,$J$41:$J$61,"Y") -> 0 | H21: =SUMIFS($C$41:$C$61,$F$41:$F$61,2024,$G$41:$G$61,8,$J$41:$J$61,"Y") -> 0 | I21: =SUMIFS($C$41:$C$61,$F$41:$F$61,2024,$G$41:$G$61,9,$J$41:$J$61,"Y") -> 0 | J21: =SUMIFS($C$41:$C$61,$F$41:$F$61,2024,$G$41:$G$61,10,$J$41:$J$61,"Y") -> 0 | K21: =SUMIFS($C$41:$C$61,$F$41:$F$61,2024,$G$41:$G$61,11,$J$41:$J$61,"Y") -> 0 | L21: =SUMIFS($C$41:$C$61,$F$41:$F$61,2024,$G$41:$G$61,12,$J$41:$J$61,"Y") -> 0
A22: =SUMIFS($I$41:$I$61,$F$41:$F$61,2024,$G$41:$G$61,1,$J$41:$J$61,"Y") -> 0 | B22: =SUMIFS($I$41:$I$61,$F$41:$F$61,2024,$G$41:$G$61,2,$J$41:$J$61,"Y") -> 0 | C22: =SUMIFS($I$41:$I$61,$F$41:$F$61,2024,$G$41:$G$61,3,$J$41:$J$61,"Y") -> 0 | D22: =SUMIFS($I$41:$I$61,$F$41:$F$61,2024,$G$41:$G$61,4,$J$41:$J$61,"Y") -> 0 | E22: =SUMIFS($I$41:$I$61,$F$41:$F$61,2024,$G$41:$G$61,5,$J$41:$J$61,"Y") -> 0 | F22: =SUMIFS($I$41:$I$61,$F$41:$F$61,2024,$G$41:$G$61,6,$J$41:$J$61,"Y") -> 0 | G22: =SUMIFS($I$41:$I$61,$F$41:$F$61,2024,$G$41:$G$61,7,$J$41:$J$61,"Y") -> 0 | H22: =SUMIFS($I$41:$I$61,$F$41:$F$61,2024,$G$41:$G$61,8,$J$41:$J$61,"Y") -> 0 | I22: =SUMIFS($I$41:$I$61,$F$41:$F$61,2024,$G$41:$G$61,9,$J$41:$J$61,"Y") -> 0 | J22: =SUMIFS($I$41:$I$61,$F$41:$F$61,2024,$G$41:$G$61,10,$J$41:$J$61,"Y") -> 0 | K22: =SUMIFS($I$41:$I$61,$F$41:$F$61,2024,$G$41:$G$61,11,$J$41:$J$61,"Y") -> 0 | L22: =SUMIFS($I$41:$I$61,$F$41:$F$61,2024,$G$41:$G$61,12,$J$41:$J$61,"Y") -> 0
A24: 2025 | B24: =SUM(A26:L26) -> 0 | C24: =SUM(A27:L27) -> 0
A25: 01 | B25: 02 | C25: 03 | D25: 04 | E25: 05 | F25: 06 | G25: 07 | H25: 08 | I25: 09 | J25: 10 | K25: 11 | L25: 12
A26: =SUMIFS($C$41:$C$61,$F$41:$F$61,2025,$G$41:$G$61,1,$J$41:$J$61,"Y") -> 0 | B26: =SUMIFS($C$41:$C$61,$F$41:$F$61,2025,$G$41:$G$61,2,$J$41:$J$61,"Y") -> 0 | C26: =SUMIFS($C$41:$C$61,$F$41:$F$61,2025,$G$41:$G$61,3,$J$41:$J$61,"Y") -> 0 | D26: =SUMIFS($C$41:$C$61,$F$41:$F$61,2025,$G$41:$G$61,4,$J$41:$J$61,"Y") -> 0 | E26: =SUMIFS($C$41:$C$61,$F$41:$F$61,2025,$G$41:$G$61,5,$J$41:$J$61,"Y") -> 0 | F26: =SUMIFS($C$41:$C$61,$F$41:$F$61,2025,$G$41:$G$61,6,$J$41:$J$61,"Y") -> 0 | G26: =SUMIFS($C$41:$C$61,$F$41:$F$61,2025,$G$41:$G$61,7,$J$41:$J$61,"Y") -> 0 | H26: =SUMIFS($C$41:$C$61,$F$41:$F$61,2025,$G$41:$G$61,8,$J$41:$J$61,"Y") -> 0 | I26: =SUMIFS($C$41:$C$61,$F$41:$F$61,2025,$G$41:$G$61,9,$J$41:$J$61,"Y") -> 0 | J26: =SUMIFS($C$41:$C$61,$F$41:$F$61,2025,$G$41:$G$61,10,$J$41:$J$61,"Y") -> 0 | K26: =SUMIFS($C$41:$C$61,$F$41:$F$61,2025,$G$41:$G$61,11,$J$41:$J$61,"Y") -> 0 | L26: =SUMIFS($C$41:$C$61,$F$41:$F$61,2025,$G$41:$G$61,12,$J$41:$J$61,"Y") -> 0
A27: =SUMIFS($I$41:$I$61,$F$41:$F$61,2025,$G$41:$G$61,1,$J$41:$J$61,"Y") -> 0 | B27: =SUMIFS($I$41:$I$61,$F$41:$F$61,2025,$G$41:$G$61,2,$J$41:$J$61,"Y") -> 0 | C27: =SUMIFS($I$41:$I$61,$F$41:$F$61,2025,$G$41:$G$61,3,$J$41:$J$61,"Y") -> 0 | D27: =SUMIFS($I$41:$I$61,$F$41:$F$61,2025,$G$41:$G$61,4,$J$41:$J$61,"Y") -> 0 | E27: =SUMIFS($I$41:$I$61,$F$41:$F$61,2025,$G$41:$G$61,5,$J$41:$J$61,"Y") -> 0 | F27: =SUMIFS($I$41:$I$61,$F$41:$F$61,2025,$G$41:$G$61,6,$J$41:$J$61,"Y") -> 0 | G27: =SUMIFS($I$41:$I$61,$F$41:$F$61,2025,$G$41:$G$61,7,$J$41:$J$61,"Y") -> 0 | H27: =SUMIFS($I$41:$I$61,$F$41:$F$61,2025,$G$41:$G$61,8,$J$41:$J$61,"Y") -> 0 | I27: =SUMIFS($I$41:$I$61,$F$41:$F$61,2025,$G$41:$G$61,9,$J$41:$J$61,"Y") -> 0 | J27: =SUMIFS($I$41:$I$61,$F$41:$F$61,2025,$G$41:$G$61,10,$J$41:$J$61,"Y") -> 0 | K27: =SUMIFS($I$41:$I$61,$F$41:$F$61,2025,$G$41:$G$61,11,$J$41:$J$61,"Y") -> 0 | L27: =SUMIFS($I$41:$I$61,$F$41:$F$61,2025,$G$41:$G$61,12,$J$41:$J$61,"Y") -> 0
A29: 2026 | B29: =SUM(A31:L31) -> 0 | C29: =SUM(A32:L32) -> 0
A30: 01 | B30: 02 | C30: 03 | D30: 04 | E30: 05 | F30: 06 | G30: 07 | H30: 08 | I30: 09 | J30: 10 | K30: 11 | L30: 12
A31: =SUMIFS($C$41:$C$61,$F$41:$F$61,2026,$G$41:$G$61,1,$J$41:$J$61,"Y") -> 0 | B31: =SUMIFS($C$41:$C$61,$F$41:$F$61,2026,$G$41:$G$61,2,$J$41:$J$61,"Y") -> 0 | C31: =SUMIFS($C$41:$C$61,$F$41:$F$61,2026,$G$41:$G$61,3,$J$41:$J$61,"Y") -> 0 | D31: =SUMIFS($C$41:$C$61,$F$41:$F$61,2026,$G$41:$G$61,4,$J$41:$J$61,"Y") -> 0 | E31: =SUMIFS($C$41:$C$61,$F$41:$F$61,2026,$G$41:$G$61,5,$J$41:$J$61,"Y") -> 0 | F31: =SUMIFS($C$41:$C$61,$F$41:$F$61,2026,$G$41:$G$61,6,$J$41:$J$61,"Y") -> 0 | G31: =SUMIFS($C$41:$C$61,$F$41:$F$61,2026,$G$41:$G$61,7,$J$41:$J$61,"Y") -> 0 | H31: =SUMIFS($C$41:$C$61,$F$41:$F$61,2026,$G$41:$G$61,8,$J$41:$J$61,"Y") -> 0 | I31: =SUMIFS($C$41:$C$61,$F$41:$F$61,2026,$G$41:$G$61,9,$J$41:$J$61,"Y") -> 0 | J31: =SUMIFS($C$41:$C$61,$F$41:$F$61,2026,$G$41:$G$61,10,$J$41:$J$61,"Y") -> 0 | K31: =SUMIFS($C$41:$C$61,$F$41:$F$61,2026,$G$41:$G$61,11,$J$41:$J$61,"Y") -> 0 | L31: =SUMIFS($C$41:$C$61,$F$41:$F$61,2026,$G$41:$G$61,12,$J$41:$J$61,"Y") -> 0
A32: =SUMIFS($I$41:$I$61,$F$41:$F$61,2026,$G$41:$G$61,1,$J$41:$J$61,"Y") -> 0 | B32: =SUMIFS($I$41:$I$61,$F$41:$F$61,2026,$G$41:$G$61,2,$J$41:$J$61,"Y") -> 0 | C32: =SUMIFS($I$41:$I$61,$F$41:$F$61,2026,$G$41:$G$61,3,$J$41:$J$61,"Y") -> 0 | D32: =SUMIFS($I$41:$I$61,$F$41:$F$61,2026,$G$41:$G$61,4,$J$41:$J$61,"Y") -> 0 | E32: =SUMIFS($I$41:$I$61,$F$41:$F$61,2026,$G$41:$G$61,5,$J$41:$J$61,"Y") -> 0 | F32: =SUMIFS($I$41:$I$61,$F$41:$F$61,2026,$G$41:$G$61,6,$J$41:$J$61,"Y") -> 0 | G32: =SUMIFS($I$41:$I$61,$F$41:$F$61,2026,$G$41:$G$61,7,$J$41:$J$61,"Y") -> 0 | H32: =SUMIFS($I$41:$I$61,$F$41:$F$61,2026,$G$41:$G$61,8,$J$41:$J$61,"Y") -> 0 | I32: =SUMIFS($I$41:$I$61,$F$41:$F$61,2026,$G$41:$G$61,9,$J$41:$J$61,"Y") -> 0 | J32: =SUMIFS($I$41:$I$61,$F$41:$F$61,2026,$G$41:$G$61,10,$J$41:$J$61,"Y") -> 0 | K32: =SUMIFS($I$41:$I$61,$F$41:$F$61,2026,$G$41:$G$61,11,$J$41:$J$61,"Y") -> 0 | L32: =SUMIFS($I$41:$I$61,$F$41:$F$61,2026,$G$41:$G$61,12,$J$41:$J$61,"Y") -> 0
A34: 2027 | B34: =SUM(A36:L36) -> 0 | C34: =SUM(A37:L37) -> 0
A35: 01 | B35: 02 | C35: 03 | D35: 04 | E35: 05 | F35: 06 | G35: 07 | H35: 08 | I35: 09 | J35: 10 | K35: 11 | L35: 12
A36: =SUMIFS($C$41:$C$61,$F$41:$F$61,2027,$G$41:$G$61,1,$J$41:$J$61,"Y") -> 0 | B36: =SUMIFS($C$41:$C$61,$F$41:$F$61,2027,$G$41:$G$61,2,$J$41:$J$61,"Y") -> 0 | C36: =SUMIFS($C$41:$C$61,$F$41:$F$61,2027,$G$41:$G$61,3,$J$41:$J$61,"Y") -> 0 | D36: =SUMIFS($C$41:$C$61,$F$41:$F$61,2027,$G$41:$G$61,4,$J$41:$J$61,"Y") -> 0 | E36: =SUMIFS($C$41:$C$61,$F$41:$F$61,2027,$G$41:$G$61,5,$J$41:$J$61,"Y") -> 0 | F36: =SUMIFS($C$41:$C$61,$F$41:$F$61,2027,$G$41:$G$61,6,$J$41:$J$61,"Y") -> 0 | G36: =SUMIFS($C$41:$C$61,$F$41:$F$61,2027,$G$41:$G$61,7,$J$41:$J$61,"Y") -> 0 | H36: =SUMIFS($C$41:$C$61,$F$41:$F$61,2027,$G$41:$G$61,8,$J$41:$J$61,"Y") -> 0 | I36: =SUMIFS($C$41:$C$61,$F$41:$F$61,2027,$G$41:$G$61,9,$J$41:$J$61,"Y") -> 0 | J36: =SUMIFS($C$41:$C$61,$F$41:$F$61,2027,$G$41:$G$61,10,$J$41:$J$61,"Y") -> 0 | K36: =SUMIFS($C$41:$C$61,$F$41:$F$61,2027,$G$41:$G$61,11,$J$41:$J$61,"Y") -> 0 | L36: =SUMIFS($C$41:$C$61,$F$41:$F$61,2027,$G$41:$G$61,12,$J$41:$J$61,"Y") -> 0
A37: =SUMIFS($I$41:$I$61,$F$41:$F$61,2027,$G$41:$G$61,1,$J$41:$J$61,"Y") -> 0 | B37: =SUMIFS($I$41:$I$61,$F$41:$F$61,2027,$G$41:$G$61,2,$J$41:$J$61,"Y") -> 0 | C37: =SUMIFS($I$41:$I$61,$F$41:$F$61,2027,$G$41:$G$61,3,$J$41:$J$61,"Y") -> 0 | D37: =SUMIFS($I$41:$I$61,$F$41:$F$61,2027,$G$41:$G$61,4,$J$41:$J$61,"Y") -> 0 | E37: =SUMIFS($I$41:$I$61,$F$41:$F$61,2027,$G$41:$G$61,5,$J$41:$J$61,"Y") -> 0 | F37: =SUMIFS($I$41:$I$61,$F$41:$F$61,2027,$G$41:$G$61,6,$J$41:$J$61,"Y") -> 0 | G37: =SUMIFS($I$41:$I$61,$F$41:$F$61,2027,$G$41:$G$61,7,$J$41:$J$61,"Y") -> 0 | H37: =SUMIFS($I$41:$I$61,$F$41:$F$61,2027,$G$41:$G$61,8,$J$41:$J$61,"Y") -> 0 | I37: =SUMIFS($I$41:$I$61,$F$41:$F$61,2027,$G$41:$G$61,9,$J$41:$J$61,"Y") -> 0 | J37: =SUMIFS($I$41:$I$61,$F$41:$F$61,2027,$G$41:$G$61,10,$J$41:$J$61,"Y") -> 0 | K37: =SUMIFS($I$41:$I$61,$F$41:$F$61,2027,$G$41:$G$61,11,$J$41:$J$61,"Y") -> 0 | L37: =SUMIFS($I$41:$I$61,$F$41:$F$61,2027,$G$41:$G$61,12,$J$41:$J$61,"Y") -> 0
A39: 3. Costs Details | B39: 분기별/연도별 사용 금액 파악위해, 이전 CO Budget만 Quarterly sub-sum으로 입력 (without Invoice/지결 #)
A40: Milestones | B40: Budget Amount($) | C40: Invoiced Amount($) | D40: Invoice # | E40: Invoiced Date | F40: Paid Year | G40: Paid Month | H40: Paid Date | I40: Total Amount(₩) | J40: Paid (Y) | K40: 지출결의 #

Sheet 3. Sharp
A1: 3. Sharp Clinical Services (Including Zuellig Pharma Korea)
B2: Contract Number: | C2: SLJ221013328 | D2: Version & date: | E2: CO1_23Sep2025
A4: Protocol No: TTK-CS-101 | D4: Updated on: | E4: =TODAY() -> 46226
A6: 1. Sub Total Cost Status
A7: Category | B7: $ | C7: %
A8: Budget | B8: =B193 -> 706859
A9: Paid | B9: =B13+B18+B23+B28+B33 -> 581898.39 | C9: =B9/B8 -> 0.82321706
A10: Remaining | B10: =B8-B9 -> 124960.61 | C10: =B10/B8 -> 0.17678294
A12: 2. Yearly and Monthly Payment
A13: 2023 | B13: =SUM(A15:L15) -> 94935.66 | C13: =SUM(A16:L16) -> 0
A14: 01 | B14: 02 | C14: 03 | D14: 04 | E14: 05 | F14: 06 | G14: 07 | H14: 08 | I14: 09 | J14: 10 | K14: 11 | L14: 12
A15: =SUMIFS($C$40:$C$193,$F$40:$F$193,2023,$G$40:$G$193,1,$J$40:$J$193,"Y") -> 2475 | B15: =SUMIFS($C$40:$C$193,$F$40:$F$193,2023,$G$40:$G$193,2,$J$40:$J$193,"Y") -> 0 | C15: =SUMIFS($C$40:$C$193,$F$40:$F$193,2023,$G$40:$G$193,3,$J$40:$J$193,"Y") -> 9792 | D15: =SUMIFS($C$40:$C$193,$F$40:$F$193,2023,$G$40:$G$193,4,$J$40:$J$193,"Y") -> 11106 | E15: =SUMIFS($C$40:$C$193,$F$40:$F$193,2023,$G$40:$G$193,5,$J$40:$J$193,"Y") -> 2005 | F15: =SUMIFS($C$40:$C$193,$F$40:$F$193,2023,$G$40:$G$193,6,$J$40:$J$193,"Y") -> 3222.47 | G15: =SUMIFS($C$40:$C$193,$F$40:$F$193,2023,$G$40:$G$193,7,$J$40:$J$193,"Y") -> 2126.08 | H15: =SUMIFS($C$40:$C$193,$F$40:$F$193,2023,$G$40:$G$193,8,$J$40:$J$193,"Y") -> 27227.25 | I15: =SUMIFS($C$40:$C$193,$F$40:$F$193,2023,$G$40:$G$193,9,$J$40:$J$193,"Y") -> 16699 | J15: =SUMIFS($C$40:$C$193,$F$40:$F$193,2023,$G$40:$G$193,10,$J$40:$J$193,"Y") -> 2393.79 | K15: =SUMIFS($C$40:$C$193,$F$40:$F$193,2023,$G$40:$G$193,11,$J$40:$J$193,"Y") -> 14365.67 | L15: =SUMIFS($C$40:$C$193,$F$40:$F$193,2023,$G$40:$G$193,12,$J$40:$J$193,"Y") -> 3523.4
A16: =SUMIFS($I$40:$I$193,$F$40:$F$193,2023,$G$40:$G$193,1,$J$40:$J$193,"Y") -> 0 | B16: =SUMIFS($I$40:$I$193,$F$40:$F$193,2023,$G$40:$G$193,2,$J$40:$J$193,"Y") -> 0 | C16: =SUMIFS($I$40:$I$193,$F$40:$F$193,2023,$G$40:$G$193,3,$J$40:$J$193,"Y") -> 0 | D16: =SUMIFS($I$40:$I$193,$F$40:$F$193,2023,$G$40:$G$193,4,$J$40:$J$193,"Y") -> 0 | E16: =SUMIFS($I$40:$I$193,$F$40:$F$193,2023,$G$40:$G$193,5,$J$40:$J$193,"Y") -> 0 | F16: =SUMIFS($I$40:$I$193,$F$40:$F$193,2023,$G$40:$G$193,6,$J$40:$J$193,"Y") -> 0 | G16: =SUMIFS($I$40:$I$193,$F$40:$F$193,2023,$G$40:$G$193,7,$J$40:$J$193,"Y") -> 0 | H16: =SUMIFS($I$40:$I$193,$F$40:$F$193,2023,$G$40:$G$193,8,$J$40:$J$193,"Y") -> 0 | I16: =SUMIFS($I$40:$I$193,$F$40:$F$193,2023,$G$40:$G$193,9,$J$40:$J$193,"Y") -> 0 | J16: =SUMIFS($I$40:$I$193,$F$40:$F$193,2023,$G$40:$G$193,10,$J$40:$J$193,"Y") -> 0 | K16: =SUMIFS($I$40:$I$193,$F$40:$F$193,2023,$G$40:$G$193,11,$J$40:$J$193,"Y") -> 0 | L16: =SUMIFS($I$40:$I$193,$F$40:$F$193,2023,$G$40:$G$193,12,$J$40:$J$193,"Y") -> 0
A18: 2024 | B18: =SUM(A20:L20) -> 130398.55 | C18: =SUM(A21:L21) -> 0
A19: 01 | B19: 02 | C19: 03 | D19: 04 | E19: 05 | F19: 06 | G19: 07 | H19: 08 | I19: 09 | J19: 10 | K19: 11 | L19: 12
A20: =SUMIFS($C$40:$C$193,$F$40:$F$193,2024,$G$40:$G$193,1,$J$40:$J$193,"Y") -> 1605 | B20: =SUMIFS($C$40:$C$193,$F$40:$F$193,2024,$G$40:$G$193,2,$J$40:$J$193,"Y") -> 5917.83 | C20: =SUMIFS($C$40:$C$193,$F$40:$F$193,2024,$G$40:$G$193,3,$J$40:$J$193,"Y") -> 0 | D20: =SUMIFS($C$40:$C$193,$F$40:$F$193,2024,$G$40:$G$193,4,$J$40:$J$193,"Y") -> 4278.77 | E20: =SUMIFS($C$40:$C$193,$F$40:$F$193,2024,$G$40:$G$193,5,$J$40:$J$193,"Y") -> 5386 | F20: =SUMIFS($C$40:$C$193,$F$40:$F$193,2024,$G$40:$G$193,6,$J$40:$J$193,"Y") -> 40209.8 | G20: =SUMIFS($C$40:$C$193,$F$40:$F$193,2024,$G$40:$G$193,7,$J$40:$J$193,"Y") -> 10282.08 | H20: =SUMIFS($C$40:$C$193,$F$40:$F$193,2024,$G$40:$G$193,8,$J$40:$J$193,"Y") -> 20090.3 | I20: =SUMIFS($C$40:$C$193,$F$40:$F$193,2024,$G$40:$G$193,9,$J$40:$J$193,"Y") -> 11292.28 | J20: =SUMIFS($C$40:$C$193,$F$40:$F$193,2024,$G$40:$G$193,10,$J$40:$J$193,"Y") -> 9961.76 | K20: =SUMIFS($C$40:$C$193,$F$40:$F$193,2024,$G$40:$G$193,11,$J$40:$J$193,"Y") -> 21374.73 | L20: =SUMIFS($C$40:$C$193,$F$40:$F$193,2024,$G$40:$G$193,12,$J$40:$J$193,"Y") -> 0
A21: =SUMIFS($I$40:$I$193,$F$40:$F$193,2024,$G$40:$G$193,1,$J$40:$J$193,"Y") -> 0 | B21: =SUMIFS($I$40:$I$193,$F$40:$F$193,2024,$G$40:$G$193,2,$J$40:$J$193,"Y") -> 0 | C21: =SUMIFS($I$40:$I$193,$F$40:$F$193,2024,$G$40:$G$193,3,$J$40:$J$193,"Y") -> 0 | D21: =SUMIFS($I$40:$I$193,$F$40:$F$193,2024,$G$40:$G$193,4,$J$40:$J$193,"Y") -> 0 | E21: =SUMIFS($I$40:$I$193,$F$40:$F$193,2024,$G$40:$G$193,5,$J$40:$J$193,"Y") -> 0 | F21: =SUMIFS($I$40:$I$193,$F$40:$F$193,2024,$G$40:$G$193,6,$J$40:$J$193,"Y") -> 0 | G21: =SUMIFS($I$40:$I$193,$F$40:$F$193,2024,$G$40:$G$193,7,$J$40:$J$193,"Y") -> 0 | H21: =SUMIFS($I$40:$I$193,$F$40:$F$193,2024,$G$40:$G$193,8,$J$40:$J$193,"Y") -> 0 | I21: =SUMIFS($I$40:$I$193,$F$40:$F$193,2024,$G$40:$G$193,9,$J$40:$J$193,"Y") -> 0 | J21: =SUMIFS($I$40:$I$193,$F$40:$F$193,2024,$G$40:$G$193,10,$J$40:$J$193,"Y") -> 0 | K21: =SUMIFS($I$40:$I$193,$F$40:$F$193,2024,$G$40:$G$193,11,$J$40:$J$193,"Y") -> 0 | L21: =SUMIFS($I$40:$I$193,$F$40:$F$193,2024,$G$40:$G$193,12,$J$40:$J$193,"Y") -> 0
A23: 2025 | B23: =SUM(A25:L25) -> 264219.23 | C23: =SUM(A26:L26) -> 0
A24: 01 | B24: 02 | C24: 03 | D24: 04 | E24: 05 | F24: 06 | G24: 07 | H24: 08 | I24: 09 | J24: 10 | K24: 11 | L24: 12
A25: =SUMIFS($C$40:$C$193,$F$40:$F$193,2025,$G$40:$G$193,1,$J$40:$J$193,"Y") -> 13016.78 | B25: =SUMIFS($C$40:$C$193,$F$40:$F$193,2025,$G$40:$G$193,2,$J$40:$J$193,"Y") -> 10223.34 | C25: =SUMIFS($C$40:$C$193,$F$40:$F$193,2025,$G$40:$G$193,3,$J$40:$J$193,"Y") -> 2184.53 | D25: =SUMIFS($C$40:$C$193,$F$40:$F$193,2025,$G$40:$G$193,4,$J$40:$J$193,"Y") -> 16658 | E25: =SUMIFS($C$40:$C$193,$F$40:$F$193,2025,$G$40:$G$193,5,$J$40:$J$193,"Y") -> 19924.01 | F25: =SUMIFS($C$40:$C$193,$F$40:$F$193,2025,$G$40:$G$193,6,$J$40:$J$193,"Y") -> 31779.4 | G25: =SUMIFS($C$40:$C$193,$F$40:$F$193,2025,$G$40:$G$193,7,$J$40:$J$193,"Y") -> 30986.18 | H25: =SUMIFS($C$40:$C$193,$F$40:$F$193,2025,$G$40:$G$193,8,$J$40:$J$193,"Y") -> 11353.64 | I25: =SUMIFS($C$40:$C$193,$F$40:$F$193,2025,$G$40:$G$193,9,$J$40:$J$193,"Y") -> 57782.6 | J25: =SUMIFS($C$40:$C$193,$F$40:$F$193,2025,$G$40:$G$193,10,$J$40:$J$193,"Y") -> 39283.52 | K25: =SUMIFS($C$40:$C$193,$F$40:$F$193,2025,$G$40:$G$193,11,$J$40:$J$193,"Y") -> 14311.95 | L25: =SUMIFS($C$40:$C$193,$F$40:$F$193,2025,$G$40:$G$193,12,$J$40:$J$193,"Y") -> 16715.28
A26: =SUMIFS($I$40:$I$193,$F$40:$F$193,2025,$G$40:$G$193,1,$J$40:$J$193,"Y") -> 0 | B26: =SUMIFS($I$40:$I$193,$F$40:$F$193,2025,$G$40:$G$193,2,$J$40:$J$193,"Y") -> 0 | C26: =SUMIFS($I$40:$I$193,$F$40:$F$193,2025,$G$40:$G$193,3,$J$40:$J$193,"Y") -> 0 | D26: =SUMIFS($I$40:$I$193,$F$40:$F$193,2025,$G$40:$G$193,4,$J$40:$J$193,"Y") -> 0 | E26: =SUMIFS($I$40:$I$193,$F$40:$F$193,2025,$G$40:$G$193,5,$J$40:$J$193,"Y") -> 0 | F26: =SUMIFS($I$40:$I$193,$F$40:$F$193,2025,$G$40:$G$193,6,$J$40:$J$193,"Y") -> 0 | G26: =SUMIFS($I$40:$I$193,$F$40:$F$193,2025,$G$40:$G$193,7,$J$40:$J$193,"Y") -> 0 | H26: =SUMIFS($I$40:$I$193,$F$40:$F$193,2025,$G$40:$G$193,8,$J$40:$J$193,"Y") -> 0 | I26: =SUMIFS($I$40:$I$193,$F$40:$F$193,2025,$G$40:$G$193,9,$J$40:$J$193,"Y") -> 0 | J26: =SUMIFS($I$40:$I$193,$F$40:$F$193,2025,$G$40:$G$193,10,$J$40:$J$193,"Y") -> 0 | K26: =SUMIFS($I$40:$I$193,$F$40:$F$193,2025,$G$40:$G$193,11,$J$40:$J$193,"Y") -> 0 | L26: =SUMIFS($I$40:$I$193,$F$40:$F$193,2025,$G$40:$G$193,12,$J$40:$J$193,"Y") -> 0
A28: 2026 | B28: =SUM(A30:L30) -> 92344.95 | C28: =SUM(A31:L31) -> 0
A29: 01 | B29: 02 | C29: 03 | D29: 04 | E29: 05 | F29: 06 | G29: 07 | H29: 08 | I29: 09 | J29: 10 | K29: 11 | L29: 12
A30: =SUMIFS($C$40:$C$193,$F$40:$F$193,2026,$G$40:$G$193,1,$J$40:$J$193,"Y") -> 10877.97 | B30: =SUMIFS($C$40:$C$193,$F$40:$F$193,2026,$G$40:$G$193,2,$J$40:$J$193,"Y") -> 26519.9 | C30: =SUMIFS($C$40:$C$193,$F$40:$F$193,2026,$G$40:$G$193,3,$J$40:$J$193,"Y") -> 11603.99 | D30: =SUMIFS($C$40:$C$193,$F$40:$F$193,2026,$G$40:$G$193,4,$J$40:$J$193,"Y") -> 12404.26 | E30: =SUMIFS($C$40:$C$193,$F$40:$F$193,2026,$G$40:$G$193,5,$J$40:$J$193,"Y") -> 14311.06 | F30: =SUMIFS($C$40:$C$193,$F$40:$F$193,2026,$G$40:$G$193,6,$J$40:$J$193,"Y") -> 12211.97 | G30: =SUMIFS($C$40:$C$193,$F$40:$F$193,2026,$G$40:$G$193,7,$J$40:$J$193,"Y") -> 4415.8 | H30: =SUMIFS($C$40:$C$193,$F$40:$F$193,2026,$G$40:$G$193,8,$J$40:$J$193,"Y") -> 0 | I30: =SUMIFS($C$40:$C$193,$F$40:$F$193,2026,$G$40:$G$193,9,$J$40:$J$193,"Y") -> 0 | J30: =SUMIFS($C$40:$C$193,$F$40:$F$193,2026,$G$40:$G$193,10,$J$40:$J$193,"Y") -> 0 | K30: =SUMIFS($C$40:$C$193,$F$40:$F$193,2026,$G$40:$G$193,11,$J$40:$J$193,"Y") -> 0 | L30: =SUMIFS($C$40:$C$193,$F$40:$F$193,2026,$G$40:$G$193,12,$J$40:$J$193,"Y") -> 0
A31: =SUMIFS($I$40:$I$193,$F$40:$F$193,2026,$G$40:$G$193,1,$J$40:$J$193,"Y") -> 0 | B31: =SUMIFS($I$40:$I$193,$F$40:$F$193,2026,$G$40:$G$193,2,$J$40:$J$193,"Y") -> 0 | C31: =SUMIFS($I$40:$I$193,$F$40:$F$193,2026,$G$40:$G$193,3,$J$40:$J$193,"Y") -> 0 | D31: =SUMIFS($I$40:$I$193,$F$40:$F$193,2026,$G$40:$G$193,4,$J$40:$J$193,"Y") -> 0 | E31: =SUMIFS($I$40:$I$193,$F$40:$F$193,2026,$G$40:$G$193,5,$J$40:$J$193,"Y") -> 0 | F31: =SUMIFS($I$40:$I$193,$F$40:$F$193,2026,$G$40:$G$193,6,$J$40:$J$193,"Y") -> 0 | G31: =SUMIFS($I$40:$I$193,$F$40:$F$193,2026,$G$40:$G$193,7,$J$40:$J$193,"Y") -> 0 | H31: =SUMIFS($I$40:$I$193,$F$40:$F$193,2026,$G$40:$G$193,8,$J$40:$J$193,"Y") -> 0 | I31: =SUMIFS($I$40:$I$193,$F$40:$F$193,2026,$G$40:$G$193,9,$J$40:$J$193,"Y") -> 0 | J31: =SUMIFS($I$40:$I$193,$F$40:$F$193,2026,$G$40:$G$193,10,$J$40:$J$193,"Y") -> 0 | K31: =SUMIFS($I$40:$I$193,$F$40:$F$193,2026,$G$40:$G$193,11,$J$40:$J$193,"Y") -> 0 | L31: =SUMIFS($I$40:$I$193,$F$40:$F$193,2026,$G$40:$G$193,12,$J$40:$J$193,"Y") -> 0
A33: 2027 | B33: =SUM(A35:L35) -> 0 | C33: =SUM(A36:L36) -> 0
A34: 01 | B34: 02 | C34: 03 | D34: 04 | E34: 05 | F34: 06 | G34: 07 | H34: 08 | I34: 09 | J34: 10 | K34: 11 | L34: 12
A35: =SUMIFS($C$40:$C$193,$F$40:$F$193,2027,$G$40:$G$193,1,$J$40:$J$193,"Y") -> 0 | B35: =SUMIFS($C$40:$C$193,$F$40:$F$193,2027,$G$40:$G$193,2,$J$40:$J$193,"Y") -> 0 | C35: =SUMIFS($C$40:$C$193,$F$40:$F$193,2027,$G$40:$G$193,3,$J$40:$J$193,"Y") -> 0 | D35: =SUMIFS($C$40:$C$193,$F$40:$F$193,2027,$G$40:$G$193,4,$J$40:$J$193,"Y") -> 0 | E35: =SUMIFS($C$40:$C$193,$F$40:$F$193,2027,$G$40:$G$193,5,$J$40:$J$193,"Y") -> 0 | F35: =SUMIFS($C$40:$C$193,$F$40:$F$193,2027,$G$40:$G$193,6,$J$40:$J$193,"Y") -> 0 | G35: =SUMIFS($C$40:$C$193,$F$40:$F$193,2027,$G$40:$G$193,7,$J$40:$J$193,"Y") -> 0 | H35: =SUMIFS($C$40:$C$193,$F$40:$F$193,2027,$G$40:$G$193,8,$J$40:$J$193,"Y") -> 0 | I35: =SUMIFS($C$40:$C$193,$F$40:$F$193,2027,$G$40:$G$193,9,$J$40:$J$193,"Y") -> 0 | J35: =SUMIFS($C$40:$C$193,$F$40:$F$193,2027,$G$40:$G$193,10,$J$40:$J$193,"Y") -> 0 | K35: =SUMIFS($C$40:$C$193,$F$40:$F$193,2027,$G$40:$G$193,11,$J$40:$J$193,"Y") -> 0 | L35: =SUMIFS($C$40:$C$193,$F$40:$F$193,2027,$G$40:$G$193,12,$J$40:$J$193,"Y") -> 0
A36: =SUMIFS($I$40:$I$193,$F$40:$F$193,2027,$G$40:$G$193,1,$J$40:$J$193,"Y") -> 0 | B36: =SUMIFS($I$40:$I$193,$F$40:$F$193,2027,$G$40:$G$193,2,$J$40:$J$193,"Y") -> 0 | C36: =SUMIFS($I$40:$I$193,$F$40:$F$193,2027,$G$40:$G$193,3,$J$40:$J$193,"Y") -> 0 | D36: =SUMIFS($I$40:$I$193,$F$40:$F$193,2027,$G$40:$G$193,4,$J$40:$J$193,"Y") -> 0 | E36: =SUMIFS($I$40:$I$193,$F$40:$F$193,2027,$G$40:$G$193,5,$J$40:$J$193,"Y") -> 0 | F36: =SUMIFS($I$40:$I$193,$F$40:$F$193,2027,$G$40:$G$193,6,$J$40:$J$193,"Y") -> 0 | G36: =SUMIFS($I$40:$I$193,$F$40:$F$193,2027,$G$40:$G$193,7,$J$40:$J$193,"Y") -> 0 | H36: =SUMIFS($I$40:$I$193,$F$40:$F$193,2027,$G$40:$G$193,8,$J$40:$J$193,"Y") -> 0 | I36: =SUMIFS($I$40:$I$193,$F$40:$F$193,2027,$G$40:$G$193,9,$J$40:$J$193,"Y") -> 0 | J36: =SUMIFS($I$40:$I$193,$F$40:$F$193,2027,$G$40:$G$193,10,$J$40:$J$193,"Y") -> 0 | K36: =SUMIFS($I$40:$I$193,$F$40:$F$193,2027,$G$40:$G$193,11,$J$40:$J$193,"Y") -> 0 | L36: =SUMIFS($I$40:$I$193,$F$40:$F$193,2027,$G$40:$G$193,12,$J$40:$J$193,"Y") -> 0
A38: 3. Costs Details
A39: Services | B39: Budget Amount($) | C39: Invoiced Amount($) | D39: Invoice # | E39: Invoiced Date | F39: Paid Year | G39: Paid Month | H39: Paid Date | I39: Total Amount(₩) | J39: Paid (Y) | K39: 지출결의 #
A40: Project Set-up | C40: 1500 | D40: 5200065045 | E40: 44925 | F40: =YEAR(H40) -> 2023 | G40: =MONTH(H40) -> 1 | H40: 44955 | I40: 0 | J40: Y
A41: Depot Set-up | C41: 975 | D41: 5200065045 | E41: 44925 | F41: =YEAR(H41) -> 2023 | G41: =MONTH(H41) -> 1 | H41: 44955 | I41: 0 | J41: Y
A42: BAL0891 Cam 1: Carton & Vial Labels | C42: 1500 | D42: 5200066793 | E42: 44985 | F42: =YEAR(H42) -> 2023 | G42: =MONTH(H42) -> 3 | H42: 45015 | I42: 0 | J42: Y
A43: BAL0891 Cam 1: Secondary Pacakging | C43: 8292 | D43: 5200066793 | E43: 44985 | F43: =YEAR(H43) -> 2023 | G43: =MONTH(H43) -> 3 | H43: 45015 | I43: 0 | J43: Y
A44: BAL0891 Cam 2: Carton & Vial Labels | C44: 1500 | D44: 5200067550 | E44: 45016 | F44: =YEAR(H44) -> 2023 | G44: =MONTH(H44) -> 4 | H44: 45041 | I44: 0 | J44: Y | K44: CD23-033
A45: BAL0891 Cam 2: Secondary Packaging | C45: 8061 | D45: 5200067550 | E45: 45016 | F45: =YEAR(H45) -> 2023 | G45: =MONTH(H45) -> 4 | H45: 45041 | I45: 0 | J45: Y | K45: CD23-033
A46: BAL0891 Cam 2: Retest Extension Labels KOR | C46: 750 | D46: 5200070887 | E46: 45138 | F46: =YEAR(H46) -> 2023 | G46: =MONTH(H46) -> 8 | H46: 45168 | I46: 0 | J46: Y
A47: BAL0891 Cam 3: Carton & Vial Labels | C47: 1500 | D47: 5200070887 | E47: 45138 | F47: =YEAR(H47) -> 2023 | G47: =MONTH(H47) -> 8 | H47: 45168 | I47: 0 | J47: Y
A48: BAL0891 Cam 3: Secondary Packaging | C48: 8292 | D48: 5200071287 | E48: 45169 | F48: =YEAR(H48) -> 2023 | G48: =MONTH(H48) -> 9 | H48: 45199 | I48: 0 | J48: Y
A49: BAL0891 Cam 3: Retest Extension Labels KOR | C49: 1500 | D49: 5200073239 | E49: 45230 | F49: =YEAR(H49) -> 2023 | G49: =MONTH(H49) -> 11 | H49: 45260 | I49: 0 | J49: Y
A50: BAL0891 Cam 4: Retest Extension Labels US | C50: 750 | D50: 5200070887 | E50: 45138 | F50: =YEAR(H50) -> 2023 | G50: =MONTH(H50) -> 8 | H50: 45168 | I50: 0 | J50: Y
A51: BAL0891 Cam 4: Secondary Packaging | C51: 8407 | D51: 5200071287 | E51: 45169 | F51: =YEAR(H51) -> 2023 | G51: =MONTH(H51) -> 9 | H51: 45199 | I51: 0 | J51: Y
A52: BAL0891 Cam 5: Cartons & Foam Inserts | C52: 2220 | D52: 5200077497 | E52: 45412 | F52: =YEAR(H52) -> 2024 | G52: =MONTH(H52) -> 5 | H52: 45435 | I52: 0 | J52: Y | K52: CD24-100
A53: BAL0891 Cam 5: Carton & Vial Labels | C53: 2061 | D53: 5200077547 | E53: 45412 | F53: =YEAR(H53) -> 2024 | G53: =MONTH(H53) -> 5 | H53: 45435 | I53: 0 | J53: Y | K53: CD24-100
A54: BAL0891 Cam 5: Secondary Packaging | C54: 9459 | D54: 5200078686 | E54: 45442 | F54: =YEAR(H54) -> 2024 | G54: =MONTH(H54) -> 6 | H54: 45463 | I54: 0 | J54: Y | K54: CD24-119
A55: BAL0891 Cam 5: Expiry Extension Labels | C55: 3000 | D55: 5200085214 | E55: 45778 | F55: =YEAR(H55) -> 2025 | G55: =MONTH(H55) -> 6 | H55: 45813 | I55: 0 | J55: Y | K55: CD25-103
A56: BAL0891 Cam 6, 7 & 8: Carton & Foam Insert | C56: 6026 | D56: 5200088722 | E56: 45777 | F56: =YEAR(H56) -> 2025 | G56: =MONTH(H56) -> 6 | H56: 45813 | I56: 0 | J56: Y | K56: CD25-103
A57: BAL0891 Cam 6: PM & Batch Record | C57: 3000 | D57: 5200088906 | E57: 45777 | F57: =YEAR(H57) -> 2025 | G57: =MONTH(H57) -> 5 | H57: 45799 | I57: 0 | J57: Y | K57: CD25-091
A58: BAL0891 Cam 6: Carton & Vial Labels | C58: 1575 | D58: 5200089927 | E58: 45808 | F58: =YEAR(H58) -> 2025 | G58: =MONTH(H58) -> 7 | H58: 45841 | I58: 0 | J58: Y | K58: CD25-121
A59: BAL0891 Cam 6: Secondary Packaging | C59: 9455 | D59: 5200092006 | E59: 45869 | F59: =YEAR(H59) -> 2025 | G59: =MONTH(H59) -> 10 | H59: 45960 | I59: 0 | J59: Y | K59: CD25-197
A60: BAL0891 Cam 7: Carton & Vial Labels | C60: 2372 | D60: 5200092634 | E60: 45896 | F60: =YEAR(H60) -> 2025 | G60: =MONTH(H60) -> 9 | H60: 45911 | I60: 0 | J60: Y | K60: CD25-175
A61: BAL0891 Cam 7: Secondary Packaging | C61: 9862 | D61: 5200092634 | E61: 45896 | F61: =YEAR(H61) -> 2025 | G61: =MONTH(H61) -> 9 | H61: 45911 | I61: 0 | J61: Y | K61: CD25-175
A62: BAL0891 Cam 8: Carton & Vial Labels | C62: 2394 | D62: 5200092634 | E62: 45896 | F62: =YEAR(H62) -> 2025 | G62: =MONTH(H62) -> 9 | H62: 45911 | I62: 0 | J62: Y | K62: CD25-175
A63: BAL0891 Cam 8: Secondary Packaging | C63: 9897 | D63: 5200092634 | E63: 45896 | F63: =YEAR(H63) -> 2025 | G63: =MONTH(H63) -> 9 | H63: 45911 | I63: 0 | J63: Y | K63: CD25-175
... A72: BAL0891 Cam 9 & 10: Carton & Foam Inserts | C72: 8018 | D72: 5200096418 | E72: 46000 | F72: =YEAR(H72) -> 2025 | G72: =MONTH(H72) -> 12 | H72: 46015 | I72: 0 | J72: Y | K72: CD25-223
A73: BAL0891 Cam 9: Retest Date Extension Labels | C73: 1575 | D73: 5200104684 | E73: 46203 | F73: 2026 | G73: 7 | H73: 46226 | I73: 0 | J73: Y | K73: CO26-050
A74: Paclitaxel Cam 1: Northstar Drug Procurement | C74: 18192 | D74: 5200078157 | E74: 45433 | F74: =YEAR(H74) -> 2024 | G74: =MONTH(H74) -> 6 | H74: 45456 | I74: 0 | J74: Y | K74: CD24-113
A75: Paclitaxel Cam 1: Carton & Vial Labels US/KOR | C75: 1576 | D75: 5200080808 | E75: 45504 | F75: =YEAR(H75) -> 2024 | G75: =MONTH(H75) -> 8 | H75: 45526 | I75: 0 | J75: Y | K75: CD24-177
A76: Paclitaxel Cam 1: Secondary Packaging US/KOR | C76: 16000 | D76: 5200081832 | E76: 45778 | F76: =YEAR(H76) -> 2025 | G76: =MONTH(H76) -> 6 | H76: 45813 | I76: 0 | J76: Y | K76: CD25-103
A77: Paclitaxel Cam 2: Northstar Drug Procurement | C77: 14523 | D77: 5200087108 | E77: 45736 | F77: =YEAR(H77) -> 2025 | G77: =MONTH(H77) -> 4 | H77: 45750 | I77: 0 | J77: Y | K77: CD25-058
A78: Paclitaxel Cam 2: Secondary Packaging | C78: 8000 | D78: 5200089927 | E78: 45808 | F78: =YEAR(H78) -> 2025 | G78: =MONTH(H78) -> 7 | H78: 45841 | I78: 0 | J78: Y | K78: CD25-121
A79: Paclitaxel Cam 2: Carton & Vial Labels | C79: 1575 | D79: 5200089927 | E79: 45808 | F79: =YEAR(H79) -> 2025 | G79: =MONTH(H79) -> 7 | H79: 45841 | I79: 0 | J79: Y | K79: CD25-121
A80: Paclitaxel Cam 3: Secondary Packaging | C80: 8400 | D80: 5200103463 | E80: 46173 | F80: 2026 | G80: 6 | H80: 46191 | I80: 0 | J80: Y | K80: CO26-031
A81: Paclitaxel Cam 3: Project Management | C81: 2500 | D81: 5200101056 | E81: 46112 | F81: 2026 | G81: 4 | H81: 46135 | I81: 0 | J81: Y | K81: CO26-003
A82: Sharp Services: 2022.09 to 2023.02 (Basilea) | C82: 24227.25 | D82: 101 299 | E82: 45119 | F82: =YEAR(H82) -> 2023 | G82: =MONTH(H82) -> 8 | H82: 45149 | I82: 0 | J82: Y
A83: Sharp Services: 2023.03 | C83: 1545 | D83: 5200067172 | E83: 45013 | F83: =YEAR(H83) -> 2023 | G83: =MONTH(H83) -> 4 | H83: 45041 | I83: 0 | J83: Y | K83: CD23-033
A84: Sharp Services: 2023.04 | C84: 2005 | D84: 5200068500 | E84: 45044 | F84: =YEAR(H84) -> 2023 | G84: =MONTH(H84) -> 5 | H84: 45074 | I84: 0 | J84: Y
A85: Sharp Services: 2023.05 | C85: 3222.47 | D85: 5200069200 | E85: 45077 | F85: =YEAR(H85) -> 2023 | G85: =MONTH(H85) -> 6 | H85: 45107 | I85: 0 | J85: Y
A86: Zuellig Services: 2023.05 | C86: 4087.2 | D86: 5200070199 | E86: 45482 | F86: =YEAR(H86) -> 2025 | G86: =MONTH(H86) -> 8 | H86: 45870 | I86: 0 | J86: Y | K86: CD24-159
A87: Sharp Services: 2023.06 | C87: 2784 | D87: 5200070171 | E87: 45482 | F87: =YEAR(H87) -> 2024 | G87: =MONTH(H87) -> 8 | H87: 45505 | I87: 0 | J87: Y | K87: CD24-156
A88: Zuellig Services: 2023.06 | C88: =3942.4 -> 3942.4 | D88: 5200079105 | E88: 45456 | F88: =YEAR(H88) -> 2024 | G88: =MONTH(H88) -> 7 | H88: 45486 | I88: 0 | J88: Y
A89: Zuellig Services: 2023.06 (Credit) | C89: -806 | D89: 5200075835 | E89: 45349 | F89: =YEAR(H89) -> 2024 | G89: =MONTH(H89) -> 7 | H89: 45486 | I89: 0 | J89: Y
A90: Sharp Services: 2023.07 | C90: 2126.08 | D90: 5200070877 | E90: 45108 | F90: =YEAR(H90) -> 2023 | G90: =MONTH(H90) -> 7 | H90: 45138 | I90: 0 | J90: Y
A91: Zuellig Services: 2023.07 | C91: 873.6 | D91: 5200072442 | E91: 45211 | F91: =YEAR(H91) -> 2023 | G91: =MONTH(H91) -> 11 | H91: 45241 | I91: 0 | J91: Y
A92: Sharp Services: 2023.08 | C92: 2393.79 | D92: 5200071638 | E92: 45183 | F92: =YEAR(H92) -> 2023 | G92: =MONTH(H92) -> 10 | H92: 45213 | I92: 0 | J92: Y
A93: Zuellig Services: 2023.08 | C93: 873.6 | D93: 5200072441 | E93: 45211 | F93: =YEAR(H93) -> 2023 | G93: =MONTH(H93) -> 11 | H93: 45241 | I93: 0 | J93: Y
A94: Sharp Services: 2023.09 | C94: 5589.27 | D94: 5200072333 | E94: 45208 | F94: =YEAR(H94) -> 2023 | G94: =MONTH(H94) -> 11 | H94: 45238 | I94: 0 | J94: Y
A95: Zuellig Services: 2023.09 | C95: 4202.2 | D95: 5200072541 | E95: 45222 | F95: =YEAR(H95) -> 2023 | G95: =MONTH(H95) -> 11 | H95: 45252 | I95: 0 | J95: Y
A96: Sharp Services: 2023.10 | C96: 1327 | D96: 5200073166 | E96: 45226 | F96: =YEAR(H96) -> 2023 | G96: =MONTH(H96) -> 11 | H96: 45256 | I96: 0 | J96: Y
A97: Zuellig Services: 2023.10 | C97: 2418.4 | D97: 5200073887 | E97: 45260 | F97: =YEAR(H97) -> 2023 | G97: =MONTH(H97) -> 12 | H97: 45290 | I97: 0 | J97: Y
A98: Sharp Services: 2023.11 | C98: 1105 | D98: 5200074050 | E98: 45260 | F98: =YEAR(H98) -> 2023 | G98: =MONTH(H98) -> 12 | H98: 45290 | I98: 0 | J98: Y
A99: Zuellig Services: 2023.11 | C99: 1882.8 | D99: 5200074353 | E99: 45287 | F99: =YEAR(H99) -> 2024 | G99: =MONTH(H99) -> 2 | H99: 45330 | I99: 0 | J99: Y | K99: CD24-024
A100: Sharp Services: 2023.12 | C100: 1605 | D100: 5200074453 | E100: 45287 | F100: =YEAR(H100) -> 2024 | G100: =MONTH(H100) -> 1 | H100: 45309 | I100: 0 | J100: Y | K100: CD24-010
A101: Zuellig Services: 2023.12 | C101: 1882.8 | D101: 5200075141 | E101: 45314 | F101: =YEAR(H101) -> 2024 | G101: =MONTH(H101) -> 2 | H101: 45330 | I101: 0 | J101: Y | K101: CD24-024
A102: Sharp Services: 2024.01 | C102: 1501.88 | D102: 5200075740 | E102: 45323 | F102: =YEAR(H102) -> 2024 | G102: =MONTH(H102) -> 2 | H102: 45344 | I102: 0 | J102: Y | K102: CD24-043
A103: Sharp Services: 2024.01 (PM & Freight) | C103: 650.35 | D103: 5200075741 | E103: 45324 | F103: =YEAR(H103) -> 2024 | G103: =MONTH(H103) -> 2 | H103: 45344 | I103: 0 | J103: Y | K103: CD24-043
A104: Zuellig Services: 2024.01 | C104: 1258.4 | D104: 5200076555 | E104: 45376 | F104: =YEAR(H104) -> 2024 | G104: =MONTH(H104) -> 4 | H104: 45400 | I104: 0 | J104: Y | K104: CD24-078
A105: Sharp Services: 2024.02 | C105: 3020.37 | D105: 5200076461 | E105: 45365 | F105: =YEAR(H105) -> 2024 | G105: =MONTH(H105) -> 4 | H105: 45386 | I105: 0 | J105: Y | K105: CD24-069
A106: Sharp Services: 2024.02 (PM) | C106: 500 | D106: 5200078947 | E106: 45453 | F106: =YEAR(H106) -> 2024 | G106: =MONTH(H106) -> 7 | H106: 45477 | I106: 0 | J106: Y | K106: CD24-130
A107: Zuellig Services: 2024.02 | C107: 6844.4 | D107: 5200078052 | E107: 45427 | F107: =YEAR(H107) -> 2024 | G107: =MONTH(H107) -> 10 | H107: 45575 | I107: 0 | J107: Y | K107: CD24-211
A108: Sharp Services: 2024.03 | C108: 1105 | D108: 5200077260 | E108: 45397 | F108: =YEAR(H108) -> 2024 | G108: =MONTH(H108) -> 5 | H108: 45435 | I108: 0 | J108: Y | K108: CD24-100
A109: Zuellig Services: 2024.03 | C109: 8758.8 | D109: 5200078171 | E109: 45436 | F109: =YEAR(H109) -> 2024 | G109: =MONTH(H109) -> 6 | H109: 45463 | I109: 0 | J109: Y | K109: CD24-126
A110: Sharp Services: 2024.04 | C110: 3800 | D110: 5200078006 | E110: 45422 | F110: =YEAR(H110) -> 2024 | G110: =MONTH(H110) -> 6 | H110: 45456 | I110: 0 | J110: Y | K110: CD24-113
A111: Zuellig Services: 2024.04 | C111: =5274 -> 5274 | D111: 5200078172 | E111: 45436 | F111: =YEAR(H111) -> 2024 | G111: =MONTH(H111) -> 9 | H111: 45540 | I111: 0 | J111: Y | K111: CD24-189
A112: Zuellig Services: 2024.04 (Credit) | C112: -1560 | D112: 5200081129 | E112: 45523 | F112: =YEAR(H112) -> 2024 | G112: =MONTH(H112) -> 9 | H112: 45540 | I112: 0 | J112: Y | K112: CD24-189
A113: Sharp Services: 2024.05 | C113: 1590 | D113: 5200078746 | E113: 45442 | F113: =YEAR(H113) -> 2024 | G113: =MONTH(H113) -> 7 | H113: 45477 | I113: 0 | J113: Y | K113: CD24-135
A114: Sharp Services: 2024.06 | C114: 5055.68 | D114: 5200079921 | E114: 45482 | F114: =YEAR(H114) -> 2024 | G114: =MONTH(H114) -> 7 | H114: 45491 | I114: 0 | J114: Y | K114: CD24-151
A115: Zuellig Services: 2024.05 & 2024.06 | C115: 13444.8 | D115: 5200080497 | E115: 45503 | F115: =YEAR(H115) -> 2024 | G115: =MONTH(H115) -> 8 | H115: 45526 | I115: 0 | J115: Y | K115: CD24-178
A116: Sharp Services: 2024.07 | C116: 2285.5 | D116: 5200080874 | E116: 45510 | F116: =YEAR(H116) -> 2024 | G116: =MONTH(H116) -> 8 | H116: 45526 | I116: 0 | J116: Y | K116: CD24-175
...

Sheet 4. Fisher
A1: 4. Fisher Clinical Services (KOR & US Mt Prospect)
B2: Contract Number: | C2: PSG-A-1106216 | D2: Version & date: | E2: CO1_23Sep2025
A4: Protocol No: TTK-CS-101 | D4: Updated on: | E4: =TODAY() -> 46226
A6: 1. Sub Total Cost Status
A7: Category | B7: ₩ | C7: %
A8: Budget | B8: =B76 -> 249693702
A9: Paid | B9: =C14+C19+C24 -> 82331344 | C9: =B9/B8 -> 0.32972936
A10: Remaining | B10: =B8-B9 -> 167362358 | C10: =B10/B8 -> 0.67027064
A12: 2. Yearly and Monthly Payment
A14: 2025 | B14: =SUM(A16:L16) -> 0 | C14: =SUM(A17:L17) -> 15142569
A15: 01 | B15: 02 | C15: 03 | D15: 04 | E15: 05 | F15: 06 | G15: 07 | H15: 08 | I15: 09 | J15: 10 | K15: 11 | L15: 12
A16: =SUMIFS($C$31:$C$76,$F$31:$F$76,2025,$G$31:$G$76,1,$L$31:$L$76,"Y") -> 0 | B16: =SUMIFS($C$31:$C$76,$F$31:$F$76,2025,$G$31:$G$76,2,$L$31:$L$76,"Y") -> 0 | C16: =SUMIFS($C$31:$C$76,$F$31:$F$76,2025,$G$31:$G$76,3,$L$31:$L$76,"Y") -> 0 | D16: =SUMIFS($C$31:$C$76,$F$31:$F$76,2025,$G$31:$G$76,4,$L$31:$L$76,"Y") -> 0 | E16: =SUMIFS($C$31:$C$76,$F$31:$F$76,2025,$G$31:$G$76,5,$L$31:$L$76,"Y") -> 0 | F16: =SUMIFS($C$31:$C$76,$F$31:$F$76,2025,$G$31:$G$76,6,$L$31:$L$76,"Y") -> 0 | G16: =SUMIFS($C$31:$C$76,$F$31:$F$76,2025,$G$31:$G$76,7,$L$31:$L$76,"Y") -> 0 | H16: =SUMIFS($C$31:$C$76,$F$31:$F$76,2025,$G$31:$G$76,8,$L$31:$L$76,"Y") -> 0 | I16: =SUMIFS($C$31:$C$76,$F$31:$F$76,2025,$G$31:$G$76,9,$L$31:$L$76,"Y") -> 0 | J16: =SUMIFS($C$31:$C$76,$F$31:$F$76,2025,$G$31:$G$76,10,$L$31:$L$76,"Y") -> 0 | K16: =SUMIFS($C$31:$C$76,$F$31:$F$76,2025,$G$31:$G$76,11,$L$31:$L$76,"Y") -> 0 | L16: =SUMIFS($C$31:$C$76,$F$31:$F$76,2025,$G$31:$G$76,12,$L$31:$L$76,"Y") -> 0
A17: =SUMIFS($I$31:$I$76,$F$31:$F$76,2025,$G$31:$G$76,1,$L$31:$L$76,"Y") -> 0 | B17: =SUMIFS($I$31:$I$76,$F$31:$F$76,2025,$G$31:$G$76,2,$L$31:$L$76,"Y") -> 0 | C17: =SUMIFS($I$31:$I$76,$F$31:$F$76,2025,$G$31:$G$76,3,$L$31:$L$76,"Y") -> 0 | D17: =SUMIFS($I$31:$I$76,$F$31:$F$76,2025,$G$31:$G$76,4,$L$31:$L$76,"Y") -> 0 | E17: =SUMIFS($I$31:$I$76,$F$31:$F$76,2025,$G$31:$G$76,5,$L$31:$L$76,"Y") -> 0 | F17: =SUMIFS($I$31:$I$76,$F$31:$F$76,2025,$G$31:$G$76,6,$L$31:$L$76,"Y") -> 0 | G17: =SUMIFS($I$31:$I$76,$F$31:$F$76,2025,$G$31:$G$76,7,$L$31:$L$76,"Y") -> 0 | H17: =SUMIFS($I$31:$I$76,$F$31:$F$76,2025,$G$31:$G$76,8,$L$31:$L$76,"Y") -> 0 | I17: =SUMIFS($I$31:$I$76,$F$31:$F$76,2025,$G$31:$G$76,9,$L$31:$L$76,"Y") -> 4838959 | J17: =SUMIFS($I$31:$I$76,$F$31:$F$76,2025,$G$31:$G$76,10,$L$31:$L$76,"Y") -> 3344264 | K17: =SUMIFS($I$31:$I$76,$F$31:$F$76,2025,$G$31:$G$76,11,$L$31:$L$76,"Y") -> 3663082 | L17: =SUMIFS($I$31:$I$76,$F$31:$F$76,2025,$G$31:$G$76,12,$L$31:$L$76,"Y") -> 3296264
A19: 2026 | B19: =SUM(A21:L21) -> 0 | C19: =SUM(A22:L22) -> 67188775
A20: 01 | B20: 02 | C20: 03 | D20: 04 | E20: 05 | F20: 06 | G20: 07 | H20: 08 | I20: 09 | J20: 10 | K20: 11 | L20: 12
A21: =SUMIFS($C$31:$C$76,$F$31:$F$76,2026,$G$31:$G$76,1,$L$31:$L$76,"Y") -> 0 | B21: =SUMIFS($C$31:$C$76,$F$31:$F$76,2026,$G$31:$G$76,2,$L$31:$L$76,"Y") -> 0 | C21: =SUMIFS($C$31:$C$76,$F$31:$F$76,2026,$G$31:$G$76,3,$L$31:$L$76,"Y") -> 0 | D21: =SUMIFS($C$31:$C$76,$F$31:$F$76,2026,$G$31:$G$76,4,$L$31:$L$76,"Y") -> 0 | E21: =SUMIFS($C$31:$C$76,$F$31:$F$76,2026,$G$31:$G$76,5,$L$31:$L$76,"Y") -> 0 | F21: =SUMIFS($C$31:$C$76,$F$31:$F$76,2026,$G$31:$G$76,6,$L$31:$L$76,"Y") -> 0 | G21: =SUMIFS($C$31:$C$76,$F$31:$F$76,2026,$G$31:$G$76,7,$L$31:$L$76,"Y") -> 0 | H21: =SUMIFS($C$31:$C$76,$F$31:$F$76,2026,$G$31:$G$76,8,$L$31:$L$76,"Y") -> 0 | I21: =SUMIFS($C$31:$C$76,$F$31:$F$76,2026,$G$31:$G$76,9,$L$31:$L$76,"Y") -> 0 | J21: =SUMIFS($C$31:$C$76,$F$31:$F$76,2026,$G$31:$G$76,10,$L$31:$L$76,"Y") -> 0 | K21: =SUMIFS($C$31:$C$76,$F$31:$F$76,2026,$G$31:$G$76,11,$L$31:$L$76,"Y") -> 0 | L21: =SUMIFS($C$31:$C$76,$F$31:$F$76,2026,$G$31:$G$76,12,$L$31:$L$76,"Y") -> 0
A22: =SUMIFS($I$31:$I$76,$F$31:$F$76,2026,$G$31:$G$76,1,$L$31:$L$76,"Y") -> 30552133 | B22: =SUMIFS($I$31:$I$76,$F$31:$F$76,2026,$G$31:$G$76,2,$L$31:$L$76,"Y") -> 2499191 | C22: =SUMIFS($I$31:$I$76,$F$31:$F$76,2026,$G$31:$G$76,3,$L$31:$L$76,"Y") -> 14479210 | D22: =SUMIFS($I$31:$I$76,$F$31:$F$76,2026,$G$31:$G$76,4,$L$31:$L$76,"Y") -> 5197074 | E22: =SUMIFS($I$31:$I$76,$F$31:$F$76,2026,$G$31:$G$76,5,$L$31:$L$76,"Y") -> 4006625 | F22: =SUMIFS($I$31:$I$76,$F$31:$F$76,2026,$G$31:$G$76,6,$L$31:$L$76,"Y") -> 4954690 | G22: =SUMIFS($I$31:$I$76,$F$31:$F$76,2026,$G$31:$G$76,7,$L$31:$L$76,"Y") -> 5499852 | H22: =SUMIFS($I$31:$I$76,$F$31:$F$76,2026,$G$31:$G$76,8,$L$31:$L$76,"Y") -> 0 | I22: =SUMIFS($I$31:$I$76,$F$31:$F$76,2026,$G$31:$G$76,9,$L$31:$L$76,"Y") -> 0 | J22: =SUMIFS($I$31:$I$76,$F$31:$F$76,2026,$G$31:$G$76,10,$L$31:$L$76,"Y") -> 0 | K22: =SUMIFS($I$31:$I$76,$F$31:$F$76,2026,$G$31:$G$76,11,$L$31:$L$76,"Y") -> 0 | L22: =SUMIFS($I$31:$I$76,$F$31:$F$76,2026,$G$31:$G$76,12,$L$31:$L$76,"Y") -> 0
A24: 2027 | B24: =SUM(A26:L26) -> 0 | C24: =SUM(A27:L27) -> 0
A25: 01 | B25: 02 | C25: 03 | D25: 04 | E25: 05 | F25: 06 | G25: 07 | H25: 08 | I25: 09 | J25: 10 | K25: 11 | L25: 12
A26: =SUMIFS($C$31:$C$76,$F$31:$F$76,2027,$G$31:$G$76,1,$L$31:$L$76,"Y") -> 0 | B26: =SUMIFS($C$31:$C$76,$F$31:$F$76,2027,$G$31:$G$76,2,$L$31:$L$76,"Y") -> 0 | C26: =SUMIFS($C$31:$C$76,$F$31:$F$76,2027,$G$31:$G$76,3,$L$31:$L$76,"Y") -> 0 | D26: =SUMIFS($C$31:$C$76,$F$31:$F$76,2027,$G$31:$G$76,4,$L$31:$L$76,"Y") -> 0 | E26: =SUMIFS($C$31:$C$76,$F$31:$F$76,2027,$G$31:$G$76,5,$L$31:$L$76,"Y") -> 0 | F26: =SUMIFS($C$31:$C$76,$F$31:$F$76,2027,$G$31:$G$76,6,$L$31:$L$76,"Y") -> 0 | G26: =SUMIFS($C$31:$C$76,$F$31:$F$76,2027,$G$31:$G$76,7,$L$31:$L$76,"Y") -> 0 | H26: =SUMIFS($C$31:$C$76,$F$31:$F$76,2027,$G$31:$G$76,8,$L$31:$L$76,"Y") -> 0 | I26: =SUMIFS($C$31:$C$76,$F$31:$F$76,2027,$G$31:$G$76,9,$L$31:$L$76,"Y") -> 0 | J26: =SUMIFS($C$31:$C$76,$F$31:$F$76,2027,$G$31:$G$76,10,$L$31:$L$76,"Y") -> 0 | K26: =SUMIFS($C$31:$C$76,$F$31:$F$76,2027,$G$31:$G$76,11,$L$31:$L$76,"Y") -> 0 | L26: =SUMIFS($C$31:$C$76,$F$31:$F$76,2027,$G$31:$G$76,12,$L$31:$L$76,"Y") -> 0
A27: =SUMIFS($I$31:$I$76,$F$31:$F$76,2027,$G$31:$G$76,1,$L$31:$L$76,"Y") -> 0 | B27: =SUMIFS($I$31:$I$76,$F$31:$F$76,2027,$G$31:$G$76,2,$L$31:$L$76,"Y") -> 0 | C27: =SUMIFS($I$31:$I$76,$F$31:$F$76,2027,$G$31:$G$76,3,$L$31:$L$76,"Y") -> 0 | D27: =SUMIFS($I$31:$I$76,$F$31:$F$76,2027,$G$31:$G$76,4,$L$31:$L$76,"Y") -> 0 | E27: =SUMIFS($I$31:$I$76,$F$31:$F$76,2027,$G$31:$G$76,5,$L$31:$L$76,"Y") -> 0 | F27: =SUMIFS($I$31:$I$76,$F$31:$F$76,2027,$G$31:$G$76,6,$L$31:$L$76,"Y") -> 0 | G27: =SUMIFS($I$31:$I$76,$F$31:$F$76,2027,$G$31:$G$76,7,$L$31:$L$76,"Y") -> 0 | H27: =SUMIFS($I$31:$I$76,$F$31:$F$76,2027,$G$31:$G$76,8,$L$31:$L$76,"Y") -> 0 | I27: =SUMIFS($I$31:$I$76,$F$31:$F$76,2027,$G$31:$G$76,9,$L$31:$L$76,"Y") -> 0 | J27: =SUMIFS($I$31:$I$76,$F$31:$F$76,2027,$G$31:$G$76,10,$L$31:$L$76,"Y") -> 0 | K27: =SUMIFS($I$31:$I$76,$F$31:$F$76,2027,$G$31:$G$76,11,$L$31:$L$76,"Y") -> 0 | L27: =SUMIFS($I$31:$I$76,$F$31:$F$76,2027,$G$31:$G$76,12,$L$31:$L$76,"Y") -> 0
A29: 3. Costs Details
A30: Services | B30: Budget Amount(₩) | C30: Invoiced Amount(₩) | D30: Invoice # | E30: Invoiced Date | F30: Paid Year | G30: Paid Month | H30: Paid Date | I30: Amount(₩) | J30: VAT(₩) | K30: Total Amount(₩) | L30: Paid (Y) | M30: 지출결의 #
A31: Study Set-up (KOR) | D31: 7316 | E31: 45893 | F31: =YEAR(H31) -> 2025 | G31: =MONTH(H31) -> 9 | H31: 45918 | I31: =2648318+971905 -> 3620223 | J31: =ROUNDUP(I31*10%,0.5) -> 362023 | K31: =I31+J31 -> 3982246 | L31: Y | M31: CD25-183
A32: Fisher Clinical Services (KOR): 2025.08 (PM) | D32: 7316 | E32: 45893 | F32: =YEAR(H32) -> 2025 | G32: =MONTH(H32) -> 9 | H32: 45918 | I32: 1218736 | J32: =ROUNDUP(I32*10%,0.5)-1 -> 121873 | K32: =I32+J32 -> 1340609 | L32: Y | M32: CD25-183
A33: Fisher Clinical Services (KOR): 2025.09 | D33: 7443 | E33: 45923 | F33: =YEAR(H33) -> 2025 | G33: =MONTH(H33) -> 10 | H33: 45946 | I33: 3344264 | J33: 334426 | K33: =I33+J33 -> 3678690 | L33: Y | M33: CD25-192
A34: Fisher Clinical Services (KOR): 2025.10 | D34: 7590 | E34: 45954 | F34: =YEAR(H34) -> 2025 | G34: =MONTH(H34) -> 11 | H34: 45974 | I34: 3663082 | J34: 366308 | K34: =I34+J34 -> 4029390 | L34: Y | M34: CD25-200
A35: Fisher Clinical Services (KOR): 2025.11 | D35: 7718 | E35: 45985 | F35: =YEAR(H35) -> 2025 | G35: =MONTH(H35) -> 12 | H35: 45995 | I35: 3296264 | J35: 329626 | K35: =I35+J35 -> 3625890 | L35: Y | M35: CD25-213
A36: Fisher Clinical Services(KOR): 2025.12 + Tislelizumab 1st Campaign (US&KOR) | D36: 7867 | E36: 46013 | F36: 2026 | G36: 1 | H36: 46037 | I36: 30552133 | J36: 3055213 | K36: =I36+J36 -> 33607346 | L36: Y | M36: CD26-003
A37: Fisher Clinical Services (KOR): 2026.01 | D37: 8020 | E37: 46045 | F37: 2026 | G37: 2 | H37: 46058 | I37: 2499191 | J37: 249919 | K37: =I37+J37 -> 2749110 | L37: Y | M37: CD26-013
A38: Study Set-up (US) | D38: 8231 | E38: 46075 | F38: 2026 | G38: 3 | H38: 46093 | I38: 4655550 | J38: 465555 | K38: =I38+J38 -> 5121105 | L38: Y | M38: CD26-028
A39: Fisher Clinical Services (US): 2025.12 | D39: 8232 | E39: 46075 | F39: 2026 | G39: 3 | H39: 46093 | I39: 1131752 | J39: 113175 | K39: =I39+J39 -> 1244927 | L39: Y | M39: CD26-028
A40: Fisher Clinical Services (US): 2026.12 (Storage) | D40: 8233 | E40: 46075 | F40: 2026 | G40: 3 | H40: 46093 | I40: 361870 | J40: 36187 | K40: =I40+J40 -> 398057 | L40: Y | M40: CD26-028
A41: Fisher Clinical Services (US): 2026.01 (Storage) | D41: 8234 | E41: 46075 | F41: 2026 | G41: 3 | H41: 46093 | I41: 361870 | J41: 36187 | K41: =I41+J41 -> 398057 | L41: Y | M41: CD26-028
A42: Fisher Clinical Services (KOR): 2026.02 | D42: 8180 | E42: 46075 | F42: 2026 | G42: 3 | H42: 46093 | I42: 6195043 | J42: 619504 | K42: =I42+J42 -> 6814547 | L42: Y | M42: CD26-028
A43: Fisher Clinical Services (US): 2026.01 | D43: 8235 | E43: 46075 | F43: 2026 | G43: 3 | H43: 46093 | I43: 1773125 | J43: 177313 | K43: =I43+J43 -> 1950438 | L43: Y | M43: CD26-028
A44: Fisher Clinical Services (US): 2026.02 | D44: 8392 | E44: 46103 | F44: 2026 | G44: 4 | H44: 46128 | I44: 1131409 | J44: 113141 | K44: =I44+J44 -> 1244550 | L44: Y | M44: CD26-046
A45: Fisher Clinical Services (US): 2026.02 (Storage) | D45: 8391 | E45: 46103 | F45: 2026 | G45: 4 | H45: 46128 | I45: 723739 | J45: 72374 | K45: =I45+J45 -> 796113 | L45: Y | M45: CD26-046
A46: Fisher Clinical Services (KOR): 2026.03 | D46: 8390 | E46: 46103 | F46: 2026 | G46: 4 | H46: 46128 | I46: 3341926 | J46: 334193 | K46: =I46+J46 -> 3676119 | L46: Y | M46: CD26-046
A47: Fisher Clinical Services (US): 2026.04 | D47: 8440 | E47: 46138 | F47: 2026 | G47: 5 | H47: 46149 | I47: 1773125 | J47: 177313 | K47: =I47+J47 -> 1950438 | L47: Y | M47: CO26-007
A48: Fisher Clinical Services (US): 2026.04 (Storage) | D48: 8441 | E48: 46138 | I48: 361870 | K48: =I48+J48 -> 361870 | L48: N
A49: Fisher Clinical Services (US): 2026.03 (Storage) - Credit for 8391 | D49: 4079761C | E49: 46154 | I49: -361870 | K49: =I49+J49 -> -361870 | L49: N
A50: Fisher Clinical Services (KOR): 2026.04 | D50: 8439 | E50: 46138 | F50: 2026 | G50: 5 | H50: 46149 | I50: 2233500 | J50: 223350 | K50: =I50+J50 -> 2456850 | L50: Y | M50: CO26-007
A51: Fisher Clinical Services (KOR): 2026.05 | D51: 8677 | E51: 46168 | F51: 2026 | G51: 6 | H51: 46184 | I51: 4465320 | J51: 446532 | K51: =I51+J51 -> 4911852 | L51: Y | M51: CO26-026
A52: Fisher Clinical Services (US): 2026.04 (Storage) | D52: 8678 | E52: 46167 | F52: 2026 | G52: 6 | H52: 46184 | I52: 361870 | J52: 36187 | K52: =I52+J52 -> 398057 | L52: Y | M52: CO26-026
A53: Fisher Clinical Services (US): 2026.04 (Freight) | D53: 8679 | E53: 46168 | F53: 2026 | G53: 6 | H53: 46184 | I53: 127500 | J53: 12750 | K53: =I53+J53 -> 140250 | L53: Y | M53: CO26-026
A54: Fisher Clinical Services (KOR): 2026.06 | D54: 9214 | E54: 46194 | F54: 2026 | G54: 7 | H54: 46212 | I54: 2233500 | J54: 223350 | K54: =I54+J54 -> 2456850 | L54: Y | M54: CO26-042
A55: Fisher Clinical Services (US): 2026.05 | D55: 92141 | E55: 46194 | F55: 2026 | G55: 7 | H55: 46212 | I55: 2904482 | J55: 290448 | K55: =I55+J55 -> 3194930 | L55: Y | M55: CO26-042
A56: Fisher Clinical Services (US): 2026.05 (Storage) | D56: 92142 | E56: 46194 | F56: 2026 | G56: 7 | H56: 46212 | I56: 361870 | J56: 36187 | K56: =I56+J56 -> 398057 | L56: Y | M56: CO26-042
A76: Total | B76: 249693702 | C76: =SUM(C31:C75) -> 0

Sheet 5. Marken
A1: 5. Marken
B2: Contract Number: | D2: Version & date: | E2: CO1_23Sep2025
A4: Protocol No: TTK-CS-101 | D4: Updated on: | E4: =TODAY() -> 46226
A6: 1. Sub Total Cost Status
A7: Category | B7: ₩ | C7: %
A8: Budget | B8: =B69 -> 149805492
A9: Paid | B9: =C14+C19+C24+C29+C34 -> 149805492 | C9: =B9/B8 -> 1
A10: Remaining | B10: =B8-B9 -> 0 | C10: =B10/B8 -> 0
A12: 2. Yearly and Monthly Payment
A14: 2023 | B14: =SUM(A16:L16) -> 0 | C14: =SUM(A17:L17) -> 6874940
A15: 01 | B15: 02 | C15: 03 | D15: 04 | E15: 05 | F15: 06 | G15: 07 | H15: 08 | I15: 09 | J15: 10 | K15: 11 | L15: 12
A16: =SUMIFS($C$42:$C$69,$F$42:$F$69,2025,$G$42:$G$69,1,$L$42:$L$69,"Y") -> 0 | B16: =SUMIFS($C$42:$C$69,$F$42:$F$69,2025,$G$42:$G$69,2,$L$42:$L$69,"Y") -> 0 | C16: =SUMIFS($C$42:$C$69,$F$42:$F$69,2025,$G$42:$G$69,3,$L$42:$L$69,"Y") -> 0 | D16: =SUMIFS($C$42:$C$69,$F$42:$F$69,2025,$G$42:$G$69,4,$L$42:$L$69,"Y") -> 0 | E16: =SUMIFS($C$42:$C$69,$F$42:$F$69,2025,$G$42:$G$69,5,$L$42:$L$69,"Y") -> 0 | F16: =SUMIFS($C$42:$C$69,$F$42:$F$69,2025,$G$42:$G$69,6,$L$42:$L$69,"Y") -> 0 | G16: =SUMIFS($C$42:$C$69,$F$42:$F$69,2025,$G$42:$G$69,7,$L$42:$L$69,"Y") -> 0 | H16: =SUMIFS($C$42:$C$69,$F$42:$F$69,2025,$G$42:$G$69,8,$L$42:$L$69,"Y") -> 0 | I16: =SUMIFS($C$42:$C$69,$F$42:$F$69,2025,$G$42:$G$69,9,$L$42:$L$69,"Y") -> 0 | J16: =SUMIFS($C$42:$C$69,$F$42:$F$69,2025,$G$42:$G$69,10,$L$42:$L$69,"Y") -> 0 | K16: =SUMIFS($C$42:$C$69,$F$42:$F$69,2025,$G$42:$G$69,11,$L$42:$L$69,"Y") -> 0 | L16: =SUMIFS($C$42:$C$69,$F$42:$F$69,2025,$G$42:$G$69,12,$L$42:$L$69,"Y") -> 0
A17: =SUMIFS($K$42:$K$69,$F$42:$F$69,2023,$G$42:$G$69,1,$L$42:$L$69,"Y") -> 0 | B17: =SUMIFS($K$42:$K$69,$F$42:$F$69,2023,$G$42:$G$69,2,$L$42:$L$69,"Y") -> 0 | C17: =SUMIFS($K$42:$K$69,$F$42:$F$69,2023,$G$42:$G$69,3,$L$42:$L$69,"Y") -> 0 | D17: =SUMIFS($K$42:$K$69,$F$42:$F$69,2023,$G$42:$G$69,4,$L$42:$L$69,"Y") -> 0 | E17: =SUMIFS($K$42:$K$69,$F$42:$F$69,2023,$G$42:$G$69,5,$L$42:$L$69,"Y") -> 0 | F17: =SUMIFS($K$42:$K$69,$F$42:$F$69,2023,$G$42:$G$69,6,$L$42:$L$69,"Y") -> 6832940 | G17: =SUMIFS($K$42:$K$69,$F$42:$F$69,2023,$G$42:$G$69,7,$L$42:$L$69,"Y") -> 0 | H17: =SUMIFS($K$42:$K$69,$F$42:$F$69,2023,$G$42:$G$69,8,$L$42:$L$69,"Y") -> 42000 | I17: =SUMIFS($K$42:$K$69,$F$42:$F$69,2023,$G$42:$G$69,9,$L$42:$L$69,"Y") -> 0 | J17: =SUMIFS($K$42:$K$69,$F$42:$F$69,2023,$G$42:$G$69,10,$L$42:$L$69,"Y") -> 0 | K17: =SUMIFS($K$42:$K$69,$F$42:$F$69,2023,$G$42:$G$69,11,$L$42:$L$69,"Y") -> 0 | L17: =SUMIFS($K$42:$K$69,$F$42:$F$69,2023,$G$42:$G$69,12,$L$42:$L$69,"Y") -> 0
A19: 2024 | B19: =SUM(A21:L21) -> 0 | C19: =SUM(A22:L22) -> 39872732
A20: 01 | B20: 02 | C20: 03 | D20: 04 | E20: 05 | F20: 06 | G20: 07 | H20: 08 | I20: 09 | J20: 10 | K20: 11 | L20: 12
A21: =SUMIFS($C$42:$C$69,$F$42:$F$69,2025,$G$42:$G$69,1,$L$42:$L$69,"Y") -> 0 | B21: =SUMIFS($C$42:$C$69,$F$42:$F$69,2025,$G$42:$G$69,2,$L$42:$L$69,"Y") -> 0 | C21: =SUMIFS($C$42:$C$69,$F$42:$F$69,2025,$G$42:$G$69,3,$L$42:$L$69,"Y") -> 0 | D21: =SUMIFS($C$42:$C$69,$F$42:$F$69,2025,$G$42:$G$69,4,$L$42:$L$69,"Y") -> 0 | E21: =SUMIFS($C$42:$C$69,$F$42:$F$69,2025,$G$42:$G$69,5,$L$42:$L$69,"Y") -> 0 | F21: =SUMIFS($C$42:$C$69,$F$42:$F$69,2025,$G$42:$G$69,6,$L$42:$L$69,"Y") -> 0 | G21: =SUMIFS($C$42:$C$69,$F$42:$F$69,2025,$G$42:$G$69,7,$L$42:$L$69,"Y") -> 0 | H21: =SUMIFS($C$42:$C$69,$F$42:$F$69,2025,$G$42:$G$69,8,$L$42:$L$69,"Y") -> 0 | I21: =SUMIFS($C$42:$C$69,$F$42:$F$69,2025,$G$42:$G$69,9,$L$42:$L$69,"Y") -> 0 | J21: =SUMIFS($C$42:$C$69,$F$42:$F$69,2025,$G$42:$G$69,10,$L$42:$L$69,"Y") -> 0 | K21: =SUMIFS($C$42:$C$69,$F$42:$F$69,2025,$G$42:$G$69,11,$L$42:$L$69,"Y") -> 0 | L21: =SUMIFS($C$42:$C$69,$F$42:$F$69,2025,$G$42:$G$69,12,$L$42:$L$69,"Y") -> 0
A22: =SUMIFS($K$42:$K$69,$F$42:$F$69,2024,$G$42:$G$69,1,$L$42:$L$69,"Y") -> 0 | B22: =SUMIFS($K$42:$K$69,$F$42:$F$69,2024,$G$42:$G$69,2,$L$42:$L$69,"Y") -> 0 | C22: =SUMIFS($K$42:$K$69,$F$42:$F$69,2024,$G$42:$G$69,3,$L$42:$L$69,"Y") -> 0 | D22: =SUMIFS($K$42:$K$69,$F$42:$F$69,2024,$G$42:$G$69,4,$L$42:$L$69,"Y") -> 0 | E22: =SUMIFS($K$42:$K$69,$F$42:$F$69,2024,$G$42:$G$69,5,$L$42:$L$69,"Y") -> 0 | F22: =SUMIFS($K$42:$K$69,$F$42:$F$69,2024,$G$42:$G$69,6,$L$42:$L$69,"Y") -> 29201942 | G22: =SUMIFS($K$42:$K$69,$F$42:$F$69,2024,$G$42:$G$69,7,$L$42:$L$69,"Y") -> 0 | H22: =SUMIFS($K$42:$K$69,$F$42:$F$69,2024,$G$42:$G$69,8,$L$42:$L$69,"Y") -> 0 | I22: =SUMIFS($K$42:$K$69,$F$42:$F$69,2024,$G$42:$G$69,9,$L$42:$L$69,"Y") -> 0 | J22: =SUMIFS($K$42:$K$69,$F$42:$F$69,2024,$G$42:$G$69,10,$L$42:$L$69,"Y") -> 10670790 | K22: =SUMIFS($K$42:$K$69,$F$42:$F$69,2024,$G$42:$G$69,11,$L$42:$L$69,"Y") -> 0 | L22: =SUMIFS($K$42:$K$69,$F$42:$F$69,2024,$G$42:$G$69,12,$L$42:$L$69,"Y") -> 0
A24: 2025 | B24: =SUM(A26:L26) -> 0 | C24: =SUM(A27:L27) -> 85621177
A25: 01 | B25: 02 | C25: 03 | D25: 04 | E25: 05 | F25: 06 | G25: 07 | H25: 08 | I25: 09 | J25: 10 | K25: 11 | L25: 12
A26: =SUMIFS($C$42:$C$69,$F$42:$F$69,2025,$G$42:$G$69,1,$L$42:$L$69,"Y") -> 0 | B26: =SUMIFS($C$42:$C$69,$F$42:$F$69,2025,$G$42:$G$69,2,$L$42:$L$69,"Y") -> 0 | C26: =SUMIFS($C$42:$C$69,$F$42:$F$69,2025,$G$42:$G$69,3,$L$42:$L$69,"Y") -> 0 | D26: =SUMIFS($C$42:$C$69,$F$42:$F$69,2025,$G$42:$G$69,4,$L$42:$L$69,"Y") -> 0 | E26: =SUMIFS($C$42:$C$69,$F$42:$F$69,2025,$G$42:$G$69,5,$L$42:$L$69,"Y") -> 0 | F26: =SUMIFS($C$42:$C$69,$F$42:$F$69,2025,$G$42:$G$69,6,$L$42:$L$69,"Y") -> 0 | G26: =SUMIFS($C$42:$C$69,$F$42:$F$69,2025,$G$42:$G$69,7,$L$42:$L$69,"Y") -> 0 | H26: =SUMIFS($C$42:$C$69,$F$42:$F$69,2025,$G$42:$G$69,8,$L$42:$L$69,"Y") -> 0 | I26: =SUMIFS($C$42:$C$69,$F$42:$F$69,2025,$G$42:$G$69,9,$L$42:$L$69,"Y") -> 0 | J26: =SUMIFS($C$42:$C$69,$F$42:$F$69,2025,$G$42:$G$69,10,$L$42:$L$69,"Y") -> 0 | K26: =SUMIFS($C$42:$C$69,$F$42:$F$69,2025,$G$42:$G$69,11,$L$42:$L$69,"Y") -> 0 | L26: =SUMIFS($C$42:$C$69,$F$42:$F$69,2025,$G$42:$G$69,12,$L$42:$L$69,"Y") -> 0
A27: =SUMIFS($K$42:$K$69,$F$42:$F$69,2025,$G$42:$G$69,1,$L$42:$L$69,"Y") -> 0 | B27: =SUMIFS($K$42:$K$69,$F$42:$F$69,2025,$G$42:$G$69,2,$L$42:$L$69,"Y") -> 0 | C27: =SUMIFS($K$42:$K$69,$F$42:$F$69,2025,$G$42:$G$69,3,$L$42:$L$69,"Y") -> 0 | D27: =SUMIFS($K$42:$K$69,$F$42:$F$69,2025,$G$42:$G$69,4,$L$42:$L$69,"Y") -> 0 | E27: =SUMIFS($K$42:$K$69,$F$42:$F$69,2025,$G$42:$G$69,5,$L$42:$L$69,"Y") -> 0 | F27: =SUMIFS($K$42:$K$69,$F$42:$F$69,2025,$G$42:$G$69,6,$L$42:$L$69,"Y") -> 2942881 | G27: =SUMIFS($K$42:$K$69,$F$42:$F$69,2025,$G$42:$G$69,7,$L$42:$L$69,"Y") -> 0 | H27: =SUMIFS($K$42:$K$69,$F$42:$F$69,2025,$G$42:$G$69,8,$L$42:$L$69,"Y") -> 34675243 | I27: =SUMIFS($K$42:$K$69,$F$42:$F$69,2025,$G$42:$G$69,9,$L$42:$L$69,"Y") -> 5119000 | J27: =SUMIFS($K$42:$K$69,$F$42:$F$69,2025,$G$42:$G$69,10,$L$42:$L$69,"Y") -> 42884053 | K27: =SUMIFS($K$42:$K$69,$F$42:$F$69,2025,$G$42:$G$69,11,$L$42:$L$69,"Y") -> 0 | L27: =SUMIFS($K$42:$K$69,$F$42:$F$69,2025,$G$42:$G$69,12,$L$42:$L$69,"Y") -> 0
A29: 2026 | B29: =SUM(A31:L31) -> 0 | C29: =SUM(A32:L32) -> 17436643
A30: 01 | B30: 02 | C30: 03 | D30: 04 | E30: 05 | F30: 06 | G30: 07 | H30: 08 | I30: 09 | J30: 10 | K30: 11 | L30: 12
A31: =SUMIFS($C$42:$C$69,$F$42:$F$69,2026,$G$42:$G$69,1,$L$42:$L$69,"Y") -> 0 | B31: =SUMIFS($C$42:$C$69,$F$42:$F$69,2026,$G$42:$G$69,2,$L$42:$L$69,"Y") -> 0 | C31: =SUMIFS($C$42:$C$69,$F$42:$F$69,2026,$G$42:$G$69,3,$L$42:$L$69,"Y") -> 0 | D31: =SUMIFS($C$42:$C$69,$F$42:$F$69,2026,$G$42:$G$69,4,$L$42:$L$69,"Y") -> 0 | E31: =SUMIFS($C$42:$C$69,$F$42:$F$69,2026,$G$42:$G$69,5,$L$42:$L$69,"Y") -> 0 | F31: =SUMIFS($C$42:$C$69,$F$42:$F$69,2026,$G$42:$G$69,6,$L$42:$L$69,"Y") -> 0 | G31: =SUMIFS($C$42:$C$69,$F$42:$F$69,2026,$G$42:$G$69,7,$L$42:$L$69,"Y") -> 0 | H31: =SUMIFS($C$42:$C$69,$F$42:$F$69,2026,$G$42:$G$69,8,$L$42:$L$69,"Y") -> 0 | I31: =SUMIFS($C$42:$C$69,$F$42:$F$69,2026,$G$42:$G$69,9,$L$42:$L$69,"Y") -> 0 | J31: =SUMIFS($C$42:$C$69,$F$42:$F$69,2026,$G$42:$G$69,10,$L$42:$L$69,"Y") -> 0 | K31: =SUMIFS($C$42:$C$69,$F$42:$F$69,2026,$G$42:$G$69,11,$L$42:$L$69,"Y") -> 0 | L31: =SUMIFS($C$42:$C$69,$F$42:$F$69,2026,$G$42:$G$69,12,$L$42:$L$69,"Y") -> 0
A32: =SUMIFS($K$42:$K$69,$F$42:$F$69,2026,$G$42:$G$69,1,$L$42:$L$69,"Y") -> 11907417 | B32: =SUMIFS($K$42:$K$69,$F$42:$F$69,2026,$G$42:$G$69,2,$L$42:$L$69,"Y") -> 0 | C32: =SUMIFS($K$42:$K$69,$F$42:$F$69,2026,$G$42:$G$69,3,$L$42:$L$69,"Y") -> 0 | D32: =SUMIFS($K$42:$K$69,$F$42:$F$69,2026,$G$42:$G$69,4,$L$42:$L$69,"Y") -> 0 | E32: =SUMIFS($K$42:$K$69,$F$42:$F$69,2026,$G$42:$G$69,5,$L$42:$L$69,"Y") -> 0 | F32: =SUMIFS($K$42:$K$69,$F$42:$F$69,2026,$G$42:$G$69,6,$L$42:$L$69,"Y") -> 0 | G32: =SUMIFS($K$42:$K$69,$F$42:$F$69,2026,$G$42:$G$69,7,$L$42:$L$69,"Y") -> 0 | H32: =SUMIFS($K$42:$K$69,$F$42:$F$69,2026,$G$42:$G$69,8,$L$42:$L$69,"Y") -> 5529226 | I32: =SUMIFS($K$42:$K$69,$F$42:$F$69,2026,$G$42:$G$69,9,$L$42:$L$69,"Y") -> 0 | J32: =SUMIFS($K$42:$K$69,$F$42:$F$69,2026,$G$42:$G$69,10,$L$42:$L$69,"Y") -> 0 | K32: =SUMIFS($K$42:$K$69,$F$42:$F$69,2026,$G$42:$G$69,11,$L$42:$L$69,"Y") -> 0 | L32: =SUMIFS($K$42:$K$69,$F$42:$F$69,2026,$G$42:$G$69,12,$L$42:$L$69,"Y") -> 0
A34: 2027 | B34: =SUM(A36:L36) -> 0 | C34: =SUM(A37:L37) -> 0
A35: 01 | B35: 02 | C35: 03 | D35: 04 | E35: 05 | F35: 06 | G35: 07 | H35: 08 | I35: 09 | J35: 10 | K35: 11 | L35: 12
A36: =SUMIFS($C$42:$C$69,$F$42:$F$69,2027,$G$42:$G$69,1,$L$42:$L$69,"Y") -> 0 | B36: =SUMIFS($C$42:$C$69,$F$42:$F$69,2027,$G$42:$G$69,2,$L$42:$L$69,"Y") -> 0 | C36: =SUMIFS($C$42:$C$69,$F$42:$F$69,2027,$G$42:$G$69,3,$L$42:$L$69,"Y") -> 0 | D36: =SUMIFS($C$42:$C$69,$F$42:$F$69,2027,$G$42:$G$69,4,$L$42:$L$69,"Y") -> 0 | E36: =SUMIFS($C$42:$C$69,$F$42:$F$69,2027,$G$42:$G$69,5,$L$42:$L$69,"Y") -> 0 | F36: =SUMIFS($C$42:$C$69,$F$42:$F$69,2027,$G$42:$G$69,6,$L$42:$L$69,"Y") -> 0 | G36: =SUMIFS($C$42:$C$69,$F$42:$F$69,2027,$G$42:$G$69,7,$L$42:$L$69,"Y") -> 0 | H36: =SUMIFS($C$42:$C$69,$F$42:$F$69,2027,$G$42:$G$69,8,$L$42:$L$69,"Y") -> 0 | I36: =SUMIFS($C$42:$C$69,$F$42:$F$69,2027,$G$42:$G$69,9,$L$42:$L$69,"Y") -> 0 | J36: =SUMIFS($C$42:$C$69,$F$42:$F$69,2027,$G$42:$G$69,10,$L$42:$L$69,"Y") -> 0 | K36: =SUMIFS($C$42:$C$69,$F$42:$F$69,2027,$G$42:$G$69,11,$L$42:$L$69,"Y") -> 0 | L36: =SUMIFS($C$42:$C$69,$F$42:$F$69,2027,$G$42:$G$69,12,$L$42:$L$69,"Y") -> 0
A37: =SUMIFS($K$42:$K$69,$F$42:$F$69,2027,$G$42:$G$69,1,$L$42:$L$69,"Y") -> 0 | B37: =SUMIFS($K$42:$K$69,$F$42:$F$69,2027,$G$42:$G$69,2,$L$42:$L$69,"Y") -> 0 | C37: =SUMIFS($K$42:$K$69,$F$42:$F$69,2027,$G$42:$G$69,3,$L$42:$L$69,"Y") -> 0 | D37: =SUMIFS($K$42:$K$69,$F$42:$F$69,2027,$G$42:$G$69,4,$L$42:$L$69,"Y") -> 0 | E37: =SUMIFS($K$42:$K$69,$F$42:$F$69,2027,$G$42:$G$69,5,$L$42:$L$69,"Y") -> 0 | F37: =SUMIFS($K$42:$K$69,$F$42:$F$69,2027,$G$42:$G$69,6,$L$42:$L$69,"Y") -> 0 | G37: =SUMIFS($K$42:$K$69,$F$42:$F$69,2027,$G$42:$G$69,7,$L$42:$L$69,"Y") -> 0 | H37: =SUMIFS($K$42:$K$69,$F$42:$F$69,2027,$G$42:$G$69,8,$L$42:$L$69,"Y") -> 0 | I37: =SUMIFS($K$42:$K$69,$F$42:$F$69,2027,$G$42:$G$69,9,$L$42:$L$69,"Y") -> 0 | J37: =SUMIFS($K$42:$K$69,$F$42:$F$69,2027,$G$42:$G$69,10,$L$42:$L$69,"Y") -> 0 | K37: =SUMIFS($K$42:$K$69,$F$42:$F$69,2027,$G$42:$G$69,11,$L$42:$L$69,"Y") -> 0 | L37: =SUMIFS($K$42:$K$69,$F$42:$F$69,2027,$G$42:$G$69,12,$L$42:$L$69,"Y") -> 0
A39: 3. Costs Details
A40: Services | B40: Budget Amount(₩) | C40: Invoiced Amount(₩) | D40: Invoice # | E40: Invoiced Date | F40: Paid Year | G40: Paid Month | H40: Paid Date | I40: Transport Amount(₩) | J40: Duty & Tax(₩) | K40: Total Amount(₩) | L40: Paid (Y) | M40: 지출결의 #
A41: BAL0891 Internal Standard Shipment: 10mg (Eurofins:Germany to SBQ:Swiss) | B41: =K41 -> 976003 | D41: SEL13786 | E41: 45043 | F41: =YEAR(H41) -> 2023 | G41: =MONTH(H41) -> 5 | H41: 45071 | I41: 976003 | J41: 0 | K41: =I41+J41 -> 976003 | L41: Y | M41: CO23-060
A42: BAL0891 IP 1st Shipment: 50 Kits (Sharp:US to Zuellig:KOR) | B42: =K42 -> 3450500 | D42: SEL14022 | E42: 45069 | F42: =YEAR(H42) -> 2023 | G42: =MONTH(H42) -> 6 | H42: 45092 | I42: 2876650 | J42: 573850 | K42: =I42+J42 -> 3450500 | L42: Y | M42: CO23-082
A43: BAL0891 IP 2nd Shipment: 50 Kits (Sharp:US to Zuellig:KOR) | B43: =K43 -> 3382440 | D43: SEL14235 | E43: 45091 | F43: =YEAR(H43) -> 2023 | G43: =MONTH(H43) -> 6 | H43: 45106 | I43: 2803150 | J43: 579290 | K43: =I43+J43 -> 3382440 | L43: Y | M43: CO23-103
A44: BAL0891 IP 2nd Shipment: US Export Declaration Fee | B44: =K44 -> 42000 | D44: SEL14826 | E44: 45159 | F44: =YEAR(H44) -> 2023 | G44: =MONTH(H44) -> 8 | H44: 45169 | I44: 0 | J44: 42000 | K44: =I44+J44 -> 42000 | L44: Y | M44: CO23-158
A45: BAL0891 IP 3rd Shipment: 90 Kits (Sharp:US to Zuellig:KOR) | B45: =K45 -> 6793120 | D45: SEL15057 | E45: 45184 | F45: =YEAR(H45) -> 2025 | G45: =MONTH(H45) -> 10 | H45: 45942 | I45: 4867810 | J45: 1925310 | K45: =I45+J45 -> 6793120 | L45: Y | M45: CO23-182
A46: BAL0891 IP 4th Shipment: 90 Kits (Sharp:US to Zuellig:KOR) | B46: =K46 -> 5343625 | D46: SEL15197 | E46: 45204 | F46: =YEAR(H46) -> 2025 | G46: =MONTH(H46) -> 10 | H46: 45956 | I46: 4311805 | J46: 1031820 | K46: =I46+J46 -> 5343625 | L46: Y | M46: CO23-196
A47: BAL0891 IP 5th Shipment: 891 Kits (Sharp:US to Zuellig:KOR) | B47: =K47 -> 29201942 | D47: SEL17590 | E47: 45453 | F47: =YEAR(H47) -> 2024 | G47: =MONTH(H47) -> 6 | H47: 45470 | I47: 18992332 | J47: 10209610 | K47: =I47+J47 -> 29201942 | L47: Y | M47: CO24-105
A48: Paclitaxel IP 1st Shipment: 254 Kits (Sharp:US to Zuellig:KOR) | B48: =K48 -> 10670790 | D48: SEL18511 | E48: 45558 | F48: =YEAR(H48) -> 2024 | G48: =MONTH(H48) -> 10 | H48: 45575 | I48: 7050800 | J48: 3619990 | K48: =I48+J48 -> 10670790 | L48: Y | M48: CO24-185
A49: BAL0891 IP Internal Standard Shipment: 10mg (Eurofins:Germany to SBQ:KOR) | B49: =K49 -> 2942881 | D49: SEL21038 | E49: 45817 | F49: =YEAR(H49) -> 2025 | G49: =MONTH(H49) -> 6 | H49: 45834 | I49: 2529911 | J49: 412970 | K49: =I49+J49 -> 2942881 | L49: Y | M49: CO25-113
A50: BAL0891 IP 6th Shipment: 998 Kits (Sharp:US to Zuellig:KOR) | B50: =K50 -> 34675243 | D50: SEL21663 | E50: 45880 | F50: =YEAR(H50) -> 2025 | G50: =MONTH(H50) -> 8 | H50: 45897 | I50: 21798633 | J50: 12876610 | K50: =I50+J50 -> 34675243 | L50: Y | M50: CO25-169
A51: BAL0891 IP Shipment: 300 kits (Sharp:US to Piramal:US) | B51: =K51 -> 5119000 | D51: SEL21868 | E51: 45890 | F51: =YEAR(H51) -> 2025 | G51: =MONTH(H51) -> 9 | H51: 45904 | I51: 5119000 | J51: 0 | K51: =I51+J51 -> 5119000 | L51: Y | M51: CO25-174
A52: BAL0891 IP 7th Shipment: 698 Kits (Sharp:US to Zuellig:KOR) | B52: =K52 -> 22264275 | D52: SEL22347 | E52: 45932 | F52: =YEAR(H52) -> 2025 | G52: =MONTH(H52) -> 10 | H52: 45960 | I52: 13268835 | J52: 8995440 | K52: =I52+J52 -> 22264275 | L52: Y | M52: CO25-211
A53: Tislelizumab IP 1st Supply: 300 Vials (Beigene:CHINA to FCS:KOR) | B53: =K53 -> 8483033 | D53: SEL22348 | E53: 45932 | F53: =YEAR(H53) -> 2025 | G53: =MONTH(H53) -> 10 | H53: 45960 | I53: 4751933 | J53: 3731100 | K53: =I53+J53 -> 8483033 | L53: Y | M53: CO25-211
A54: Tislelizumab IP 1st Shipment: 149 Kits (FCS Korea to FCS US) | B54: =K54 -> 11907417 | D54: SEL23563 | E54: 46031 | F54: 2026 | G54: 1 | H54: 46051 | I54: 10158008 | J54: 1749409 | K54: =I54+J54 -> 11907417 | L54: Y | M54: CO126-005
A55: Paclitaxel IP 2nd Shipment: 35 Kits (Sharp:US to Zuellig:KOR) | B55: 5529226 | D55: SEL25960 | E55: 46219 | F55: 2026 | G55: 8 | H55: 46240 | I55: 4353686 | J55: 1175540 | K55: =I55+J55 -> 5529226 | L55: Y | M55: CO26-057
A69: Total | B69: =SUM(B42:B68) -> 149805492 | C69: =SUM(C42:C68) -> 0

Sheet 6. SBQ
A1: 4. SBQ
B2: Contract Number: | D2: Version & date:
A4: Protocol No: TTK-CS-101 | D4: Updated on:
A6: 1. Total Payment Status
A7: Category | B7: CHF | C7: %
A8: Budget | B8: =L73 -> 440404.83
A9: Paid | B9: =B14+B19+B24+B29+B34 -> 160795.18 | C9: =B9/B8 -> 0.36510767
A10: Remaining | B10: =B8-B9 -> 279609.65 | C10: =B10/B8 -> 0.63489233
A12: 2. Yearly and Monthly Payment
B13: CHF | C13: KRW
A14: 2023 | B14: =SUM(A16:L16) -> 69301.98 | C14: =SUM(A17:L17) -> 0
A15: 01 | B15: 02 | C15: 03 | D15: 04 | E15: 05 | F15: 06 | G15: 07 | H15: 08 | I15: 09 | J15: 10 | K15: 11 | L15: 12
A16: =SUMIFS($L$41:$L$69,$I$41:$I$69,2023,$J$41:$J$69,1,$H$41:$H$69,"Y") -> 0 | B16: =SUMIFS($L$41:$L$69,$I$41:$I$69,2023,$J$41:$J$69,2,$H$41:$H$69,"Y") -> 67333.98 | C16: =SUMIFS($L$41:$L$69,$I$41:$I$69,2023,$J$41:$J$69,3,$H$41:$H$69,"Y") -> 0 | D16: =SUMIFS($L$41:$L$69,$I$41:$I$69,2023,$J$41:$J$69,4,$H$41:$H$69,"Y") -> 0 | E16: =SUMIFS($L$41:$L$69,$I$41:$I$69,2023,$J$41:$J$69,5,$H$41:$H$69,"Y") -> 0 | F16: =SUMIFS($L$41:$L$69,$I$41:$I$69,2023,$J$41:$J$69,6,$H$41:$H$69,"Y") -> 0 | G16: =SUMIFS($L$41:$L$69,$I$41:$I$69,2023,$J$41:$J$69,7,$H$41:$H$69,"Y") -> 0 | H16: =SUMIFS($L$41:$L$69,$I$41:$I$69,2023,$J$41:$J$69,8,$H$41:$H$69,"Y") -> 1968 | I16: =SUMIFS($L$41:$L$69,$I$41:$I$69,2023,$J$41:$J$69,9,$H$41:$H$69,"Y") -> 0 | J16: =SUMIFS($L$41:$L$69,$I$41:$I$69,2023,$J$41:$J$69,10,$H$41:$H$69,"Y") -> 0 | K16: =SUMIFS($L$41:$L$69,$I$41:$I$69,2023,$J$41:$J$69,11,$H$41:$H$69,"Y") -> 0 | L16: =SUMIFS($L$41:$L$69,$I$41:$I$69,2023,$J$41:$J$69,12,$H$41:$H$69,"Y") -> 0
A17: =SUMIFS($M$41:$M$69,$I$41:$I$69,2023,$J$41:$J$69,1,$H$41:$H$69,"Y") -> 0 | B17: =SUMIFS($M$41:$M$69,$I$41:$I$69,2023,$J$41:$J$69,2,$H$41:$H$69,"Y") -> 0 | C17: =SUMIFS($M$41:$M$69,$I$41:$I$69,2023,$J$41:$J$69,3,$H$41:$H$69,"Y") -> 0 | D17: =SUMIFS($M$41:$M$69,$I$41:$I$69,2023,$J$41:$J$69,4,$H$41:$H$69,"Y") -> 0 | E17: =SUMIFS($M$41:$M$69,$I$41:$I$69,2023,$J$41:$J$69,5,$H$41:$H$69,"Y") -> 0 | F17: =SUMIFS($M$41:$M$69,$I$41:$I$69,2023,$J$41:$J$69,6,$H$41:$H$69,"Y") -> 0 | G17: =SUMIFS($M$41:$M$69,$I$41:$I$69,2023,$J$41:$J$69,7,$H$41:$H$69,"Y") -> 0 | H17: =SUMIFS($M$41:$M$69,$I$41:$I$69,2023,$J$41:$J$69,8,$H$41:$H$69,"Y") -> 0 | I17: =SUMIFS($M$41:$M$69,$I$41:$I$69,2023,$J$41:$J$69,9,$H$41:$H$69,"Y") -> 0 | J17: =SUMIFS($M$41:$M$69,$I$41:$I$69,2023,$J$41:$J$69,10,$H$41:$H$69,"Y") -> 0 | K17: =SUMIFS($M$41:$M$69,$I$41:$I$69,2023,$J$41:$J$69,11,$H$41:$H$69,"Y") -> 0 | L17: =SUMIFS($M$41:$M$69,$I$41:$I$69,2023,$J$41:$J$69,12,$H$41:$H$69,"Y") -> 0
A19: 2024 | B19: =SUM(A21:L21) -> 4750 | C19: =SUM(A22:L22) -> 0
A20: 01 | B20: 02 | C20: 03 | D20: 04 | E20: 05 | F20: 06 | G20: 07 | H20: 08 | I20: 09 | J20: 10 | K20: 11 | L20: 12
A21: =SUMIFS($L$41:$L$69,$I$41:$I$69,2024,$J$41:$J$69,1,$H$41:$H$69,"Y") -> 0 | B21: =SUMIFS($L$41:$L$69,$I$41:$I$69,2024,$J$41:$J$69,2,$H$41:$H$69,"Y") -> 0 | C21: =SUMIFS($L$41:$L$69,$I$41:$I$69,2024,$J$41:$J$69,3,$H$41:$H$69,"Y") -> 0 | D21: =SUMIFS($L$41:$L$69,$I$41:$I$69,2024,$J$41:$J$69,4,$H$41:$H$69,"Y") -> 0 | E21: =SUMIFS($L$41:$L$69,$I$41:$I$69,2024,$J$41:$J$69,5,$H$41:$H$69,"Y") -> 0 | F21: =SUMIFS($L$41:$L$69,$I$41:$I$69,2024,$J$41:$J$69,6,$H$41:$H$69,"Y") -> 0 | G21: =SUMIFS($L$41:$L$69,$I$41:$I$69,2024,$J$41:$J$69,7,$H$41:$H$69,"Y") -> 0 | H21: =SUMIFS($L$41:$L$69,$I$41:$I$69,2024,$J$41:$J$69,8,$H$41:$H$69,"Y") -> 0 | I21: =SUMIFS($L$41:$L$69,$I$41:$I$69,2024,$J$41:$J$69,9,$H$41:$H$69,"Y") -> 0 | J21: =SUMIFS($L$41:$L$69,$I$41:$I$69,2024,$J$41:$J$69,10,$H$41:$H$69,"Y") -> 0 | K21: =SUMIFS($L$41:$L$69,$I$41:$I$69,2024,$J$41:$J$69,11,$H$41:$H$69,"Y") -> 0 | L21: =SUMIFS($L$41:$L$69,$I$41:$I$69,2024,$J$41:$J$69,12,$H$41:$H$69,"Y") -> 4750
A22: =SUMIFS($M$41:$M$69,$I$41:$I$69,2024,$J$41:$J$69,1,$H$41:$H$69,"Y") -> 0 | B22: =SUMIFS($M$41:$M$69,$I$41:$I$69,2024,$J$41:$J$69,2,$H$41:$H$69,"Y") -> 0 | C22: =SUMIFS($M$41:$M$69,$I$41:$I$69,2024,$J$41:$J$69,3,$H$41:$H$69,"Y") -> 0 | D22: =SUMIFS($M$41:$M$69,$I$41:$I$69,2024,$J$41:$J$69,4,$H$41:$H$69,"Y") -> 0 | E22: =SUMIFS($M$41:$M$69,$I$41:$I$69,2024,$J$41:$J$69,5,$H$41:$H$69,"Y") -> 0 | F22: =SUMIFS($M$41:$M$69,$I$41:$I$69,2024,$J$41:$J$69,6,$H$41:$H$69,"Y") -> 0 | G22: =SUMIFS($M$41:$M$69,$I$41:$I$69,2024,$J$41:$J$69,7,$H$41:$H$69,"Y") -> 0 | H22: =SUMIFS($M$41:$M$69,$I$41:$I$69,2024,$J$41:$J$69,8,$H$41:$H$69,"Y") -> 0 | I22: =SUMIFS($M$41:$M$69,$I$41:$I$69,2024,$J$41:$J$69,9,$H$41:$H$69,"Y") -> 0 | J22: =SUMIFS($M$41:$M$69,$I$41:$I$69,2024,$J$41:$J$69,10,$H$41:$H$69,"Y") -> 0 | K22: =SUMIFS($M$41:$M$69,$I$41:$I$69,2024,$J$41:$J$69,11,$H$41:$H$69,"Y") -> 0 | L22: =SUMIFS($M$41:$M$69,$I$41:$I$69,2024,$J$41:$J$69,12,$H$41:$H$69,"Y") -> 0
A24: 2025 | B24: =SUM(A26:L26) -> 76627.2 | C24: =SUM(A27:L27) -> 0
A25: 01 | B25: 02 | C25: 03 | D25: 04 | E25: 05 | F25: 06 | G25: 07 | H25: 08 | I25: 09 | J25: 10 | K25: 11 | L25: 12
A26: =SUMIFS($L$41:$L$69,$I$41:$I$69,2025,$J$41:$J$69,1,$H$41:$H$69,"Y") -> 6213.6 | B26: =SUMIFS($L$41:$L$69,$I$41:$I$69,2025,$J$41:$J$69,2,$H$41:$H$69,"Y") -> 0 | C26: =SUMIFS($L$41:$L$69,$I$41:$I$69,2025,$J$41:$J$69,3,$H$41:$H$69,"Y") -> 0 | D26: =SUMIFS($L$41:$L$69,$I$41:$I$69,2025,$J$41:$J$69,4,$H$41:$H$69,"Y") -> 70413.6 | E26: =SUMIFS($L$41:$L$69,$I$41:$I$69,2025,$J$41:$J$69,5,$H$41:$H$69,"Y") -> 0 | F26: =SUMIFS($L$41:$L$69,$I$41:$I$69,2025,$J$41:$J$69,6,$H$41:$H$69,"Y") -> 0 | G26: =SUMIFS($L$41:$L$69,$I$41:$I$69,2025,$J$41:$J$69,7,$H$41:$H$69,"Y") -> 0 | H26: =SUMIFS($L$41:$L$69,$I$41:$I$69,2025,$J$41:$J$69,8,$H$41:$H$69,"Y") -> 0 | I26: =SUMIFS($L$41:$L$69,$I$41:$I$69,2025,$J$41:$J$69,9,$H$41:$H$69,"Y") -> 0 | J26: =SUMIFS($L$41:$L$69,$I$41:$I$69,2025,$J$41:$J$69,10,$H$41:$H$69,"Y") -> 0 | K26: =SUMIFS($L$41:$L$69,$I$41:$I$69,2025,$J$41:$J$69,11,$H$41:$H$69,"Y") -> 0 | L26: =SUMIFS($L$41:$L$69,$I$41:$I$69,2025,$J$41:$J$69,12,$H$41:$H$69,"Y") -> 0
A27: =SUMIFS($M$41:$M$69,$I$41:$I$69,2025,$J$41:$J$69,1,$H$41:$H$69,"Y") -> 0 | B27: =SUMIFS($M$41:$M$69,$I$41:$I$69,2025,$J$41:$J$69,2,$H$41:$H$69,"Y") -> 0 | C27: =SUMIFS($M$41:$M$69,$I$41:$I$69,2025,$J$41:$J$69,3,$H$41:$H$69,"Y") -> 0 | D27: =SUMIFS($M$41:$M$69,$I$41:$I$69,2025,$J$41:$J$69,4,$H$41:$H$69,"Y") -> 0 | E27: =SUMIFS($M$41:$M$69,$I$41:$I$69,2025,$J$41:$J$69,5,$H$41:$H$69,"Y") -> 0 | F27: =SUMIFS($M$41:$M$69,$I$41:$I$69,2025,$J$41:$J$69,6,$H$41:$H$69,"Y") -> 0 | G27: =SUMIFS($M$41:$M$69,$I$41:$I$69,2025,$J$41:$J$69,7,$H$41:$H$69,"Y") -> 0 | H27: =SUMIFS($M$41:$M$69,$I$41:$I$69,2025,$J$41:$J$69,8,$H$41:$H$69,"Y") -> 0 | I27: =SUMIFS($M$41:$M$69,$I$41:$I$69,2025,$J$41:$J$69,9,$H$41:$H$69,"Y") -> 0 | J27: =SUMIFS($M$41:$M$69,$I$41:$I$69,2025,$J$41:$J$69,10,$H$41:$H$69,"Y") -> 0 | K27: =SUMIFS($M$41:$M$69,$I$41:$I$69,2025,$J$41:$J$69,11,$H$41:$H$69,"Y") -> 0 | L27: =SUMIFS($M$41:$M$69,$I$41:$I$69,2025,$J$41:$J$69,12,$H$41:$H$69,"Y") -> 0
A29: 2026 | B29: =SUM(A31:L31) -> 10116 | C29: =SUM(A32:L32) -> 0
A30: 01 | B30: 02 | C30: 03 | D30: 04 | E30: 05 | F30: 06 | G30: 07 | H30: 08 | I30: 09 | J30: 10 | K30: 11 | L30: 12
A31: =SUMIFS($L$41:$L$69,$I$41:$I$69,2026,$J$41:$J$69,1,$H$41:$H$69,"Y") -> 0 | B31: =SUMIFS($L$41:$L$69,$I$41:$I$69,2026,$J$41:$J$69,2,$H$41:$H$69,"Y") -> 0 | C31: =SUMIFS($L$41:$L$69,$I$41:$I$69,2026,$J$41:$J$69,3,$H$41:$H$69,"Y") -> 0 | D31: =SUMIFS($L$41:$L$69,$I$41:$I$69,2026,$J$41:$J$69,4,$H$41:$H$69,"Y") -> 0 | E31: =SUMIFS($L$41:$L$69,$I$41:$I$69,2026,$J$41:$J$69,5,$H$41:$H$69,"Y") -> 10116 | F31: =SUMIFS($L$41:$L$69,$I$41:$I$69,2026,$J$41:$J$69,6,$H$41:$H$69,"Y") -> 0 | G31: =SUMIFS($L$41:$L$69,$I$41:$I$69,2026,$J$41:$J$69,7,$H$41:$H$69,"Y") -> 0 | H31: =SUMIFS($L$41:$L$69,$I$41:$I$69,2026,$J$41:$J$69,8,$H$41:$H$69,"Y") -> 0 | I31: =SUMIFS($L$41:$L$69,$I$41:$I$69,2026,$J$41:$J$69,9,$H$41:$H$69,"Y") -> 0 | J31: =SUMIFS($L$41:$L$69,$I$41:$I$69,2026,$J$41:$J$69,10,$H$41:$H$69,"Y") -> 0 | K31: =SUMIFS($L$41:$L$69,$I$41:$I$69,2026,$J$41:$J$69,11,$H$41:$H$69,"Y") -> 0 | L31: =SUMIFS($L$41:$L$69,$I$41:$I$69,2026,$J$41:$J$69,12,$H$41:$H$69,"Y") -> 0
A32: =SUMIFS($M$41:$M$69,$I$41:$I$69,2026,$J$41:$J$69,1,$H$41:$H$69,"Y") -> 0 | B32: =SUMIFS($M$41:$M$69,$I$41:$I$69,2026,$J$41:$J$69,2,$H$41:$H$69,"Y") -> 0 | C32: =SUMIFS($M$41:$M$69,$I$41:$I$69,2026,$J$41:$J$69,3,$H$41:$H$69,"Y") -> 0 | D32: =SUMIFS($M$41:$M$69,$I$41:$I$69,2026,$J$41:$J$69,4,$H$41:$H$69,"Y") -> 0 | E32: =SUMIFS($M$41:$M$69,$I$41:$I$69,2026,$J$41:$J$69,5,$H$41:$H$69,"Y") -> 0 | F32: =SUMIFS($M$41:$M$69,$I$41:$I$69,2026,$J$41:$J$69,6,$H$41:$H$69,"Y") -> 0 | G32: =SUMIFS($M$41:$M$69,$I$41:$I$69,2026,$J$41:$J$69,7,$H$41:$H$69,"Y") -> 0 | H32: =SUMIFS($M$41:$M$69,$I$41:$I$69,2026,$J$41:$J$69,8,$H$41:$H$69,"Y") -> 0 | I32: =SUMIFS($M$41:$M$69,$I$41:$I$69,2026,$J$41:$J$69,9,$H$41:$H$69,"Y") -> 0 | J32: =SUMIFS($M$41:$M$69,$I$41:$I$69,2026,$J$41:$J$69,10,$H$41:$H$69,"Y") -> 0 | K32: =SUMIFS($M$41:$M$69,$I$41:$I$69,2026,$J$41:$J$69,11,$H$41:$H$69,"Y") -> 0 | L32: =SUMIFS($M$41:$M$69,$I$41:$I$69,2026,$J$41:$J$69,12,$H$41:$H$69,"Y") -> 0
A34: 2027 | B34: =SUM(A36:L36) -> 0 | C34: =SUM(A37:L37) -> 0
A35: 01 | B35: 02 | C35: 03 | D35: 04 | E35: 05 | F35: 06 | G35: 07 | H35: 08 | I35: 09 | J35: 10 | K35: 11 | L35: 12
A36: =SUMIFS($L$41:$L$69,$I$41:$I$69,2027,$J$41:$J$69,1,$H$41:$H$69,"Y") -> 0 | B36: =SUMIFS($L$41:$L$69,$I$41:$I$69,2027,$J$41:$J$69,2,$H$41:$H$69,"Y") -> 0 | C36: =SUMIFS($L$41:$L$69,$I$41:$I$69,2027,$J$41:$J$69,3,$H$41:$H$69,"Y") -> 0 | D36: =SUMIFS($L$41:$L$69,$I$41:$I$69,2027,$J$41:$J$69,4,$H$41:$H$69,"Y") -> 0 | E36: =SUMIFS($L$41:$L$69,$I$41:$I$69,2027,$J$41:$J$69,5,$H$41:$H$69,"Y") -> 0 | F36: =SUMIFS($L$41:$L$69,$I$41:$I$69,2027,$J$41:$J$69,6,$H$41:$H$69,"Y") -> 0 | G36: =SUMIFS($L$41:$L$69,$I$41:$I$69,2027,$J$41:$J$69,7,$H$41:$H$69,"Y") -> 0 | H36: =SUMIFS($L$41:$L$69,$I$41:$I$69,2027,$J$41:$J$69,8,$H$41:$H$69,"Y") -> 0 | I36: =SUMIFS($L$41:$L$69,$I$41:$I$69,2027,$J$41:$J$69,9,$H$41:$H$69,"Y") -> 0 | J36: =SUMIFS($L$41:$L$69,$I$41:$I$69,2027,$J$41:$J$69,10,$H$41:$H$69,"Y") -> 0 | K36: =SUMIFS($L$41:$L$69,$I$41:$I$69,2027,$J$41:$J$69,11,$H$41:$H$69,"Y") -> 0 | L36: =SUMIFS($L$41:$L$69,$I$41:$I$69,2027,$J$41:$J$69,12,$H$41:$H$69,"Y") -> 0
A37: =SUMIFS($M$41:$M$69,$I$41:$I$69,2027,$J$41:$J$69,1,$H$41:$H$69,"Y") -> 0 | B37: =SUMIFS($M$41:$M$69,$I$41:$I$69,2027,$J$41:$J$69,2,$H$41:$H$69,"Y") -> 0 | C37: =SUMIFS($M$41:$M$69,$I$41:$I$69,2027,$J$41:$J$69,3,$H$41:$H$69,"Y") -> 0 | D37: =SUMIFS($M$41:$M$69,$I$41:$I$69,2027,$J$41:$J$69,4,$H$41:$H$69,"Y") -> 0 | E37: =SUMIFS($M$41:$M$69,$I$41:$I$69,2027,$J$41:$J$69,5,$H$41:$H$69,"Y") -> 0 | F37: =SUMIFS($M$41:$M$69,$I$41:$I$69,2027,$J$41:$J$69,6,$H$41:$H$69,"Y") -> 0 | G37: =SUMIFS($M$41:$M$69,$I$41:$I$69,2027,$J$41:$J$69,7,$H$41:$H$69,"Y") -> 0 | H37: =SUMIFS($M$41:$M$69,$I$41:$I$69,2027,$J$41:$J$69,8,$H$41:$H$69,"Y") -> 0 | I37: =SUMIFS($M$41:$M$69,$I$41:$I$69,2027,$J$41:$J$69,9,$H$41:$H$69,"Y") -> 0 | J37: =SUMIFS($M$41:$M$69,$I$41:$I$69,2027,$J$41:$J$69,10,$H$41:$H$69,"Y") -> 0 | K37: =SUMIFS($M$41:$M$69,$I$41:$I$69,2027,$J$41:$J$69,11,$H$41:$H$69,"Y") -> 0 | L37: =SUMIFS($M$41:$M$69,$I$41:$I$69,2027,$J$41:$J$69,12,$H$41:$H$69,"Y") -> 0
A39: 3. Quotation details
A40: Quotation Date | B40: Quote No. | C40: Contracted | D40: Total Quotation Amount | E40: Payment milestone | F40: Invoice amount to be billed | G40: Issued invoice # | H40: Paid | I40: Paid Year | J40: Paid Month | K40: Payment Date | L40: Invoiced Amount(CHF) | M40: Total Amount(₩) | N40: 지출결의 # | O40: Remarks
A41: 2022.11.30 | B41: Q210126 | C41: Y (2023.01.12) | D41: 202800 | E41: 30% after giving the order | F41: 60840 | G41: 230046-1 | H41: Y | I41: 2023 | J41: 02 | K41: 44980 | L41: 60840
E42: 50% after delivery of the results | F42: 101400 | G42: 230046-2 | H42: Y | I42: 2025 | J42: 04 | K42: 45777 | L42: 50700 | O42: They billed us 50700 but this amount is not in the contract nor can be confirmed. | P42: 계약서와 내용이 다름 + Delivery Result에 대한 Define이 되어야 한다. 우리도 invoice를 처리하기 위해서 지금 문의를 하고 있는 것이다.
E43: 20% after delivery of the final draft study report | F43: 40560
A44: 2025.03.20 | B44: Q210126_Amd01 | C44: Y (2026.03.11) | D44: 235300 | E44: 30% after giving the order | F44: 70590
E45: 50% after delivery of the results | F45: 117650
E46: 20% after delivery of the final draft study report | F46: 47060
A47: 2022.12.20 | B47: Q210466 | C47: Y (2023.01.12) | D47: 12987.95 | E47: 50% after giving the order | F47: 6493.98 | G47: 220327-1 | H47: Y | I47: 2023 | J47: 02 | K47: 44980 | L47: 6493.98
E48: 50% after delivery of kits | F48: 6493.98
A49: 2024.08.09 | B49: Q210466 | C49: N | D49: 12987.95 | E49: 50% after giving the order | F49: 6493.98
E50: 50% after delivery of kits | F50: 6493.98 | G50: 220327-2 | H50: Y | L50: 39245.88 | O50: They billed us 39245.88 this was 57.47% of the total amount but there was no reference and no contract was made. (Based on Quotation dated 2024.08.09). | P50: 이거는 서명이 된 Quote가 아니고, 새롭게 지금 전달 해준 2025 3월에 준 Quotation을 기반으로 서명하고,
A51: 2025.03.20 | B51: Q210466_Amd01 | C51: N | D51: 69062.89 | E51: 50% after giving the order | F51: 34531.45
E52: 50% after delivery of kits | F52: 34531.45
A53: 2024.09.30 | B53: Q220591_Amd01 | C53: N | D53: 14500 | E53: 50% after giving the order | F53: 7250 | G53: 240154-F | H53: Y | L53: 7250 | O53: This was invoiced for the provided interim analysis but the quotation was not signed and contract amendment was ongoing. No communication email since it was not contracted.
E54: 50% after delivery of the final draft study report | F54: 7250 | G54: 240154-F | H54: Y | L54: 7250
A55: 2023.06.16 | B55: Q230208 | C55: Y (2023.06.20) | D55: 3936 | E55: 50% after giving the order | F55: 1968 | G55: 230187-1 | H55: Y | I55: 2023 | J55: 08 | K55: 45148 | L55: 1968
E56: 50% after storage period (1 year) | F56: 1968 | G56: 230187-2 | H56: Y | I56: 2026 | J56: 05 | K56: 46163 | L56: 1968 | P56: invoice 발행을 해주면 지급하겠다고 전달.
F57: 3456 | G57: 230187-3 | H57: Y | I57: 2026 | J57: 05 | K57: 46163 | L57: 3456
F58: 4692 | G58: 230187-4 | H58: Y | I58: 2026 | J58: 05 | K58: 46163 | L58: 4692
A59: 2023.12.22 | B59: Q230464 | C59: Y (2024.01.24) | D59: 6213.6 | E59: 50% after giving the order | F59: 3106.8 | G59: 240218-F | H59: Y | I59: 2025 | J59: 04 | K59: 45777 | L59: 3106.8 | O59: This was not paid since no inventory log was provided but as we not have the actual inventory log obtained, it can be paid. | P59: 바로 지급 진행
E60: 50% after completion of the study | F60: 3106.8 | G60: 240218-F | H60: Y | I60: 2025 | J60: 04 | K60: 45777 | L60: 3106.8 | O60: This was not paid since no inventory log was provided but as we not have the actual inventory log obtained, it can be paid. | P60: 바로 지급 진행
A61: 2024.04.29 | B61: Q240152 | C61: Y (2023.06.13) | D61: 4750 | E61: 50% after giving the order | F61: 2375 | G61: 240156-F | H61: Y | I61: 2024 | J61: 12 | K61: 45631 | L61: 2375
E62: 50% after delivery of the final draft study report | F62: 2375 | G62: 240156-F | H62: Y | I62: 2024 | J62: 12 | K62: 45631 | L62: 2375
A63: 2024.08.06 | B63: Q240254 | C63: Y (2024.10.14) | D63: 45000 | E63: 30% after giving the order | F63: 13500 | G63: 240221-1 | H63: Y | I63: 2025 | J63: 04 | K63: 45777 | L63: 13500 | O63: They increase the report cost to 2000 to 2500 and invoiced 13650 which is not contracted. No email communication as this was during the amendment. | P63: Invioice 수정 요청 진행 하고, 지급 할 수 있도록 처리 할 예정이다.
E64: 50% after delivery of the results | F64: 22500
E65: 20% after delivery of the final draft study report | F65: 9000
A66: 2025.03.20 | B66: Q240256 | C66: N | D66: 40863.14 | E66: 50% after giving the order | F66: 20431.57 | P66: Actual Cost를 확인 해야 한다는 의도가 잘못 전달이 된 것 같다 -> Actual cost를 기반으로 해서 청구를 한다는 것을 아래의 Email에서 Confirm을 해주었기 때문에, 해당 내용을 기반으로 Quotation 진행 하겠다. Quote 부터 진행하고 그 뒤에 invoice 청구를 해달라.
E67: 50% after delivery of kits | F67: 20431.57
A68: 2025.03.20 | B68: Q250120 | C68: Y (2025.05.08) | D68: 6213.6 | E68: 100% after giving the order | F68: 6213.6 | G68: 250009-F | H68: Y | I68: 2025 | J68: 01 | K68: 45659 | L68: 6213.6
A69: 2025.03.20 | B69: Q250122 | C69: N | D69: 14565.6 | E69: 100% after giving the order | F69: 14565.6
K71: Total Amount Paid | L71: 204425.06 | O71: 347522602
K72: To Payout now | O72: -
K73: Total Contracted (to be contracted Amount) | L73: 440404.83 | O73: 748688211
K74: To be Paid | L74: 235979.77 | O74: 401165609 | P74: 지금까지 사용 한 비용 정리해서 업데이트
K75: * 전임자 작성 내용; Further FU 필요

Sheet 7. Aptamer
A1: 5. Aptamer
B2: Contract Number: | D2: Version & date:
A4: Protocol No: TTK-CS-101 | D4: Updated on:
A6: 1. Total Payment Status
A7: Category | B7: ₩ | C7: %
A8: Budget | B8: =D56 -> 294600000
A9: Paid | B9: =B14+B18+B22 -> 54450000 | C9: =B9/B8 -> 0.18482688
A10: Remaining | B10: =B8-B9 -> 240150000 | C10: =B10/B8 -> 0.81517312
A12: 2. Yearly and Monthly Payment
B13: KRW
A14: 2025 | B14: =SUM(A16:L16) -> 54450000
A15: 01 | B15: 02 | C15: 03 | D15: 04 | E15: 05 | F15: 06 | G15: 07 | H15: 08 | I15: 09 | J15: 10 | K15: 11 | L15: 12
A16: =SUMIFS($K$28:$K$55,$H$28:$H$55,2025,$I$28:$I$55,1,$L$28:$L$55,"Y") -> 0 | B16: =SUMIFS($K$28:$K$55,$H$28:$H$55,2025,$I$28:$I$55,2,$L$28:$L$55,"Y") -> 0 | C16: =SUMIFS($K$28:$K$55,$H$28:$H$55,2025,$I$28:$I$55,3,$L$28:$L$55,"Y") -> 0 | D16: =SUMIFS($K$28:$K$55,$H$28:$H$55,2025,$I$28:$I$55,4,$L$28:$L$55,"Y") -> 0 | E16: =SUMIFS($K$28:$K$55,$H$28:$H$55,2025,$I$28:$I$55,5,$L$28:$L$55,"Y") -> 0 | F16: =SUMIFS($K$28:$K$55,$H$28:$H$55,2025,$I$28:$I$55,6,$L$28:$L$55,"Y") -> 14190000 | G16: =SUMIFS($K$28:$K$55,$H$28:$H$55,2025,$I$28:$I$55,7,$L$28:$L$55,"Y") -> 0 | H16: =SUMIFS($K$28:$K$55,$H$28:$H$55,2025,$I$28:$I$55,8,$L$28:$L$55,"Y") -> 0 | I16: =SUMIFS($K$28:$K$55,$H$28:$H$55,2025,$I$28:$I$55,9,$L$28:$L$55,"Y") -> 0 | J16: =SUMIFS($K$28:$K$55,$H$28:$H$55,2025,$I$28:$I$55,10,$L$28:$L$55,"Y") -> 0 | K16: =SUMIFS($K$28:$K$55,$H$28:$H$55,2025,$I$28:$I$55,11,$L$28:$L$55,"Y") -> 28380000 | L16: =SUMIFS($K$28:$K$55,$H$28:$H$55,2025,$I$28:$I$55,12,$L$28:$L$55,"Y") -> 11880000
A18: 2026 | B18: =SUM(A20:L20) -> 0
A19: 01 | B19: 02 | C19: 03 | D19: 04 | E19: 05 | F19: 06 | G19: 07 | H19: 08 | I19: 09 | J19: 10 | K19: 11 | L19: 12
A20: =SUMIFS($K$28:$K$55,$H$28:$H$55,2026,$I$28:$I$55,1,$L$28:$L$55,"Y") -> 0 | B20: =SUMIFS($K$28:$K$55,$H$28:$H$55,2026,$I$28:$I$55,2,$L$28:$L$55,"Y") -> 0 | C20: =SUMIFS($K$28:$K$55,$H$28:$H$55,2026,$I$28:$I$55,3,$L$28:$L$55,"Y") -> 0 | D20: =SUMIFS($K$28:$K$55,$H$28:$H$55,2026,$I$28:$I$55,4,$L$28:$L$55,"Y") -> 0 | E20: =SUMIFS($K$28:$K$55,$H$28:$H$55,2026,$I$28:$I$55,5,$L$28:$L$55,"Y") -> 0 | F20: =SUMIFS($K$28:$K$55,$H$28:$H$55,2026,$I$28:$I$55,6,$L$28:$L$55,"Y") -> 0 | G20: =SUMIFS($K$28:$K$55,$H$28:$H$55,2026,$I$28:$I$55,7,$L$28:$L$55,"Y") -> 0 | H20: =SUMIFS($K$28:$K$55,$H$28:$H$55,2026,$I$28:$I$55,8,$L$28:$L$55,"Y") -> 0 | I20: =SUMIFS($K$28:$K$55,$H$28:$H$55,2026,$I$28:$I$55,9,$L$28:$L$55,"Y") -> 0 | J20: =SUMIFS($K$28:$K$55,$H$28:$H$55,2026,$I$28:$I$55,10,$L$28:$L$55,"Y") -> 0 | K20: =SUMIFS($K$28:$K$55,$H$28:$H$55,2026,$I$28:$I$55,11,$L$28:$L$55,"Y") -> 0 | L20: =SUMIFS($K$28:$K$55,$H$28:$H$55,2026,$I$28:$I$55,12,$L$28:$L$55,"Y") -> 0
A22: 2027 | B22: =SUM(A24:L24) -> 0
A23: 01 | B23: 02 | C23: 03 | D23: 04 | E23: 05 | F23: 06 | G23: 07 | H23: 08 | I23: 09 | J23: 10 | K23: 11 | L23: 12
A24: =SUMIFS($K$28:$K$55,$H$28:$H$55,2027,$I$28:$I$55,1,$L$28:$L$55,"Y") -> 0 | B24: =SUMIFS($K$28:$K$55,$H$28:$H$55,2027,$I$28:$I$55,2,$L$28:$L$55,"Y") -> 0 | C24: =SUMIFS($K$28:$K$55,$H$28:$H$55,2027,$I$28:$I$55,3,$L$28:$L$55,"Y") -> 0 | D24: =SUMIFS($K$28:$K$55,$H$28:$H$55,2027,$I$28:$I$55,4,$L$28:$L$55,"Y") -> 0 | E24: =SUMIFS($K$28:$K$55,$H$28:$H$55,2027,$I$28:$I$55,5,$L$28:$L$55,"Y") -> 0 | F24: =SUMIFS($K$28:$K$55,$H$28:$H$55,2027,$I$28:$I$55,6,$L$28:$L$55,"Y") -> 0 | G24: =SUMIFS($K$28:$K$55,$H$28:$H$55,2027,$I$28:$I$55,7,$L$28:$L$55,"Y") -> 0 | H24: =SUMIFS($K$28:$K$55,$H$28:$H$55,2027,$I$28:$I$55,8,$L$28:$L$55,"Y") -> 0 | I24: =SUMIFS($K$28:$K$55,$H$28:$H$55,2027,$I$28:$I$55,9,$L$28:$L$55,"Y") -> 0 | J24: =SUMIFS($K$28:$K$55,$H$28:$H$55,2027,$I$28:$I$55,10,$L$28:$L$55,"Y") -> 0 | K24: =SUMIFS($K$28:$K$55,$H$28:$H$55,2027,$I$28:$I$55,11,$L$28:$L$55,"Y") -> 0 | L24: =SUMIFS($K$28:$K$55,$H$28:$H$55,2027,$I$28:$I$55,12,$L$28:$L$55,"Y") -> 0
A26: 3. Costs Details
A27: Study 분류 | B27: CTA# | C27: Milestones | D27: Budget Amount(₩) VAT제외 | E27: Invoiced Amount(₩) | F27: Invoice # | G27: Invoiced Date | H27: Paid Year | I27: Paid Month | J27: Paid Date | K27: Total Amount(₩) VAT 포함 | L27: Paid (Y) | M27: 지출결의 #
A28: SS4 | B28: CLA25028_20250430 | C28: CTA FE | D28: 12900000 | E28: 12900000 | G28: 45819 | H28: 2025 | I28: 6 | J28: 26 | K28: 14190000 | L28: Y | M28: CO25-127
B29: CLA25028_20250430 | C29: 시료분석 개시 후 | D29: 25800000 | E29: 25800000 | G29: 45978 | H29: 2025 | I29: 11 | J29: 27 | K29: 28380000 | L29: Y | M29: CO125-004
B30: CLA25028_20250430 | C30: 계약 시료수 50% 이상 분석 | D30: 25800000
B31: CLA25028_20250430 | C31: 의뢰사의 보고서 초안 수령 | D31: 25800000
B32: CLA25028_20250430 | C32: 의뢰사의 최종 결과 보고서 승인 | D32: 38700000
B33: CLA25028_20250430 | C33: site의 sampling kit 수령 확인 | D33: 6138000
B34: CLA25028_20250430 | C34: 각 이송건의 검체 수령 확인 | D34: 105462000
A43: SS2 | B43: CLA25085_20251124 | C43: CTA FE | D43: 10800000 | E43: 10800000 | G43: 46003 | H43: 2025 | I43: 12 | J43: 18 | K43: 11880000 | L43: Y | M43: CO125-023
B44: CLA25085_20251124 | C44: Sample analysis protocol 승인 | D44: 8100000
B45: CLA25085_20251124 | C45: 시료분석 개시 | D45: 8100000
B46: CLA25085_20251124 | C46: 시료분석 완료 | D46: 16200000
B47: CLA25085_20251124 | C47: 의뢰사의 최종 결과 보고서 승인 | D47: 10800000
C56: Total | D56: =SUM(D28:D55) -> 294600000

Sheet 8. Invivo
A1: 6. Invivo
B2: Contract Number: | D2: Version & date:
A4: Protocol No: TTK-CS-101 | D4: Updated on:
A6: 1. Total Payment Status
A7: Category | B7: $ | C7: %
A8: Budget | B8: =C50 -> 490894
A9: Paid | B9: =B14+B19+B24 -> 213142.36 | C9: =B9/B8 -> 0.43419223
A10: Remaining | B10: =B8-B9 -> 277751.64 | C10: =B10/B8 -> 0.56580777
A12: 2. Yearly and Monthly Payment
B13: USD | C13: KRW
A14: 2025 | B14: =SUM(A16:L16) -> 184437.87 | C14: =SUM(A17:L17) -> 184330.91
A15: 01 | B15: 02 | C15: 03 | D15: 04 | E15: 05 | F15: 06 | G15: 07 | H15: 08 | I15: 09 | J15: 10 | K15: 11 | L15: 12
A16: =SUMIFS($D$31:$D$49,$G$31:$G$49,2025,$H$31:$H$49,1,$K$31:$K$49,"Y") -> 0 | B16: =SUMIFS($D$31:$D$49,$G$31:$G$49,2025,$H$31:$H$49,2,$K$31:$K$49,"Y") -> 0 | C16: =SUMIFS($D$31:$D$49,$G$31:$G$49,2025,$H$31:$H$49,3,$K$31:$K$49,"Y") -> 0 | D16: =SUMIFS($D$31:$D$49,$G$31:$G$49,2025,$H$31:$H$49,4,$K$31:$K$49,"Y") -> 0 | E16: =SUMIFS($D$31:$D$49,$G$31:$G$49,2025,$H$31:$H$49,5,$K$31:$K$49,"Y") -> 0 | F16: =SUMIFS($D$31:$D$49,$G$31:$G$49,2025,$H$31:$H$49,6,$K$31:$K$49,"Y") -> 0 | G16: =SUMIFS($D$31:$D$49,$G$31:$G$49,2025,$H$31:$H$49,7,$K$31:$K$49,"Y") -> 0 | H16: =SUMIFS($D$31:$D$49,$G$31:$G$49,2025,$H$31:$H$49,8,$K$31:$K$49,"Y") -> 162651 | I16: =SUMIFS($D$31:$D$49,$G$31:$G$49,2025,$H$31:$H$49,9,$K$31:$K$49,"Y") -> 4038 | J16: =SUMIFS($D$31:$D$49,$G$31:$G$49,2025,$H$31:$H$49,10,$K$31:$K$49,"Y") -> 9255.57 | K16: =SUMIFS($D$31:$D$49,$G$31:$G$49,2025,$H$31:$H$49,11,$K$31:$K$49,"Y") -> 4317.74 | L16: =SUMIFS($D$31:$D$49,$G$31:$G$49,2025,$H$31:$H$49,12,$K$31:$K$49,"Y") -> 4175.56
A17: =SUMIFS($J$31:$J$49,$G$31:$G$49,2025,$H$31:$H$49,1,$K$31:$K$49,"Y") -> 0 | B17: =SUMIFS($J$31:$J$49,$G$31:$G$49,2025,$H$31:$H$49,2,$K$31:$K$49,"Y") -> 0 | C17: =SUMIFS($J$31:$J$49,$G$31:$G$49,2025,$H$31:$H$49,3,$K$31:$K$49,"Y") -> 0 | D17: =SUMIFS($J$31:$J$49,$G$31:$G$49,2025,$H$31:$H$49,4,$K$31:$K$49,"Y") -> 0 | E17: =SUMIFS($J$31:$J$49,$G$31:$G$49,2025,$H$31:$H$49,5,$K$31:$K$49,"Y") -> 0 | F17: =SUMIFS($J$31:$J$49,$G$31:$G$49,2025,$H$31:$H$49,6,$K$31:$K$49,"Y") -> 0 | G17: =SUMIFS($J$31:$J$49,$G$31:$G$49,2025,$H$31:$H$49,7,$K$31:$K$49,"Y") -> 0 | H17: =SUMIFS($J$31:$J$49,$G$31:$G$49,2025,$H$31:$H$49,8,$K$31:$K$49,"Y") -> 162651 | I17: =SUMIFS($J$31:$J$49,$G$31:$G$49,2025,$H$31:$H$49,9,$K$31:$K$49,"Y") -> 4038 | J17: =SUMIFS($J$31:$J$49,$G$31:$G$49,2025,$H$31:$H$49,10,$K$31:$K$49,"Y") -> 9148.61 | K17: =SUMIFS($J$31:$J$49,$G$31:$G$49,2025,$H$31:$H$49,11,$K$31:$K$49,"Y") -> 4317.74 | L17: =SUMIFS($J$31:$J$49,$G$31:$G$49,2025,$H$31:$H$49,12,$K$31:$K$49,"Y") -> 4175.56
A19: 2026 | B19: =SUM(A21:L21) -> 28704.49 | C19: =SUM(A22:L22) -> 28704.49
A20: 01 | B20: 02 | C20: 03 | D20: 04 | E20: 05 | F20: 06 | G20: 07 | H20: 08 | I20: 09 | J20: 10 | K20: 11 | L20: 12
A21: =SUMIFS($D$31:$D$49,$G$31:$G$49,2026,$H$31:$H$49,1,$K$31:$K$49,"Y") -> 4512.03 | B21: =SUMIFS($D$31:$D$49,$G$31:$G$49,2026,$H$31:$H$49,2,$K$31:$K$49,"Y") -> 0 | C21: =SUMIFS($D$31:$D$49,$G$31:$G$49,2026,$H$31:$H$49,3,$K$31:$K$49,"Y") -> 8972.12 | D21: =SUMIFS($D$31:$D$49,$G$31:$G$49,2026,$H$31:$H$49,4,$K$31:$K$49,"Y") -> 6668.66 | E21: =SUMIFS($D$31:$D$49,$G$31:$G$49,2026,$H$31:$H$49,5,$K$31:$K$49,"Y") -> 4148 | F21: =SUMIFS($D$31:$D$49,$G$31:$G$49,2026,$H$31:$H$49,6,$K$31:$K$49,"Y") -> 4403.68 | G21: =SUMIFS($D$31:$D$49,$G$31:$G$49,2026,$H$31:$H$49,7,$K$31:$K$49,"Y") -> 0 | H21: =SUMIFS($D$31:$D$49,$G$31:$G$49,2026,$H$31:$H$49,8,$K$31:$K$49,"Y") -> 0 | I21: =SUMIFS($D$31:$D$49,$G$31:$G$49,2026,$H$31:$H$49,9,$K$31:$K$49,"Y") -> 0 | J21: =SUMIFS($D$31:$D$49,$G$31:$G$49,2026,$H$31:$H$49,10,$K$31:$K$49,"Y") -> 0 | K21: =SUMIFS($D$31:$D$49,$G$31:$G$49,2026,$H$31:$H$49,11,$K$31:$K$49,"Y") -> 0 | L21: =SUMIFS($D$31:$D$49,$G$31:$G$49,2026,$H$31:$H$49,12,$K$31:$K$49,"Y") -> 0
A22: =SUMIFS($J$31:$J$49,$G$31:$G$49,2026,$H$31:$H$49,1,$K$31:$K$49,"Y") -> 4512.03 | B22: =SUMIFS($J$31:$J$49,$G$31:$G$49,2026,$H$31:$H$49,2,$K$31:$K$49,"Y") -> 0 | C22: =SUMIFS($J$31:$J$49,$G$31:$G$49,2026,$H$31:$H$49,3,$K$31:$K$49,"Y") -> 8972.12 | D22: =SUMIFS($J$31:$J$49,$G$31:$G$49,2026,$H$31:$H$49,4,$K$31:$K$49,"Y") -> 6668.66 | E22: =SUMIFS($J$31:$J$49,$G$31:$G$49,2026,$H$31:$H$49,5,$K$31:$K$49,"Y") -> 4148 | F22: =SUMIFS($J$31:$J$49,$G$31:$G$49,2026,$H$31:$H$49,6,$K$31:$K$49,"Y") -> 4403.68 | G22: =SUMIFS($J$31:$J$49,$G$31:$G$49,2026,$H$31:$H$49,7,$K$31:$K$49,"Y") -> 0 | H22: =SUMIFS($J$31:$J$49,$G$31:$G$49,2026,$H$31:$H$49,8,$K$31:$K$49,"Y") -> 0 | I22: =SUMIFS($J$31:$J$49,$G$31:$G$49,2026,$H$31:$H$49,9,$K$31:$K$49,"Y") -> 0 | J22: =SUMIFS($J$31:$J$49,$G$31:$G$49,2026,$H$31:$H$49,10,$K$31:$K$49,"Y") -> 0 | K22: =SUMIFS($J$31:$J$49,$G$31:$G$49,2026,$H$31:$H$49,11,$K$31:$K$49,"Y") -> 0 | L22: =SUMIFS($J$31:$J$49,$G$31:$G$49,2026,$H$31:$H$49,12,$K$31:$K$49,"Y") -> 0
A24: 2027 | B24: =SUM(A26:L26) -> 0 | C24: =SUM(A27:L27) -> 0
A25: 01 | B25: 02 | C25: 03 | D25: 04 | E25: 05 | F25: 06 | G25: 07 | H25: 08 | I25: 09 | J25: 10 | K25: 11 | L25: 12
A26: =SUMIFS($D$31:$D$49,$G$31:$G$49,2027,$H$31:$H$49,1,$K$31:$K$49,"Y") -> 0 | B26: =SUMIFS($D$31:$D$49,$G$31:$G$49,2027,$H$31:$H$49,2,$K$31:$K$49,"Y") -> 0 | C26: =SUMIFS($D$31:$D$49,$G$31:$G$49,2027,$H$31:$H$49,3,$K$31:$K$49,"Y") -> 0 | D26: =SUMIFS($D$31:$D$49,$G$31:$G$49,2027,$H$31:$H$49,4,$K$31:$K$49,"Y") -> 0 | E26: =SUMIFS($D$31:$D$49,$G$31:$G$49,2027,$H$31:$H$49,5,$K$31:$K$49,"Y") -> 0 | F26: =SUMIFS($D$31:$D$49,$G$31:$G$49,2027,$H$31:$H$49,6,$K$31:$K$49,"Y") -> 0 | G26: =SUMIFS($D$31:$D$49,$G$31:$G$49,2027,$H$31:$H$49,7,$K$31:$K$49,"Y") -> 0 | H26: =SUMIFS($D$31:$D$49,$G$31:$G$49,2027,$H$31:$H$49,8,$K$31:$K$49,"Y") -> 0 | I26: =SUMIFS($D$31:$D$49,$G$31:$G$49,2027,$H$31:$H$49,9,$K$31:$K$49,"Y") -> 0 | J26: =SUMIFS($D$31:$D$49,$G$31:$G$49,2027,$H$31:$H$49,10,$K$31:$K$49,"Y") -> 0 | K26: =SUMIFS($D$31:$D$49,$G$31:$G$49,2027,$H$31:$H$49,11,$K$31:$K$49,"Y") -> 0 | L26: =SUMIFS($D$31:$D$49,$G$31:$G$49,2027,$H$31:$H$49,12,$K$31:$K$49,"Y") -> 0
A27: =SUMIFS($J$31:$J$49,$G$31:$G$49,2027,$H$31:$H$49,1,$K$31:$K$49,"Y") -> 0 | B27: =SUMIFS($J$31:$J$49,$G$31:$G$49,2027,$H$31:$H$49,2,$K$31:$K$49,"Y") -> 0 | C27: =SUMIFS($J$31:$J$49,$G$31:$G$49,2027,$H$31:$H$49,3,$K$31:$K$49,"Y") -> 0 | D27: =SUMIFS($J$31:$J$49,$G$31:$G$49,2027,$H$31:$H$49,4,$K$31:$K$49,"Y") -> 0 | E27: =SUMIFS($J$31:$J$49,$G$31:$G$49,2027,$H$31:$H$49,5,$K$31:$K$49,"Y") -> 0 | F27: =SUMIFS($J$31:$J$49,$G$31:$G$49,2027,$H$31:$H$49,6,$K$31:$K$49,"Y") -> 0 | G27: =SUMIFS($J$31:$J$49,$G$31:$G$49,2027,$H$31:$H$49,7,$K$31:$K$49,"Y") -> 0 | H27: =SUMIFS($J$31:$J$49,$G$31:$G$49,2027,$H$31:$H$49,8,$K$31:$K$49,"Y") -> 0 | I27: =SUMIFS($J$31:$J$49,$G$31:$G$49,2027,$H$31:$H$49,9,$K$31:$K$49,"Y") -> 0 | J27: =SUMIFS($J$31:$J$49,$G$31:$G$49,2027,$H$31:$H$49,10,$K$31:$K$49,"Y") -> 0 | K27: =SUMIFS($J$31:$J$49,$G$31:$G$49,2027,$H$31:$H$49,11,$K$31:$K$49,"Y") -> 0 | L27: =SUMIFS($J$31:$J$49,$G$31:$G$49,2027,$H$31:$H$49,12,$K$31:$K$49,"Y") -> 0
A29: 3. Costs Details
A30: Service Deliverables | B30: Milestones | C30: Budget Amount($) | D30: Invoiced Amount($) | E30: Invoice # | F30: Invoiced Date | G30: Paid Year | H30: Paid Month | I30: Paid Date | J30: Total Amount($) | K30: Paid (Y) | L30: 지출결의 #
A31: Study setup fee | B31: Upfront fee due upon WO effective date (non-refundable) | C31: 25000 | D31: 162651 | E31: 110007019 | F31: 45838 | G31: 2025 | H31: 8 | I31: 14 | J31: 162651 | K31: Y | L31: CD25-153
A32: Data Management Fee | C32: 25000 | D32: 4038 | E32: 110007238 | F32: 45869 | G32: 2025 | H32: 9 | I32: 11 | J32: 4038 | K32: Y | L32: CD25-173
A33: Collection Kits | C33: 12000 | D33: 4796.15 | E33: 110007486 | F33: 45900 | G33: 2025 | H33: 10 | I33: 30 | J33: 4689.19 | K33: Y | L33: CD25-194
A34: 25% of the Testing Services | C34: 92575 | D34: 4459.42 | E34: 110007719 | F34: 45930 | G34: 2025 | H34: 10 | I34: 30 | J34: 4459.42 | K34: Y | L34: CD25-194
A35: Project Management Fee (13 months) | B35: $4,038, Monthly for 13 months | C35: 52494 | D35: 4317.74 | E35: 110007978 | F35: 45961 | G35: 2025 | H35: 11 | I35: 27 | J35: 4317.74 | K35: Y | L35: CD25-208
A36: 75% of the Testing Services | B36: Monthly, based on the # of samples tested and reported during that month | C36: 277725 | D36: 4175.56 | E36: 110008236 | F36: 45991 | G36: 2025 | H36: 12 | I36: 24 | J36: 4175.56 | K36: Y | L36: CD25-226
A37: Storage Fee | B37: Monthly | C37: 4550 | D37: 4512.03 | E37: 110008460 | F37: 46022 | G37: 2026 | H37: 1 | I37: 22 | J37: 4512.03 | K37: Y | L37: CD26-005
A38: Disposition/Shipment Base Fee | B38: Upon disposition/transfer | C38: 500 | D38: 4246.09 | E38: 110008812 | F38: 46053 | G38: 2026 | H38: 3 | I38: 26 | J38: 4246.09 | K38: Y | L38: CD26-035
A39: Disposition/Shipment Per Sample Fee | B39: Upon disposition/transfer ($15) | C39: 1050 | D39: 4726.03 | E39: 110009031 | F39: 46081 | G39: 2026 | H39: 3 | I39: 26 | J39: 4726.03 | K39: Y | L39: CD26-037
A40: Pass-through expenses | B40: To be billed as incurred | D40: 6668.66 | E40: 110009327 | F40: 46112 | G40: 2026 | H40: 4 | I40: 23 | J40: 6668.66 | K40: Y | L40: CD26-049
A41: Storage Fee | B41: Monthly | D41: 4148 | E41: 110009659 | F41: 46142 | G41: 2026 | H41: 5 | I41: 21 | J41: 4148 | K41: Y | L41: CO26-018
A42: Storage Fee | B42: Monthly | D42: 4403.68 | E42: 110009972 | F42: 46173 | G42: 2026 | H42: 6 | I42: 18 | J42: 4403.68 | K42: Y | L42: CO26-033
A43: Storage Fee | B43: Monthly | D43: 4421.08 | E43: 110010223 | F43: 46203 | G43: 2026
B50: Total | C50: =SUM(C31:C49) -> 490894

Sheet 9. Labconnect
A1: 9. LabConnect
B2: Contract Number: | D2: Version & date:
A4: Protocol No: TTK-CS-101 | D4: Updated on:
A6: 1. Total Payment Status
A7: Category | B7: $ | C7: %
A8: Budget | B8: =D39 -> 68277
A9: Paid | B9: =B14+B19+B24 -> 45962.23 | C9: =B9/B8 -> 0.67317296
A10: Remaining | B10: =B8-B9 -> 22314.77 | C10: =B10/B8 -> 0.32682704
A12: 2. Yearly and Monthly Payment
B13: USD | C13: KRW
A14: 2025 | B14: =SUM(A16:L16) -> 45962.23 | C14: =SUM(A17:L17) -> 45962.26
A15: 01 | B15: 02 | C15: 03 | D15: 04 | E15: 05 | F15: 06 | G15: 07 | H15: 08 | I15: 09 | J15: 10 | K15: 11 | L15: 12
A16: =SUMIFS($E$31:$E$38,$H$31:$H$38,2025,$I$31:$I$38,1,$L$31:$L$38,"Y") -> 0 | B16: =SUMIFS($E$31:$E$38,$H$31:$H$38,2025,$I$31:$I$38,2,$L$31:$L$38,"Y") -> 0 | C16: =SUMIFS($E$31:$E$38,$H$31:$H$38,2025,$I$31:$I$38,3,$L$31:$L$38,"Y") -> 0 | D16: =SUMIFS($E$31:$E$38,$H$31:$H$38,2025,$I$31:$I$38,4,$L$31:$L$38,"Y") -> 0 | E16: =SUMIFS($E$31:$E$38,$H$31:$H$38,2025,$I$31:$I$38,5,$L$31:$L$38,"Y") -> 0 | F16: =SUMIFS($E$31:$E$38,$H$31:$H$38,2025,$I$31:$I$38,6,$L$31:$L$38,"Y") -> 0 | G16: =SUMIFS($E$31:$E$38,$H$31:$H$38,2025,$I$31:$I$38,7,$L$31:$L$38,"Y") -> 0 | H16: =SUMIFS($E$31:$E$38,$H$31:$H$38,2025,$I$31:$I$38,8,$L$31:$L$38,"Y") -> 0 | I16: =SUMIFS($E$31:$E$38,$H$31:$H$38,2025,$I$31:$I$38,9,$L$31:$L$38,"Y") -> 45130 | J16: =SUMIFS($E$31:$E$38,$H$31:$H$38,2025,$I$31:$I$38,10,$L$31:$L$38,"Y") -> 0 | K16: =SUMIFS($E$31:$E$38,$H$31:$H$38,2025,$I$31:$I$38,11,$L$31:$L$38,"Y") -> 0 | L16: =SUMIFS($E$31:$E$38,$H$31:$H$38,2025,$I$31:$I$38,12,$L$31:$L$38,"Y") -> 832.23
A17: =SUMIFS($K$31:$K$38,$H$31:$H$38,2025,$I$31:$I$38,1,$L$31:$L$38,"Y") -> 0 | B17: =SUMIFS($K$31:$K$38,$H$31:$H$38,2025,$I$31:$I$38,2,$L$31:$L$38,"Y") -> 0 | C17: =SUMIFS($K$31:$K$38,$H$31:$H$38,2025,$I$31:$I$38,3,$L$31:$L$38,"Y") -> 0 | D17: =SUMIFS($K$31:$K$38,$H$31:$H$38,2025,$I$31:$I$38,4,$L$31:$L$38,"Y") -> 0 | E17: =SUMIFS($K$31:$K$38,$H$31:$H$38,2025,$I$31:$I$38,5,$L$31:$L$38,"Y") -> 0 | F17: =SUMIFS($K$31:$K$38,$H$31:$H$38,2025,$I$31:$I$38,6,$L$31:$L$38,"Y") -> 0 | G17: =SUMIFS($K$31:$K$38,$H$31:$H$38,2025,$I$31:$I$38,7,$L$31:$L$38,"Y") -> 0 | H17: =SUMIFS($K$31:$K$38,$H$31:$H$38,2025,$I$31:$I$38,8,$L$31:$L$38,"Y") -> 0 | I17: =SUMIFS($K$31:$K$38,$H$31:$H$38,2025,$I$31:$I$38,9,$L$31:$L$38,"Y") -> 45130 | J17: =SUMIFS($K$31:$K$38,$H$31:$H$38,2025,$I$31:$I$38,10,$L$31:$L$38,"Y") -> 0 | K17: =SUMIFS($K$31:$K$38,$H$31:$H$38,2025,$I$31:$I$38,11,$L$31:$L$38,"Y") -> 0 | L17: =SUMIFS($K$31:$K$38,$H$31:$H$38,2025,$I$31:$I$38,12,$L$31:$L$38,"Y") -> 832.26
A19: 2026 | B19: =SUM(A21:L21) -> 0 | C19: =SUM(A22:L22) -> 0
A20: 01 | B20: 02 | C20: 03 | D20: 04 | E20: 05 | F20: 06 | G20: 07 | H20: 08 | I20: 09 | J20: 10 | K20: 11 | L20: 12
A21: =SUMIFS($E$31:$E$38,$H$31:$H$38,2026,$I$31:$I$38,1,$L$31:$L$38,"Y") -> 0 | B21: =SUMIFS($E$31:$E$38,$H$31:$H$38,2026,$I$31:$I$38,2,$L$31:$L$38,"Y") -> 0 | C21: =SUMIFS($E$31:$E$38,$H$31:$H$38,2026,$I$31:$I$38,3,$L$31:$L$38,"Y") -> 0 | D21: =SUMIFS($E$31:$E$38,$H$31:$H$38,2026,$I$31:$I$38,4,$L$31:$L$38,"Y") -> 0 | E21: =SUMIFS($E$31:$E$38,$H$31:$H$38,2026,$I$31:$I$38,5,$L$31:$L$38,"Y") -> 0 | F21: =SUMIFS($E$31:$E$38,$H$31:$H$38,2026,$I$31:$I$38,6,$L$31:$L$38,"Y") -> 0 | G21: =SUMIFS($E$31:$E$38,$H$31:$H$38,2026,$I$31:$I$38,7,$L$31:$L$38,"Y") -> 0 | H21: =SUMIFS($E$31:$E$38,$H$31:$H$38,2026,$I$31:$I$38,8,$L$31:$L$38,"Y") -> 0 | I21: =SUMIFS($E$31:$E$38,$H$31:$H$38,2026,$I$31:$I$38,9,$L$31:$L$38,"Y") -> 0 | J21: =SUMIFS($E$31:$E$38,$H$31:$H$38,2026,$I$31:$I$38,10,$L$31:$L$38,"Y") -> 0 | K21: =SUMIFS($E$31:$E$38,$H$31:$H$38,2026,$I$31:$I$38,11,$L$31:$L$38,"Y") -> 0 | L21: =SUMIFS($E$31:$E$38,$H$31:$H$38,2026,$I$31:$I$38,12,$L$31:$L$38,"Y") -> 0
A22: =SUMIFS($K$31:$K$38,$H$31:$H$38,2026,$I$31:$I$38,1,$L$31:$L$38,"Y") -> 0 | B22: =SUMIFS($K$31:$K$38,$H$31:$H$38,2026,$I$31:$I$38,2,$L$31:$L$38,"Y") -> 0 | C22: =SUMIFS($K$31:$K$38,$H$31:$H$38,2026,$I$31:$I$38,3,$L$31:$L$38,"Y") -> 0 | D22: =SUMIFS($K$31:$K$38,$H$31:$H$38,2026,$I$31:$I$38,4,$L$31:$L$38,"Y") -> 0 | E22: =SUMIFS($K$31:$K$38,$H$31:$H$38,2026,$I$31:$I$38,5,$L$31:$L$38,"Y") -> 0 | F22: =SUMIFS($K$31:$K$38,$H$31:$H$38,2026,$I$31:$I$38,6,$L$31:$L$38,"Y") -> 0 | G22: =SUMIFS($K$31:$K$38,$H$31:$H$38,2026,$I$31:$I$38,7,$L$31:$L$38,"Y") -> 0 | H22: =SUMIFS($K$31:$K$38,$H$31:$H$38,2026,$I$31:$I$38,8,$L$31:$L$38,"Y") -> 0 | I22: =SUMIFS($K$31:$K$38,$H$31:$H$38,2026,$I$31:$I$38,9,$L$31:$L$38,"Y") -> 0 | J22: =SUMIFS($K$31:$K$38,$H$31:$H$38,2026,$I$31:$I$38,10,$L$31:$L$38,"Y") -> 0 | K22: =SUMIFS($K$31:$K$38,$H$31:$H$38,2026,$I$31:$I$38,11,$L$31:$L$38,"Y") -> 0 | L22: =SUMIFS($K$31:$K$38,$H$31:$H$38,2026,$I$31:$I$38,12,$L$31:$L$38,"Y") -> 0
A24: 2027 | B24: =SUM(A26:L26) -> 0 | C24: =SUM(A27:L27) -> 0
A25: 01 | B25: 02 | C25: 03 | D25: 04 | E25: 05 | F25: 06 | G25: 07 | H25: 08 | I25: 09 | J25: 10 | K25: 11 | L25: 12
A26: =SUMIFS($E$31:$E$38,$H$31:$H$38,2027,$I$31:$I$38,1,$L$31:$L$38,"Y") -> 0 | B26: =SUMIFS($E$31:$E$38,$H$31:$H$38,2027,$I$31:$I$38,2,$L$31:$L$38,"Y") -> 0 | C26: =SUMIFS($E$31:$E$38,$H$31:$H$38,2027,$I$31:$I$38,3,$L$31:$L$38,"Y") -> 0 | D26: =SUMIFS($E$31:$E$38,$H$31:$H$38,2027,$I$31:$I$38,4,$L$31:$L$38,"Y") -> 0 | E26: =SUMIFS($E$31:$E$38,$H$31:$H$38,2027,$I$31:$I$38,5,$L$31:$L$38,"Y") -> 0 | F26: =SUMIFS($E$31:$E$38,$H$31:$H$38,2027,$I$31:$I$38,6,$L$31:$L$38,"Y") -> 0 | G26: =SUMIFS($E$31:$E$38,$H$31:$H$38,2027,$I$31:$I$38,7,$L$31:$L$38,"Y") -> 0 | H26: =SUMIFS($E$31:$E$38,$H$31:$H$38,2027,$I$31:$I$38,8,$L$31:$L$38,"Y") -> 0 | I26: =SUMIFS($E$31:$E$38,$H$31:$H$38,2027,$I$31:$I$38,9,$L$31:$L$38,"Y") -> 0 | J26: =SUMIFS($E$31:$E$38,$H$31:$H$38,2027,$I$31:$I$38,10,$L$31:$L$38,"Y") -> 0 | K26: =SUMIFS($E$31:$E$38,$H$31:$H$38,2027,$I$31:$I$38,11,$L$31:$L$38,"Y") -> 0 | L26: =SUMIFS($E$31:$E$38,$H$31:$H$38,2027,$I$31:$I$38,12,$L$31:$L$38,"Y") -> 0
A27: =SUMIFS($K$31:$K$38,$H$31:$H$38,2027,$I$31:$I$38,1,$L$31:$L$38,"Y") -> 0 | B27: =SUMIFS($K$31:$K$38,$H$31:$H$38,2027,$I$31:$I$38,2,$L$31:$L$38,"Y") -> 0 | C27: =SUMIFS($K$31:$K$38,$H$31:$H$38,2027,$I$31:$I$38,3,$L$31:$L$38,"Y") -> 0 | D27: =SUMIFS($K$31:$K$38,$H$31:$H$38,2027,$I$31:$I$38,4,$L$31:$L$38,"Y") -> 0 | E27: =SUMIFS($K$31:$K$38,$H$31:$H$38,2027,$I$31:$I$38,5,$L$31:$L$38,"Y") -> 0 | F27: =SUMIFS($K$31:$K$38,$H$31:$H$38,2027,$I$31:$I$38,6,$L$31:$L$38,"Y") -> 0 | G27: =SUMIFS($K$31:$K$38,$H$31:$H$38,2027,$I$31:$I$38,7,$L$31:$L$38,"Y") -> 0 | H27: =SUMIFS($K$31:$K$38,$H$31:$H$38,2027,$I$31:$I$38,8,$L$31:$L$38,"Y") -> 0 | I27: =SUMIFS($K$31:$K$38,$H$31:$H$38,2027,$I$31:$I$38,9,$L$31:$L$38,"Y") -> 0 | J27: =SUMIFS($K$31:$K$38,$H$31:$H$38,2027,$I$31:$I$38,10,$L$31:$L$38,"Y") -> 0 | K27: =SUMIFS($K$31:$K$38,$H$31:$H$38,2027,$I$31:$I$38,11,$L$31:$L$38,"Y") -> 0 | L27: =SUMIFS($K$31:$K$38,$H$31:$H$38,2027,$I$31:$I$38,12,$L$31:$L$38,"Y") -> 0
A29: 3. Costs Details
A30: Contract # | D30: Budget Amount($) | E30: Invoiced Amount($) | F30: Invoice # | G30: Invoiced Date | H30: Paid Year | I30: Paid Month | J30: Paid Date | K30: Total Amount(₩) | L30: Paid (Y) | M30: 지출결의 #
A31: SLJNS101_ver.4.0 | B31: Advance Payment | C31: Project Initiation, non-refundable | D31: 14530 | E31: 45130 | F31: SI145264 | G31: 45889 | H31: 2025 | I31: 9 | J31: 11 | K31: 45130 | L31: Y | M31: CD25-182
A32: SLJNS101_ver.4.0 | C32: Expedited Startup, non-refundable | D32: 18900 | E32: 832.23 | F32: SI146666 | G32: 45979 | H32: 2025 | I32: 12 | J32: 11 | K32: 832.26 | L32: Y | M32: CD25-214
A33: SLJNS101_ver.4.0 | C33: Project Deposit (will be credited to final invoices) | D33: 13655
A34: SLJNS101_ver.4.0 | B34: Maintenance | C34: Project Management | D34: 11700
A35: SLJNS101_ver.4.0 | C35: Supplies | D35: 22240
A36: SLJNS101_ver.4.0 | C36: Logistics | D36: 4275
A37: SLJNS101_ver.4.0 | B37: Discount & Credit | C37: Discount | D37: =-3368 -> -3368
A38: SLJNS101_ver.4.0 | C38: To be credited to final invoices | D38: =-D33 -> -13655
C39: Total | D39: =SUM(D31:D38) -> 68277

Sheet 10. AIMS
A1: 7. AIMS
B2: Contract Number: | D2: Version & date:
A4: Protocol No: TTK-CS-101 | D4: Updated on:
A6: 1. Total Payment Status
A7: Category | B7: ₩ | C7: %
A8: Budget | B8: =C59 -> 367130000
A9: Paid | B9: =B14+B18+B22+B26+B30 -> 250597600 | C9: =B9/B8 -> 0.68258546
A10: Remaining | B10: =B8-B9 -> 116532400 | C10: =B10/B8 -> 0.31741454
A12: 2. Yearly and Monthly Payment
B13: KRW
A14: 2023 | B14: =SUM(A16:L16) -> 23650000
A15: 01 | B15: 02 | C15: 03 | D15: 04 | E15: 05 | F15: 06 | G15: 07 | H15: 08 | I15: 09 | J15: 10 | K15: 11 | L15: 12
A16: =SUMIFS($J$36:$J$58,$G$36:$G$58,2023,$H$36:$H$58,1,$K$36:$K$58,"Y") -> 0 | B16: =SUMIFS($J$36:$J$58,$G$36:$G$58,2023,$H$36:$H$58,2,$K$36:$K$58,"Y") -> 0 | C16: =SUMIFS($J$36:$J$58,$G$36:$G$58,2023,$H$36:$H$58,3,$K$36:$K$58,"Y") -> 0 | D16: =SUMIFS($J$36:$J$58,$G$36:$G$58,2023,$H$36:$H$58,4,$K$36:$K$58,"Y") -> 0 | E16: =SUMIFS($J$36:$J$58,$G$36:$G$58,2023,$H$36:$H$58,5,$K$36:$K$58,"Y") -> 0 | F16: =SUMIFS($J$36:$J$58,$G$36:$G$58,2023,$H$36:$H$58,6,$K$36:$K$58,"Y") -> 0 | G16: =SUMIFS($J$36:$J$58,$G$36:$G$58,2023,$H$36:$H$58,7,$K$36:$K$58,"Y") -> 0 | H16: =SUMIFS($J$36:$J$58,$G$36:$G$58,2023,$H$36:$H$58,8,$K$36:$K$58,"Y") -> 0 | I16: =SUMIFS($J$36:$J$58,$G$36:$G$58,2023,$H$36:$H$58,9,$K$36:$K$58,"Y") -> 0 | J16: =SUMIFS($J$36:$J$58,$G$36:$G$58,2023,$H$36:$H$58,10,$K$36:$K$58,"Y") -> 23650000 | K16: =SUMIFS($J$36:$J$58,$G$36:$G$58,2023,$H$36:$H$58,11,$K$36:$K$58,"Y") -> 0 | L16: =SUMIFS($J$36:$J$58,$G$36:$G$58,2023,$H$36:$H$58,12,$K$36:$K$58,"Y") -> 0
A18: 2024 | B18: =SUM(A20:L20) -> 100094500
A19: 01 | B19: 02 | C19: 03 | D19: 04 | E19: 05 | F19: 06 | G19: 07 | H19: 08 | I19: 09 | J19: 10 | K19: 11 | L19: 12
A20: =SUMIFS($J$36:$J$58,$G$36:$G$58,2024,$H$36:$H$58,1,$K$36:$K$58,"Y") -> 0 | B20: =SUMIFS($J$36:$J$58,$G$36:$G$58,2024,$H$36:$H$58,2,$K$36:$K$58,"Y") -> 0 | C20: =SUMIFS($J$36:$J$58,$G$36:$G$58,2024,$H$36:$H$58,3,$K$36:$K$58,"Y") -> 0 | D20: =SUMIFS($J$36:$J$58,$G$36:$G$58,2024,$H$36:$H$58,4,$K$36:$K$58,"Y") -> 0 | E20: =SUMIFS($J$36:$J$58,$G$36:$G$58,2024,$H$36:$H$58,5,$K$36:$K$58,"Y") -> 0 | F20: =SUMIFS($J$36:$J$58,$G$36:$G$58,2024,$H$36:$H$58,6,$K$36:$K$58,"Y") -> 0 | G20: =SUMIFS($J$36:$J$58,$G$36:$G$58,2024,$H$36:$H$58,7,$K$36:$K$58,"Y") -> 37620000 | H20: =SUMIFS($J$36:$J$58,$G$36:$G$58,2024,$H$36:$H$58,8,$K$36:$K$58,"Y") -> 0 | I20: =SUMIFS($J$36:$J$58,$G$36:$G$58,2024,$H$36:$H$58,9,$K$36:$K$58,"Y") -> 15779500 | J20: =SUMIFS($J$36:$J$58,$G$36:$G$58,2024,$H$36:$H$58,10,$K$36:$K$58,"Y") -> 37620000 | K20: =SUMIFS($J$36:$J$58,$G$36:$G$58,2024,$H$36:$H$58,11,$K$36:$K$58,"Y") -> 9075000 | L20: =SUMIFS($J$36:$J$58,$G$36:$G$58,2024,$H$36:$H$58,12,$K$36:$K$58,"Y") -> 0
A22: 2025 | B22: =SUM(A24:L24) -> 117877100
A23: 01 | B23: 02 | C23: 03 | D23: 04 | E23: 05 | F23: 06 | G23: 07 | H23: 08 | I23: 09 | J23: 10 | K23: 11 | L23: 12
A24: =SUMIFS($J$36:$J$58,$G$36:$G$58,2025,$H$36:$H$58,1,$K$36:$K$58,"Y") -> 50160000 | B24: =SUMIFS($J$36:$J$58,$G$36:$G$58,2025,$H$36:$H$58,2,$K$36:$K$58,"Y") -> 0 | C24: =SUMIFS($J$36:$J$58,$G$36:$G$58,2025,$H$36:$H$58,3,$K$36:$K$58,"Y") -> 0 | D24: =SUMIFS($J$36:$J$58,$G$36:$G$58,2025,$H$36:$H$58,4,$K$36:$K$58,"Y") -> 23650000 | E24: =SUMIFS($J$36:$J$58,$G$36:$G$58,2025,$H$36:$H$58,5,$K$36:$K$58,"Y") -> 0 | F24: =SUMIFS($J$36:$J$58,$G$36:$G$58,2025,$H$36:$H$58,6,$K$36:$K$58,"Y") -> 0 | G24: =SUMIFS($J$36:$J$58,$G$36:$G$58,2025,$H$36:$H$58,7,$K$36:$K$58,"Y") -> 0 | H24: =SUMIFS($J$36:$J$58,$G$36:$G$58,2025,$H$36:$H$58,8,$K$36:$K$58,"Y") -> 0 | I24: =SUMIFS($J$36:$J$58,$G$36:$G$58,2025,$H$36:$H$58,9,$K$36:$K$58,"Y") -> 0 | J24: =SUMIFS($J$36:$J$58,$G$36:$G$58,2025,$H$36:$H$58,10,$K$36:$K$58,"Y") -> 0 | K24: =SUMIFS($J$36:$J$58,$G$36:$G$58,2025,$H$36:$H$58,11,$K$36:$K$58,"Y") -> 19212600 | L24: =SUMIFS($J$36:$J$58,$G$36:$G$58,2025,$H$36:$H$58,12,$K$36:$K$58,"Y") -> 24854500
A26: 2026 | B26: =SUM(A28:L28) -> 8976000
A27: 01 | B27: 02 | C27: 03 | D27: 04 | E27: 05 | F27: 06 | G27: 07 | H27: 08 | I27: 09 | J27: 10 | K27: 11 | L27: 12
A28: =SUMIFS($J$36:$J$58,$G$36:$G$58,2026,$H$36:$H$58,1,$K$36:$K$58,"Y") -> 0 | B28: =SUMIFS($J$36:$J$58,$G$36:$G$58,2026,$H$36:$H$58,2,$K$36:$K$58,"Y") -> 8976000 | C28: =SUMIFS($J$36:$J$58,$G$36:$G$58,2026,$H$36:$H$58,3,$K$36:$K$58,"Y") -> 0 | D28: =SUMIFS($J$36:$J$58,$G$36:$G$58,2026,$H$36:$H$58,4,$K$36:$K$58,"Y") -> 0 | E28: =SUMIFS($J$36:$J$58,$G$36:$G$58,2026,$H$36:$H$58,5,$K$36:$K$58,"Y") -> 0 | F28: =SUMIFS($J$36:$J$58,$G$36:$G$58,2026,$H$36:$H$58,6,$K$36:$K$58,"Y") -> 0 | G28: =SUMIFS($J$36:$J$58,$G$36:$G$58,2026,$H$36:$H$58,7,$K$36:$K$58,"Y") -> 0 | H28: =SUMIFS($J$36:$J$58,$G$36:$G$58,2026,$H$36:$H$58,8,$K$36:$K$58,"Y") -> 0 | I28: =SUMIFS($J$36:$J$58,$G$36:$G$58,2026,$H$36:$H$58,9,$K$36:$K$58,"Y") -> 0 | J28: =SUMIFS($J$36:$J$58,$G$36:$G$58,2026,$H$36:$H$58,10,$K$36:$K$58,"Y") -> 0 | K28: =SUMIFS($J$36:$J$58,$G$36:$G$58,2026,$H$36:$H$58,11,$K$36:$K$58,"Y") -> 0 | L28: =SUMIFS($J$36:$J$58,$G$36:$G$58,2026,$H$36:$H$58,12,$K$36:$K$58,"Y") -> 0
A30: 2027 | B30: =SUM(A32:L32) -> 0
A31: 01 | B31: 02 | C31: 03 | D31: 04 | E31: 05 | F31: 06 | G31: 07 | H31: 08 | I31: 09 | J31: 10 | K31: 11 | L31: 12
A32: =SUMIFS($J$36:$J$58,$G$36:$G$58,2027,$H$36:$H$58,1,$K$36:$K$58,"Y") -> 0 | B32: =SUMIFS($J$36:$J$58,$G$36:$G$58,2027,$H$36:$H$58,2,$K$36:$K$58,"Y") -> 0 | C32: =SUMIFS($J$36:$J$58,$G$36:$G$58,2027,$H$36:$H$58,3,$K$36:$K$58,"Y") -> 0 | D32: =SUMIFS($J$36:$J$58,$G$36:$G$58,2027,$H$36:$H$58,4,$K$36:$K$58,"Y") -> 0 | E32: =SUMIFS($J$36:$J$58,$G$36:$G$58,2027,$H$36:$H$58,5,$K$36:$K$58,"Y") -> 0 | F32: =SUMIFS($J$36:$J$58,$G$36:$G$58,2027,$H$36:$H$58,6,$K$36:$K$58,"Y") -> 0 | G32: =SUMIFS($J$36:$J$58,$G$36:$G$58,2027,$H$36:$H$58,7,$K$36:$K$58,"Y") -> 0 | H32: =SUMIFS($J$36:$J$58,$G$36:$G$58,2027,$H$36:$H$58,8,$K$36:$K$58,"Y") -> 0 | I32: =SUMIFS($J$36:$J$58,$G$36:$G$58,2027,$H$36:$H$58,9,$K$36:$K$58,"Y") -> 0 | J32: =SUMIFS($J$36:$J$58,$G$36:$G$58,2027,$H$36:$H$58,10,$K$36:$K$58,"Y") -> 0 | K32: =SUMIFS($J$36:$J$58,$G$36:$G$58,2027,$H$36:$H$58,11,$K$36:$K$58,"Y") -> 0 | L32: =SUMIFS($J$36:$J$58,$G$36:$G$58,2027,$H$36:$H$58,12,$K$36:$K$58,"Y") -> 0
A34: 3. Costs Details
A35: Contract # | B35: Milestones | C35: Budget Amount(₩) VAT제외 | D35: Invoiced Amount(₩) | E35: Invoice # | F35: Invoiced Date | G35: Paid Year | H35: Paid Month | I35: Paid Date | J35: Total Amount(₩) VAT 포함 | K35: Paid (Y) | L35: 지출결의 #
A36: AIMS-SA-033.v4_20231006 | B36: CTA FE | C36: =43000000*50% -> 21500000 | D36: 23650000 | E36: 23SLJ01-01 | F36: 45209 | G36: 2023 | H36: 10 | I36: 45218 | J36: 23650000 | K36: Y | L36: CO23-198
A37: AIMS-SA-033.v4_20231006 | B37: 업무 완료 | C37: =43000000*50% -> 21500000 | D37: 23650000 | E37: 23SLJ01-01 | F37: 45723 | G37: 2025 | H37: 4 | I37: 45764 | J37: 23650000 | K37: Y | L37: CO25-067
A38: AIMS-SA-033.v4_20240626 | B38: CTA FE | C38: =114000000*30% -> 34200000 | D38: 37620000 | E38: 23SLJ01-03 | F38: 45471 | G38: 2024 | H38: 7 | I38: 45484 | J38: 37620000 | K38: Y | L38: CO24-123
A39: AIMS-SA-033.v4_20240626 | B39: 성과물 전달 | C39: =114000000*30% -> 34200000 | D39: 37620000 | E39: 23SLJ01-03 | F39: 45561 | G39: 2024 | H39: 10 | I39: 45575 | J39: 37620000 | K39: Y | L39: CO24-190
A40: AIMS-SA-033.v4_20240626 | B40: 업무 완료 | C40: =114000000*40% -> 45600000 | D40: 50160000 | E40: 23SLJ01-03 | F40: 45672 | G40: 2025 | H40: 1 | I40: 45680 | J40: 50160000 | K40: Y | L40: CO25-014
A41: AIMS-SA-033.v4_20240909 | B41: CTA FE | C41: 14345000 | D41: 15779500 | E41: 23SLJ01-04 | F41: 45546 | G41: 2024 | H41: 9 | I41: 45561 | J41: 15779500 | K41: Y | L41: CO24-179
A42: AIMS-SA-033.v4_20240909 | B42: 업무 완료 | C42: 14345000 | D42: 15779500 | E42: 23SLJ01-04 | F42: 45968 | G42: 2025 | H42: 12 | I42: 46009 | J42: 15779500 | K42: Y | L42: CO125-021
A43: AIMS-SA-033.v4_20241021 | B43: CTA FE | C43: =12180000*50% -> 6090000
A44: AIMS-SA-033.v4_20241021 | B44: 업무 완료 | C44: =12180000*50% -> 6090000
A45: AIMS-SA-033.v4_20241103 | B45: CTA FE | C45: 8250000 | D45: 9075000 | E45: 23SLJ01-06 | F45: 45602 | G45: 2024 | H45: 11 | I45: 45624 | J45: 9075000 | K45: Y | L45: CO24-253
A46: AIMS-SA-033.v4_20241103 | B46: 업무 완료 | C46: 8250000 | D46: 9075000 | E46: 23SLJ01-06 | F46: 45968 | G46: 2025 | H46: 12 | I46: 46009 | J46: 9075000 | K46: Y | L46: CO125-022
A47: AIMS-SA-033.v4_20250828 | B47: CTA FE | C47: =72300000*20% -> 14460000
A48: AIMS-SA-033.v4_20250828 | B48: NCA 기반 작업 제출 및 승인 | C48: =72300000*30% -> 21690000
A49: AIMS-SA-033.v4_20250828 | B49: 중간 분석 완료 (4unit, 10cohorts 기준) | C49: =72300000*30% -> 21690000
A50: AIMS-SA-033.v4_20250828 | B50: 최종 분석 완료 (2unit, 4 cohorts 기준) | C50: =72300000*20% -> 14460000
A51: AIMS-SA-033.v4_20251107 | B51: CTA FE | C51: 17466000 | D51: 19212600 | E51: SLJ01-25-03 | F51: 45981 | G51: 2025 | H51: 11 | I51: 45988 | J51: 19212600 | K51: Y | L51: CO125-007
A52: AIMS-SA-033.v4_20251107 | B52: 중간 분석 (5 cohorts) | C52: 29561000 | E52: SLJ01-25-03
A53: AIMS-SA-033.v4_20251107 | B53: 분석 reconcile, 업무완료 | C53: 25273000 | E53: SLJ01-25-03
A54: AIMS-SA-033.v4_20260126 | B54: 계약변경합의서 승인 | C54: 8160000 | D54: 8976000 | E54: SLJ01-25-03-C02 | F54: 46051 | G54: 2026 | H54: 2 | I54: 46058 | J54: 8976000 | K54: Y | L54: CO126-011
B59: Total | C59: =SUM(C36:C58) -> 367130000

Sheet 11. Cytel
A1: 11. Cytel
B2: Contract Number: | D2: Version & date:
A4: Protocol No: TTK-CS-101 | D4: Updated on:
A6: 1. Total Payment Status
A7: Category | B7: $ | C7: %
A8: Budget | B8: =D39 -> 0
A9: Paid | B9: =B14+B19+B24 -> 0 | C9: =B9/B8 -> #DIV/0!
A10: Remaining | B10: =B8-B9 -> 0 | C10: =B10/B8 -> #DIV/0!
A12: 2. Yearly and Monthly Payment
B13: USD | C13: KRW
A14: 2025 | B14: =SUM(A16:L16) -> 0 | C14: =SUM(A17:L17) -> 0
A15: 01 | B15: 02 | C15: 03 | D15: 04 | E15: 05 | F15: 06 | G15: 07 | H15: 08 | I15: 09 | J15: 10 | K15: 11 | L15: 12
A16: =SUMIFS($E$31:$E$38,$H$31:$H$38,2025,$I$31:$I$38,1,$L$31:$L$38,"Y") -> 0 | B16: =SUMIFS($E$31:$E$38,$H$31:$H$38,2025,$I$31:$I$38,2,$L$31:$L$38,"Y") -> 0 | C16: =SUMIFS($E$31:$E$38,$H$31:$H$38,2025,$I$31:$I$38,3,$L$31:$L$38,"Y") -> 0 | D16: =SUMIFS($E$31:$E$38,$H$31:$H$38,2025,$I$31:$I$38,4,$L$31:$L$38,"Y") -> 0 | E16: =SUMIFS($E$31:$E$38,$H$31:$H$38,2025,$I$31:$I$38,5,$L$31:$L$38,"Y") -> 0 | F16: =SUMIFS($E$31:$E$38,$H$31:$H$38,2025,$I$31:$I$38,6,$L$31:$L$38,"Y") -> 0 | G16: =SUMIFS($E$31:$E$38,$H$31:$H$38,2025,$I$31:$I$38,7,$L$31:$L$38,"Y") -> 0 | H16: =SUMIFS($E$31:$E$38,$H$31:$H$38,2025,$I$31:$I$38,8,$L$31:$L$38,"Y") -> 0 | I16: =SUMIFS($E$31:$E$38,$H$31:$H$38,2025,$I$31:$I$38,9,$L$31:$L$38,"Y") -> 0 | J16: =SUMIFS($E$31:$E$38,$H$31:$H$38,2025,$I$31:$I$38,10,$L$31:$L$38,"Y") -> 0 | K16: =SUMIFS($E$31:$E$38,$H$31:$H$38,2025,$I$31:$I$38,11,$L$31:$L$38,"Y") -> 0 | L16: =SUMIFS($E$31:$E$38,$H$31:$H$38,2025,$I$31:$I$38,12,$L$31:$L$38,"Y") -> 0
A17: =SUMIFS($K$31:$K$38,$H$31:$H$38,2025,$I$31:$I$38,1,$L$31:$L$38,"Y") -> 0 | B17: =SUMIFS($K$31:$K$38,$H$31:$H$38,2025,$I$31:$I$38,2,$L$31:$L$38,"Y") -> 0 | C17: =SUMIFS($K$31:$K$38,$H$31:$H$38,2025,$I$31:$I$38,3,$L$31:$L$38,"Y") -> 0 | D17: =SUMIFS($K$31:$K$38,$H$31:$H$38,2025,$I$31:$I$38,4,$L$31:$L$38,"Y") -> 0 | E17: =SUMIFS($K$31:$K$38,$H$31:$H$38,2025,$I$31:$I$38,5,$L$31:$L$38,"Y") -> 0 | F17: =SUMIFS($K$31:$K$38,$H$31:$H$38,2025,$I$31:$I$38,6,$L$31:$L$38,"Y") -> 0 | G17: =SUMIFS($K$31:$K$38,$H$31:$H$38,2025,$I$31:$I$38,7,$L$31:$L$38,"Y") -> 0 | H17: =SUMIFS($K$31:$K$38,$H$31:$H$38,2025,$I$31:$I$38,8,$L$31:$L$38,"Y") -> 0 | I17: =SUMIFS($K$31:$K$38,$H$31:$H$38,2025,$I$31:$I$38,9,$L$31:$L$38,"Y") -> 0 | J17: =SUMIFS($K$31:$K$38,$H$31:$H$38,2025,$I$31:$I$38,10,$L$31:$L$38,"Y") -> 0 | K17: =SUMIFS($K$31:$K$38,$H$31:$H$38,2025,$I$31:$I$38,11,$L$31:$L$38,"Y") -> 0 | L17: =SUMIFS($K$31:$K$38,$H$31:$H$38,2025,$I$31:$I$38,12,$L$31:$L$38,"Y") -> 0
A19: 2026 | B19: =SUM(A21:L21) -> 0 | C19: =SUM(A22:L22) -> 0
A20: 01 | B20: 02 | C20: 03 | D20: 04 | E20: 05 | F20: 06 | G20: 07 | H20: 08 | I20: 09 | J20: 10 | K20: 11 | L20: 12
A21: =SUMIFS($E$31:$E$38,$H$31:$H$38,2026,$I$31:$I$38,1,$L$31:$L$38,"Y") -> 0 | B21: =SUMIFS($E$31:$E$38,$H$31:$H$38,2026,$I$31:$I$38,2,$L$31:$L$38,"Y") -> 0 | C21: =SUMIFS($E$31:$E$38,$H$31:$H$38,2026,$I$31:$I$38,3,$L$31:$L$38,"Y") -> 0 | D21: =SUMIFS($E$31:$E$38,$H$31:$H$38,2026,$I$31:$I$38,4,$L$31:$L$38,"Y") -> 0 | E21: =SUMIFS($E$31:$E$38,$H$31:$H$38,2026,$I$31:$I$38,5,$L$31:$L$38,"Y") -> 0 | F21: =SUMIFS($E$31:$E$38,$H$31:$H$38,2026,$I$31:$I$38,6,$L$31:$L$38,"Y") -> 0 | G21: =SUMIFS($E$31:$E$38,$H$31:$H$38,2026,$I$31:$I$38,7,$L$31:$L$38,"Y") -> 0 | H21: =SUMIFS($E$31:$E$38,$H$31:$H$38,2026,$I$31:$I$38,8,$L$31:$L$38,"Y") -> 0 | I21: =SUMIFS($E$31:$E$38,$H$31:$H$38,2026,$I$31:$I$38,9,$L$31:$L$38,"Y") -> 0 | J21: =SUMIFS($E$31:$E$38,$H$31:$H$38,2026,$I$31:$I$38,10,$L$31:$L$38,"Y") -> 0 | K21: =SUMIFS($E$31:$E$38,$H$31:$H$38,2026,$I$31:$I$38,11,$L$31:$L$38,"Y") -> 0 | L21: =SUMIFS($E$31:$E$38,$H$31:$H$38,2026,$I$31:$I$38,12,$L$31:$L$38,"Y") -> 0
A22: =SUMIFS($K$31:$K$38,$H$31:$H$38,2026,$I$31:$I$38,1,$L$31:$L$38,"Y") -> 0 | B22: =SUMIFS($K$31:$K$38,$H$31:$H$38,2026,$I$31:$I$38,2,$L$31:$L$38,"Y") -> 0 | C22: =SUMIFS($K$31:$K$38,$H$31:$H$38,2026,$I$31:$I$38,3,$L$31:$L$38,"Y") -> 0 | D22: =SUMIFS($K$31:$K$38,$H$31:$H$38,2026,$I$31:$I$38,4,$L$31:$L$38,"Y") -> 0 | E22: =SUMIFS($K$31:$K$38,$H$31:$H$38,2026,$I$31:$I$38,5,$L$31:$L$38,"Y") -> 0 | F22: =SUMIFS($K$31:$K$38,$H$31:$H$38,2026,$I$31:$I$38,6,$L$31:$L$38,"Y") -> 0 | G22: =SUMIFS($K$31:$K$38,$H$31:$H$38,2026,$I$31:$I$38,7,$L$31:$L$38,"Y") -> 0 | H22: =SUMIFS($K$31:$K$38,$H$31:$H$38,2026,$I$31:$I$38,8,$L$31:$L$38,"Y") -> 0 | I22: =SUMIFS($K$31:$K$38,$H$31:$H$38,2026,$I$31:$I$38,9,$L$31:$L$38,"Y") -> 0 | J22: =SUMIFS($K$31:$K$38,$H$31:$H$38,2026,$I$31:$I$38,10,$L$31:$L$38,"Y") -> 0 | K22: =SUMIFS($K$31:$K$38,$H$31:$H$38,2026,$I$31:$I$38,11,$L$31:$L$38,"Y") -> 0 | L22: =SUMIFS($K$31:$K$38,$H$31:$H$38,2026,$I$31:$I$38,12,$L$31:$L$38,"Y") -> 0
A24: 2027 | B24: =SUM(A26:L26) -> 0 | C24: =SUM(A27:L27) -> 0
A25: 01 | B25: 02 | C25: 03 | D25: 04 | E25: 05 | F25: 06 | G25: 07 | H25: 08 | I25: 09 | J25: 10 | K25: 11 | L25: 12
A26: =SUMIFS($E$31:$E$38,$H$31:$H$38,2027,$I$31:$I$38,1,$L$31:$L$38,"Y") -> 0 | B26: =SUMIFS($E$31:$E$38,$H$31:$H$38,2027,$I$31:$I$38,2,$L$31:$L$38,"Y") -> 0 | C26: =SUMIFS($E$31:$E$38,$H$31:$H$38,2027,$I$31:$I$38,3,$L$31:$L$38,"Y") -> 0 | D26: =SUMIFS($E$31:$E$38,$H$31:$H$38,2027,$I$31:$I$38,4,$L$31:$L$38,"Y") -> 0 | E26: =SUMIFS($E$31:$E$38,$H$31:$H$38,2027,$I$31:$I$38,5,$L$31:$L$38,"Y") -> 0 | F26: =SUMIFS($E$31:$E$38,$H$31:$H$38,2027,$I$31:$I$38,6,$L$31:$L$38,"Y") -> 0 | G26: =SUMIFS($E$31:$E$38,$H$31:$H$38,2027,$I$31:$I$38,7,$L$31:$L$38,"Y") -> 0 | H26: =SUMIFS($E$31:$E$38,$H$31:$H$38,2027,$I$31:$I$38,8,$L$31:$L$38,"Y") -> 0 | I26: =SUMIFS($E$31:$E$38,$H$31:$H$38,2027,$I$31:$I$38,9,$L$31:$L$38,"Y") -> 0 | J26: =SUMIFS($E$31:$E$38,$H$31:$H$38,2027,$I$31:$I$38,10,$L$31:$L$38,"Y") -> 0 | K26: =SUMIFS($E$31:$E$38,$H$31:$H$38,2027,$I$31:$I$38,11,$L$31:$L$38,"Y") -> 0 | L26: =SUMIFS($E$31:$E$38,$H$31:$H$38,2027,$I$31:$I$38,12,$L$31:$L$38,"Y") -> 0
A27: =SUMIFS($K$31:$K$38,$H$31:$H$38,2027,$I$31:$I$38,1,$L$31:$L$38,"Y") -> 0 | B27: =SUMIFS($K$31:$K$38,$H$31:$H$38,2027,$I$31:$I$38,2,$L$31:$L$38,"Y") -> 0 | C27: =SUMIFS($K$31:$K$38,$H$31:$H$38,2027,$I$31:$I$38,3,$L$31:$L$38,"Y") -> 0 | D27: =SUMIFS($K$31:$K$38,$H$31:$H$38,2027,$I$31:$I$38,4,$L$31:$L$38,"Y") -> 0 | E27: =SUMIFS($K$31:$K$38,$H$31:$H$38,2027,$I$31:$I$38,5,$L$31:$L$38,"Y") -> 0 | F27: =SUMIFS($K$31:$K$38,$H$31:$H$38,2027,$I$31:$I$38,6,$L$31:$L$38,"Y") -> 0 | G27: =SUMIFS($K$31:$K$38,$H$31:$H$38,2027,$I$31:$I$38,7,$L$31:$L$38,"Y") -> 0 | H27: =SUMIFS($K$31:$K$38,$H$31:$H$38,2027,$I$31:$I$38,8,$L$31:$L$38,"Y") -> 0 | I27: =SUMIFS($K$31:$K$38,$H$31:$H$38,2027,$I$31:$I$38,9,$L$31:$L$38,"Y") -> 0 | J27: =SUMIFS($K$31:$K$38,$H$31:$H$38,2027,$I$31:$I$38,10,$L$31:$L$38,"Y") -> 0 | K27: =SUMIFS($K$31:$K$38,$H$31:$H$38,2027,$I$31:$I$38,11,$L$31:$L$38,"Y") -> 0 | L27: =SUMIFS($K$31:$K$38,$H$31:$H$38,2027,$I$31:$I$38,12,$L$31:$L$38,"Y") -> 0
A29: 3. Costs Details
A30: Contract # | B30: Milestones | C30: Budget Amount($) | D30: Invoiced Amount($) | E30: Invoice # | F30: Invoiced Date | G30: Paid Year | H30: Paid Month | I30: Paid Date | J30: Total Amount(($) | K30: Paid (Y) | L30: 지출결의 #
B52: Total | C52: =SUM(C31:C51) -> 0
